Workbook

Sheet Portada
B2: BASE DE DATOS TÉCNICA — SACI (INTRUSIÓN) Y SADI (DETECCIÓN DE INCENDIOS)
B3: Plantilla editable · 34 marcas · 32 tipos de dispositivo · 5 variantes por tipo · 8 categorías de equipamiento común · Precios en USD
B5: 34 | C5: 32 | D5: =COUNTA('Base de Datos SACI'!$G$5:$G$1076) -> 1072 | E5: =COUNTA('Base de Datos SADI'!$G$5:$G$716) -> 712 | F5: 8 | G5: =COUNTA(Equipamiento!$F$5:$F$72) -> 68
B6: Marcas (SACI + SADI) | C6: Tipos de dispositivo | D6: Modelos SACI | E6: Modelos SADI | F6: Categorías de equipo | G6: Equipos registrados
B9: Hoja | C9: Contenido
B10: =HYPERLINK("#'Resumen'!B2","Resumen") -> Resumen | C10: Cobertura marca × tipo (SACI y SADI), estadísticas de precios y equipamiento
B11: =HYPERLINK("#'Base de Datos SACI'!B2","Base de Datos SACI") -> Base de Datos SACI | C11: Hoja maestra SACI: 1072 registros (5 variantes por tipo y marca) filtrables
B12: =HYPERLINK("#'Base de Datos SADI'!B2","Base de Datos SADI") -> Base de Datos SADI | C12: Hoja maestra SADI: 712 registros (5 variantes por tipo y marca) filtrables
B13: =HYPERLINK("#'Equipamiento'!B2","Equipamiento") -> Equipamiento | C13: Baterías, fuentes, gabinetes, cableado, herramientas, monitoreo, accesorios y protección
B14: =HYPERLINK("#'Comparativa'!B2","Comparativa") -> Comparativa | C14: Fichas comparativas por tipo (modelo premium / medio / económico)
B15: =HYPERLINK("#'Lista de Precios'!B2","Lista de Precios") -> Lista de Precios | C15: Cotización integral: A SACI + B SADI + C equipamiento, con TOTAL GENERAL
B16: Niveles de marca incluidos
B17: Nivel | C17: Marcas | D17: Enfoque
B18: Alta | C18: Honeywell Security · DSC · Paradox · Bosch Security · Ajax Systems · Visonic · Texecom · Risco · Optex · Siemens · Honeywell Fire · Siemens · Bosch Fire · Edwards (EST) · Simplex (JCI) · Apollo Fire Detectors · Hochiki · Gent (Honeywell) · Xtralis (Honeywell) · Det-Tronics · Fire Sentry (Honeywell) | D18: Fabricantes premium con certificaciones UL/EN y soporte profesional
B19: Media | C19: Crow · Jablotron · Satel · Pyronix (Hikvision) · Hikvision · Qolsys · Morley-IAS (Honeywell) · System Sensor · GST · Fire-Lite (Honeywell) | D19: Relación calidad/precio sólida para proyectos estándar
B20: Entrada | C20: ELDES · Chuango · Zeta Alarm Systems | D20: Opciones económicas para proyectos con presupuesto ajustado
B23: Notas de uso
B24: 1. Las especificaciones y precios son referenciales (USD, mercado 2026); verifique siempre la ficha técnica vigente del fabricante antes de cotizar o instalar.
B25: 2. SACI = Sistemas de Alarma Contra Intrusos (paneles, PIR, contactos, ruptura de vidrio, sirenas, comunicadores, perimetrales, botones de pánico y mandos). SADI = Sistemas de Detección de Incendios (centrales, detectores, estaciones, notificación, módulos de monitoreo/control, terminales repetidoras).
B26: 3. Filas «No disponible en portafolio» (marcadas en gris): la marca no fabrica ese tipo de dispositivo; en Observaciones se sugiere el equivalente de otra marca compatible.
B27: 4. Certificaciones de referencia: SACI — UL 1023/1610, EN 50131 grado 2; SADI — UL 864, EN 54 (partes 2/4/5/7/11/17/20), FM, NFPA 72. Respete la normativa local (NMX, RETIE, etc.).
B28: 5. Use los filtros de la fila de encabezados en las hojas de Base de Datos (panel congelado en H5) y Equipamiento (G5) para segmentar por marca, tipo, nivel o precio.
B29: 6. En Lista de Precios, complete Cantidad y Descuento en las secciones A/B/C; los subtotales y el TOTAL GENERAL se calculan automáticamente.
B30: 7. Las columnas Proveedor y Stock están listas para registrar sus distribuidores locales (listas desplegables en Nivel, Stock y Categoría).
B31: 8. Hoja Comparativa: fichas de los 32 tipos con modelos de referencia por nivel (alto / medio / económico); Aspiración (ASD) incluye 2 especialistas (Xtralis y Honeywell FAAST).
B32: 9. Columnas estructuradas para motor de cálculo (Y en adelante en ambas BD, S en adelante en Equipamiento): consumos en A, tensiones en V, coberturas (m²/m/grados), alturas de montaje, potencia acústica, zonas/particiones/lazos/puntos, sección-ampacidad de cables. Unidades SI; los campos no aplicables a un tipo de equipo quedan como «N/A»; valores referenciales editables.

Sheet Resumen
B2: Resumen — Cobertura Marca × Tipo y Estadísticas de Precios
B5: Tipo de Dispositivo \ Marca | C5: Honeywell Security | D5: DSC | E5: Paradox | F5: Bosch Security | G5: Ajax Systems | H5: Visonic | I5: Texecom | J5: Risco | K5: Crow | L5: Jablotron | M5: Satel | N5: Pyronix (Hikvision) | O5: Hikvision | P5: Qolsys | Q5: ELDES | R5: Chuango | S5: Optex | T5: Siemens | U5: Total
B6: Panel híbrido | C6: =COUNTIFS('Base de Datos SACI'!$C$5:$C$1076,C$5,'Base de Datos SACI'!$F$5:$F$1076,$B6,'Base de Datos SACI'!$G$5:$G$1076,"<>*No disponible*") -> 5 | D6: =COUNTIFS('Base de Datos SACI'!$C$5:$C$1076,D$5,'Base de Datos SACI'!$F$5:$F$1076,$B6,'Base de Datos SACI'!$G$5:$G$1076,"<>*No disponible*") -> 5 | E6: =COUNTIFS('Base de Datos SACI'!$C$5:$C$1076,E$5,'Base de Datos SACI'!$F$5:$F$1076,$B6,'Base de Datos SACI'!$G$5:$G$1076,"<>*No disponible*") -> 5 | F6: =COUNTIFS('Base de Datos SACI'!$C$5:$C$1076,F$5,'Base de Datos SACI'!$F$5:$F$1076,$B6,'Base de Datos SACI'!$G$5:$G$1076,"<>*No disponible*") -> 5 | G6: =COUNTIFS('Base de Datos SACI'!$C$5:$C$1076,G$5,'Base de Datos SACI'!$F$5:$F$1076,$B6,'Base de Datos SACI'!$G$5:$G$1076,"<>*No disponible*") -> 0 | H6: =COUNTIFS('Base de Datos SACI'!$C$5:$C$1076,H$5,'Base de Datos SACI'!$F$5:$F$1076,$B6,'Base de Datos SACI'!$G$5:$G$1076,"<>*No disponible*") -> 0 | I6: =COUNTIFS('Base de Datos SACI'!$C$5:$C$1076,I$5,'Base de Datos SACI'!$F$5:$F$1076,$B6,'Base de Datos SACI'!$G$5:$G$1076,"<>*No disponible*") -> 5 | J6: =COUNTIFS('Base de Datos SACI'!$C$5:$C$1076,J$5,'Base de Datos SACI'!$F$5:$F$1076,$B6,'Base de Datos SACI'!$G$5:$G$1076,"<>*No disponible*") -> 5 | ... T6: =COUNTIFS('Base de Datos SACI'!$C$5:$C$1076,T$5,'Base de Datos SACI'!$F$5:$F$1076,$B6,'Base de Datos SACI'!$G$5:$G$1076,"<>*No disponible*") -> 5 | U6: =SUM(C6:T6) -> 65
B7: Panel alámbrico | C7: =COUNTIFS('Base de Datos SACI'!$C$5:$C$1076,C$5,'Base de Datos SACI'!$F$5:$F$1076,$B7,'Base de Datos SACI'!$G$5:$G$1076,"<>*No disponible*") -> 5 | D7: =COUNTIFS('Base de Datos SACI'!$C$5:$C$1076,D$5,'Base de Datos SACI'!$F$5:$F$1076,$B7,'Base de Datos SACI'!$G$5:$G$1076,"<>*No disponible*") -> 5 | E7: =COUNTIFS('Base de Datos SACI'!$C$5:$C$1076,E$5,'Base de Datos SACI'!$F$5:$F$1076,$B7,'Base de Datos SACI'!$G$5:$G$1076,"<>*No disponible*") -> 5 | F7: =COUNTIFS('Base de Datos SACI'!$C$5:$C$1076,F$5,'Base de Datos SACI'!$F$5:$F$1076,$B7,'Base de Datos SACI'!$G$5:$G$1076,"<>*No disponible*") -> 5 | G7: =COUNTIFS('Base de Datos SACI'!$C$5:$C$1076,G$5,'Base de Datos SACI'!$F$5:$F$1076,$B7,'Base de Datos SACI'!$G$5:$G$1076,"<>*No disponible*") -> 0 | H7: =COUNTIFS('Base de Datos SACI'!$C$5:$C$1076,H$5,'Base de Datos SACI'!$F$5:$F$1076,$B7,'Base de Datos SACI'!$G$5:$G$1076,"<>*No disponible*") -> 0 | I7: =COUNTIFS('Base de Datos SACI'!$C$5:$C$1076,I$5,'Base de Datos SACI'!$F$5:$F$1076,$B7,'Base de Datos SACI'!$G$5:$G$1076,"<>*No disponible*") -> 5 | J7: =COUNTIFS('Base de Datos SACI'!$C$5:$C$1076,J$5,'Base de Datos SACI'!$F$5:$F$1076,$B7,'Base de Datos SACI'!$G$5:$G$1076,"<>*No disponible*") -> 0 | ... T7: =COUNTIFS('Base de Datos SACI'!$C$5:$C$1076,T$5,'Base de Datos SACI'!$F$5:$F$1076,$B7,'Base de Datos SACI'!$G$5:$G$1076,"<>*No disponible*") -> 0 | U7: =SUM(C7:T7) -> 45
B8: Panel inalámbrico / Hub | C8: =COUNTIFS('Base de Datos SACI'!$C$5:$C$1076,C$5,'Base de Datos SACI'!$F$5:$F$1076,$B8,'Base de Datos SACI'!$G$5:$G$1076,"<>*No disponible*") -> 5 | D8: =COUNTIFS('Base de Datos SACI'!$C$5:$C$1076,D$5,'Base de Datos SACI'!$F$5:$F$1076,$B8,'Base de Datos SACI'!$G$5:$G$1076,"<>*No disponible*") -> 5 | E8: =COUNTIFS('Base de Datos SACI'!$C$5:$C$1076,E$5,'Base de Datos SACI'!$F$5:$F$1076,$B8,'Base de Datos SACI'!$G$5:$G$1076,"<>*No disponible*") -> 5 | F8: =COUNTIFS('Base de Datos SACI'!$C$5:$C$1076,F$5,'Base de Datos SACI'!$F$5:$F$1076,$B8,'Base de Datos SACI'!$G$5:$G$1076,"<>*No disponible*") -> 5 | G8: =COUNTIFS('Base de Datos SACI'!$C$5:$C$1076,G$5,'Base de Datos SACI'!$F$5:$F$1076,$B8,'Base de Datos SACI'!$G$5:$G$1076,"<>*No disponible*") -> 5 | H8: =COUNTIFS('Base de Datos SACI'!$C$5:$C$1076,H$5,'Base de Datos SACI'!$F$5:$F$1076,$B8,'Base de Datos SACI'!$G$5:$G$1076,"<>*No disponible*") -> 5 | I8: =COUNTIFS('Base de Datos SACI'!$C$5:$C$1076,I$5,'Base de Datos SACI'!$F$5:$F$1076,$B8,'Base de Datos SACI'!$G$5:$G$1076,"<>*No disponible*") -> 0 | J8: =COUNTIFS('Base de Datos SACI'!$C$5:$C$1076,J$5,'Base de Datos SACI'!$F$5:$F$1076,$B8,'Base de Datos SACI'!$G$5:$G$1076,"<>*No disponible*") -> 5 | ... T8: =COUNTIFS('Base de Datos SACI'!$C$5:$C$1076,T$5,'Base de Datos SACI'!$F$5:$F$1076,$B8,'Base de Datos SACI'!$G$5:$G$1076,"<>*No disponible*") -> 0 | U8: =SUM(C8:T8) -> 60
B9: Teclado de control | C9: =COUNTIFS('Base de Datos SACI'!$C$5:$C$1076,C$5,'Base de Datos SACI'!$F$5:$F$1076,$B9,'Base de Datos SACI'!$G$5:$G$1076,"<>*No disponible*") -> 5 | D9: =COUNTIFS('Base de Datos SACI'!$C$5:$C$1076,D$5,'Base de Datos SACI'!$F$5:$F$1076,$B9,'Base de Datos SACI'!$G$5:$G$1076,"<>*No disponible*") -> 5 | E9: =COUNTIFS('Base de Datos SACI'!$C$5:$C$1076,E$5,'Base de Datos SACI'!$F$5:$F$1076,$B9,'Base de Datos SACI'!$G$5:$G$1076,"<>*No disponible*") -> 5 | F9: =COUNTIFS('Base de Datos SACI'!$C$5:$C$1076,F$5,'Base de Datos SACI'!$F$5:$F$1076,$B9,'Base de Datos SACI'!$G$5:$G$1076,"<>*No disponible*") -> 5 | G9: =COUNTIFS('Base de Datos SACI'!$C$5:$C$1076,G$5,'Base de Datos SACI'!$F$5:$F$1076,$B9,'Base de Datos SACI'!$G$5:$G$1076,"<>*No disponible*") -> 5 | H9: =COUNTIFS('Base de Datos SACI'!$C$5:$C$1076,H$5,'Base de Datos SACI'!$F$5:$F$1076,$B9,'Base de Datos SACI'!$G$5:$G$1076,"<>*No disponible*") -> 5 | I9: =COUNTIFS('Base de Datos SACI'!$C$5:$C$1076,I$5,'Base de Datos SACI'!$F$5:$F$1076,$B9,'Base de Datos SACI'!$G$5:$G$1076,"<>*No disponible*") -> 5 | J9: =COUNTIFS('Base de Datos SACI'!$C$5:$C$1076,J$5,'Base de Datos SACI'!$F$5:$F$1076,$B9,'Base de Datos SACI'!$G$5:$G$1076,"<>*No disponible*") -> 5 | ... T9: =COUNTIFS('Base de Datos SACI'!$C$5:$C$1076,T$5,'Base de Datos SACI'!$F$5:$F$1076,$B9,'Base de Datos SACI'!$G$5:$G$1076,"<>*No disponible*") -> 5 | U9: =SUM(C9:T9) -> 85
B10: Detector PIR interior | C10: =COUNTIFS('Base de Datos SACI'!$C$5:$C$1076,C$5,'Base de Datos SACI'!$F$5:$F$1076,$B10,'Base de Datos SACI'!$G$5:$G$1076,"<>*No disponible*") -> 5 | D10: =COUNTIFS('Base de Datos SACI'!$C$5:$C$1076,D$5,'Base de Datos SACI'!$F$5:$F$1076,$B10,'Base de Datos SACI'!$G$5:$G$1076,"<>*No disponible*") -> 5 | E10: =COUNTIFS('Base de Datos SACI'!$C$5:$C$1076,E$5,'Base de Datos SACI'!$F$5:$F$1076,$B10,'Base de Datos SACI'!$G$5:$G$1076,"<>*No disponible*") -> 5 | F10: =COUNTIFS('Base de Datos SACI'!$C$5:$C$1076,F$5,'Base de Datos SACI'!$F$5:$F$1076,$B10,'Base de Datos SACI'!$G$5:$G$1076,"<>*No disponible*") -> 5 | G10: =COUNTIFS('Base de Datos SACI'!$C$5:$C$1076,G$5,'Base de Datos SACI'!$F$5:$F$1076,$B10,'Base de Datos SACI'!$G$5:$G$1076,"<>*No disponible*") -> 5 | H10: =COUNTIFS('Base de Datos SACI'!$C$5:$C$1076,H$5,'Base de Datos SACI'!$F$5:$F$1076,$B10,'Base de Datos SACI'!$G$5:$G$1076,"<>*No disponible*") -> 5 | I10: =COUNTIFS('Base de Datos SACI'!$C$5:$C$1076,I$5,'Base de Datos SACI'!$F$5:$F$1076,$B10,'Base de Datos SACI'!$G$5:$G$1076,"<>*No disponible*") -> 5 | J10: =COUNTIFS('Base de Datos SACI'!$C$5:$C$1076,J$5,'Base de Datos SACI'!$F$5:$F$1076,$B10,'Base de Datos SACI'!$G$5:$G$1076,"<>*No disponible*") -> 5 | ... T10: =COUNTIFS('Base de Datos SACI'!$C$5:$C$1076,T$5,'Base de Datos SACI'!$F$5:$F$1076,$B10,'Base de Datos SACI'!$G$5:$G$1076,"<>*No disponible*") -> 0 | U10: =SUM(C10:T10) -> 85
B11: PIR inalámbrico | C11: =COUNTIFS('Base de Datos SACI'!$C$5:$C$1076,C$5,'Base de Datos SACI'!$F$5:$F$1076,$B11,'Base de Datos SACI'!$G$5:$G$1076,"<>*No disponible*") -> 5 | D11: =COUNTIFS('Base de Datos SACI'!$C$5:$C$1076,D$5,'Base de Datos SACI'!$F$5:$F$1076,$B11,'Base de Datos SACI'!$G$5:$G$1076,"<>*No disponible*") -> 5 | E11: =COUNTIFS('Base de Datos SACI'!$C$5:$C$1076,E$5,'Base de Datos SACI'!$F$5:$F$1076,$B11,'Base de Datos SACI'!$G$5:$G$1076,"<>*No disponible*") -> 5 | F11: =COUNTIFS('Base de Datos SACI'!$C$5:$C$1076,F$5,'Base de Datos SACI'!$F$5:$F$1076,$B11,'Base de Datos SACI'!$G$5:$G$1076,"<>*No disponible*") -> 5 | G11: =COUNTIFS('Base de Datos SACI'!$C$5:$C$1076,G$5,'Base de Datos SACI'!$F$5:$F$1076,$B11,'Base de Datos SACI'!$G$5:$G$1076,"<>*No disponible*") -> 5 | H11: =COUNTIFS('Base de Datos SACI'!$C$5:$C$1076,H$5,'Base de Datos SACI'!$F$5:$F$1076,$B11,'Base de Datos SACI'!$G$5:$G$1076,"<>*No disponible*") -> 5 | I11: =COUNTIFS('Base de Datos SACI'!$C$5:$C$1076,I$5,'Base de Datos SACI'!$F$5:$F$1076,$B11,'Base de Datos SACI'!$G$5:$G$1076,"<>*No disponible*") -> 5 | J11: =COUNTIFS('Base de Datos SACI'!$C$5:$C$1076,J$5,'Base de Datos SACI'!$F$5:$F$1076,$B11,'Base de Datos SACI'!$G$5:$G$1076,"<>*No disponible*") -> 5 | ... T11: =COUNTIFS('Base de Datos SACI'!$C$5:$C$1076,T$5,'Base de Datos SACI'!$F$5:$F$1076,$B11,'Base de Datos SACI'!$G$5:$G$1076,"<>*No disponible*") -> 5 | U11: =SUM(C11:T11) -> 80
B12: Doble tecnología / exterior | C12: =COUNTIFS('Base de Datos SACI'!$C$5:$C$1076,C$5,'Base de Datos SACI'!$F$5:$F$1076,$B12,'Base de Datos SACI'!$G$5:$G$1076,"<>*No disponible*") -> 5 | D12: =COUNTIFS('Base de Datos SACI'!$C$5:$C$1076,D$5,'Base de Datos SACI'!$F$5:$F$1076,$B12,'Base de Datos SACI'!$G$5:$G$1076,"<>*No disponible*") -> 5 | E12: =COUNTIFS('Base de Datos SACI'!$C$5:$C$1076,E$5,'Base de Datos SACI'!$F$5:$F$1076,$B12,'Base de Datos SACI'!$G$5:$G$1076,"<>*No disponible*") -> 5 | F12: =COUNTIFS('Base de Datos SACI'!$C$5:$C$1076,F$5,'Base de Datos SACI'!$F$5:$F$1076,$B12,'Base de Datos SACI'!$G$5:$G$1076,"<>*No disponible*") -> 5 | G12: =COUNTIFS('Base de Datos SACI'!$C$5:$C$1076,G$5,'Base de Datos SACI'!$F$5:$F$1076,$B12,'Base de Datos SACI'!$G$5:$G$1076,"<>*No disponible*") -> 5 | H12: =COUNTIFS('Base de Datos SACI'!$C$5:$C$1076,H$5,'Base de Datos SACI'!$F$5:$F$1076,$B12,'Base de Datos SACI'!$G$5:$G$1076,"<>*No disponible*") -> 5 | I12: =COUNTIFS('Base de Datos SACI'!$C$5:$C$1076,I$5,'Base de Datos SACI'!$F$5:$F$1076,$B12,'Base de Datos SACI'!$G$5:$G$1076,"<>*No disponible*") -> 5 | J12: =COUNTIFS('Base de Datos SACI'!$C$5:$C$1076,J$5,'Base de Datos SACI'!$F$5:$F$1076,$B12,'Base de Datos SACI'!$G$5:$G$1076,"<>*No disponible*") -> 5 | ... T12: =COUNTIFS('Base de Datos SACI'!$C$5:$C$1076,T$5,'Base de Datos SACI'!$F$5:$F$1076,$B12,'Base de Datos SACI'!$G$5:$G$1076,"<>*No disponible*") -> 0 | U12: =SUM(C12:T12) -> 70
B13: Contacto magnético | C13: =COUNTIFS('Base de Datos SACI'!$C$5:$C$1076,C$5,'Base de Datos SACI'!$F$5:$F$1076,$B13,'Base de Datos SACI'!$G$5:$G$1076,"<>*No disponible*") -> 5 | D13: =COUNTIFS('Base de Datos SACI'!$C$5:$C$1076,D$5,'Base de Datos SACI'!$F$5:$F$1076,$B13,'Base de Datos SACI'!$G$5:$G$1076,"<>*No disponible*") -> 5 | E13: =COUNTIFS('Base de Datos SACI'!$C$5:$C$1076,E$5,'Base de Datos SACI'!$F$5:$F$1076,$B13,'Base de Datos SACI'!$G$5:$G$1076,"<>*No disponible*") -> 5 | F13: =COUNTIFS('Base de Datos SACI'!$C$5:$C$1076,F$5,'Base de Datos SACI'!$F$5:$F$1076,$B13,'Base de Datos SACI'!$G$5:$G$1076,"<>*No disponible*") -> 5 | G13: =COUNTIFS('Base de Datos SACI'!$C$5:$C$1076,G$5,'Base de Datos SACI'!$F$5:$F$1076,$B13,'Base de Datos SACI'!$G$5:$G$1076,"<>*No disponible*") -> 5 | H13: =COUNTIFS('Base de Datos SACI'!$C$5:$C$1076,H$5,'Base de Datos SACI'!$F$5:$F$1076,$B13,'Base de Datos SACI'!$G$5:$G$1076,"<>*No disponible*") -> 5 | I13: =COUNTIFS('Base de Datos SACI'!$C$5:$C$1076,I$5,'Base de Datos SACI'!$F$5:$F$1076,$B13,'Base de Datos SACI'!$G$5:$G$1076,"<>*No disponible*") -> 5 | J13: =COUNTIFS('Base de Datos SACI'!$C$5:$C$1076,J$5,'Base de Datos SACI'!$F$5:$F$1076,$B13,'Base de Datos SACI'!$G$5:$G$1076,"<>*No disponible*") -> 5 | ... T13: =COUNTIFS('Base de Datos SACI'!$C$5:$C$1076,T$5,'Base de Datos SACI'!$F$5:$F$1076,$B13,'Base de Datos SACI'!$G$5:$G$1076,"<>*No disponible*") -> 5 | U13: =SUM(C13:T13) -> 85
B14: Ruptura de vidrio | C14: =COUNTIFS('Base de Datos SACI'!$C$5:$C$1076,C$5,'Base de Datos SACI'!$F$5:$F$1076,$B14,'Base de Datos SACI'!$G$5:$G$1076,"<>*No disponible*") -> 5 | D14: =COUNTIFS('Base de Datos SACI'!$C$5:$C$1076,D$5,'Base de Datos SACI'!$F$5:$F$1076,$B14,'Base de Datos SACI'!$G$5:$G$1076,"<>*No disponible*") -> 5 | E14: =COUNTIFS('Base de Datos SACI'!$C$5:$C$1076,E$5,'Base de Datos SACI'!$F$5:$F$1076,$B14,'Base de Datos SACI'!$G$5:$G$1076,"<>*No disponible*") -> 5 | F14: =COUNTIFS('Base de Datos SACI'!$C$5:$C$1076,F$5,'Base de Datos SACI'!$F$5:$F$1076,$B14,'Base de Datos SACI'!$G$5:$G$1076,"<>*No disponible*") -> 5 | G14: =COUNTIFS('Base de Datos SACI'!$C$5:$C$1076,G$5,'Base de Datos SACI'!$F$5:$F$1076,$B14,'Base de Datos SACI'!$G$5:$G$1076,"<>*No disponible*") -> 5 | H14: =COUNTIFS('Base de Datos SACI'!$C$5:$C$1076,H$5,'Base de Datos SACI'!$F$5:$F$1076,$B14,'Base de Datos SACI'!$G$5:$G$1076,"<>*No disponible*") -> 5 | I14: =COUNTIFS('Base de Datos SACI'!$C$5:$C$1076,I$5,'Base de Datos SACI'!$F$5:$F$1076,$B14,'Base de Datos SACI'!$G$5:$G$1076,"<>*No disponible*") -> 0 | J14: =COUNTIFS('Base de Datos SACI'!$C$5:$C$1076,J$5,'Base de Datos SACI'!$F$5:$F$1076,$B14,'Base de Datos SACI'!$G$5:$G$1076,"<>*No disponible*") -> 0 | ... T14: =COUNTIFS('Base de Datos SACI'!$C$5:$C$1076,T$5,'Base de Datos SACI'!$F$5:$F$1076,$B14,'Base de Datos SACI'!$G$5:$G$1076,"<>*No disponible*") -> 5 | U14: =SUM(C14:T14) -> 40
B15: Sirena exterior | C15: =COUNTIFS('Base de Datos SACI'!$C$5:$C$1076,C$5,'Base de Datos SACI'!$F$5:$F$1076,$B15,'Base de Datos SACI'!$G$5:$G$1076,"<>*No disponible*") -> 5 | D15: =COUNTIFS('Base de Datos SACI'!$C$5:$C$1076,D$5,'Base de Datos SACI'!$F$5:$F$1076,$B15,'Base de Datos SACI'!$G$5:$G$1076,"<>*No disponible*") -> 5 | E15: =COUNTIFS('Base de Datos SACI'!$C$5:$C$1076,E$5,'Base de Datos SACI'!$F$5:$F$1076,$B15,'Base de Datos SACI'!$G$5:$G$1076,"<>*No disponible*") -> 5 | F15: =COUNTIFS('Base de Datos SACI'!$C$5:$C$1076,F$5,'Base de Datos SACI'!$F$5:$F$1076,$B15,'Base de Datos SACI'!$G$5:$G$1076,"<>*No disponible*") -> 5 | G15: =COUNTIFS('Base de Datos SACI'!$C$5:$C$1076,G$5,'Base de Datos SACI'!$F$5:$F$1076,$B15,'Base de Datos SACI'!$G$5:$G$1076,"<>*No disponible*") -> 5 | H15: =COUNTIFS('Base de Datos SACI'!$C$5:$C$1076,H$5,'Base de Datos SACI'!$F$5:$F$1076,$B15,'Base de Datos SACI'!$G$5:$G$1076,"<>*No disponible*") -> 5 | I15: =COUNTIFS('Base de Datos SACI'!$C$5:$C$1076,I$5,'Base de Datos SACI'!$F$5:$F$1076,$B15,'Base de Datos SACI'!$G$5:$G$1076,"<>*No disponible*") -> 5 | J15: =COUNTIFS('Base de Datos SACI'!$C$5:$C$1076,J$5,'Base de Datos SACI'!$F$5:$F$1076,$B15,'Base de Datos SACI'!$G$5:$G$1076,"<>*No disponible*") -> 5 | ... T15: =COUNTIFS('Base de Datos SACI'!$C$5:$C$1076,T$5,'Base de Datos SACI'!$F$5:$F$1076,$B15,'Base de Datos SACI'!$G$5:$G$1076,"<>*No disponible*") -> 5 | U15: =SUM(C15:T15) -> 80
B16: Sirena interior | C16: =COUNTIFS('Base de Datos SACI'!$C$5:$C$1076,C$5,'Base de Datos SACI'!$F$5:$F$1076,$B16,'Base de Datos SACI'!$G$5:$G$1076,"<>*No disponible*") -> 5 | D16: =COUNTIFS('Base de Datos SACI'!$C$5:$C$1076,D$5,'Base de Datos SACI'!$F$5:$F$1076,$B16,'Base de Datos SACI'!$G$5:$G$1076,"<>*No disponible*") -> 5 | E16: =COUNTIFS('Base de Datos SACI'!$C$5:$C$1076,E$5,'Base de Datos SACI'!$F$5:$F$1076,$B16,'Base de Datos SACI'!$G$5:$G$1076,"<>*No disponible*") -> 5 | F16: =COUNTIFS('Base de Datos SACI'!$C$5:$C$1076,F$5,'Base de Datos SACI'!$F$5:$F$1076,$B16,'Base de Datos SACI'!$G$5:$G$1076,"<>*No disponible*") -> 5 | G16: =COUNTIFS('Base de Datos SACI'!$C$5:$C$1076,G$5,'Base de Datos SACI'!$F$5:$F$1076,$B16,'Base de Datos SACI'!$G$5:$G$1076,"<>*No disponible*") -> 5 | H16: =COUNTIFS('Base de Datos SACI'!$C$5:$C$1076,H$5,'Base de Datos SACI'!$F$5:$F$1076,$B16,'Base de Datos SACI'!$G$5:$G$1076,"<>*No disponible*") -> 5 | I16: =COUNTIFS('Base de Datos SACI'!$C$5:$C$1076,I$5,'Base de Datos SACI'!$F$5:$F$1076,$B16,'Base de Datos SACI'!$G$5:$G$1076,"<>*No disponible*") -> 5 | J16: =COUNTIFS('Base de Datos SACI'!$C$5:$C$1076,J$5,'Base de Datos SACI'!$F$5:$F$1076,$B16,'Base de Datos SACI'!$G$5:$G$1076,"<>*No disponible*") -> 5 | ... T16: =COUNTIFS('Base de Datos SACI'!$C$5:$C$1076,T$5,'Base de Datos SACI'!$F$5:$F$1076,$B16,'Base de Datos SACI'!$G$5:$G$1076,"<>*No disponible*") -> 5 | U16: =SUM(C16:T16) -> 65
B17: Comunicador de eventos | C17: =COUNTIFS('Base de Datos SACI'!$C$5:$C$1076,C$5,'Base de Datos SACI'!$F$5:$F$1076,$B17,'Base de Datos SACI'!$G$5:$G$1076,"<>*No disponible*") -> 5 | D17: =COUNTIFS('Base de Datos SACI'!$C$5:$C$1076,D$5,'Base de Datos SACI'!$F$5:$F$1076,$B17,'Base de Datos SACI'!$G$5:$G$1076,"<>*No disponible*") -> 5 | E17: =COUNTIFS('Base de Datos SACI'!$C$5:$C$1076,E$5,'Base de Datos SACI'!$F$5:$F$1076,$B17,'Base de Datos SACI'!$G$5:$G$1076,"<>*No disponible*") -> 5 | F17: =COUNTIFS('Base de Datos SACI'!$C$5:$C$1076,F$5,'Base de Datos SACI'!$F$5:$F$1076,$B17,'Base de Datos SACI'!$G$5:$G$1076,"<>*No disponible*") -> 5 | G17: =COUNTIFS('Base de Datos SACI'!$C$5:$C$1076,G$5,'Base de Datos SACI'!$F$5:$F$1076,$B17,'Base de Datos SACI'!$G$5:$G$1076,"<>*No disponible*") -> 5 | H17: =COUNTIFS('Base de Datos SACI'!$C$5:$C$1076,H$5,'Base de Datos SACI'!$F$5:$F$1076,$B17,'Base de Datos SACI'!$G$5:$G$1076,"<>*No disponible*") -> 5 | I17: =COUNTIFS('Base de Datos SACI'!$C$5:$C$1076,I$5,'Base de Datos SACI'!$F$5:$F$1076,$B17,'Base de Datos SACI'!$G$5:$G$1076,"<>*No disponible*") -> 5 | J17: =COUNTIFS('Base de Datos SACI'!$C$5:$C$1076,J$5,'Base de Datos SACI'!$F$5:$F$1076,$B17,'Base de Datos SACI'!$G$5:$G$1076,"<>*No disponible*") -> 5 | ... T17: =COUNTIFS('Base de Datos SACI'!$C$5:$C$1076,T$5,'Base de Datos SACI'!$F$5:$F$1076,$B17,'Base de Datos SACI'!$G$5:$G$1076,"<>*No disponible*") -> 5 | U17: =SUM(C17:T17) -> 65
... B21: Mando inalámbrico | C21: =COUNTIFS('Base de Datos SACI'!$C$5:$C$1076,C$5,'Base de Datos SACI'!$F$5:$F$1076,$B21,'Base de Datos SACI'!$G$5:$G$1076,"<>*No disponible*") -> 5 | D21: =COUNTIFS('Base de Datos SACI'!$C$5:$C$1076,D$5,'Base de Datos SACI'!$F$5:$F$1076,$B21,'Base de Datos SACI'!$G$5:$G$1076,"<>*No disponible*") -> 5 | E21: =COUNTIFS('Base de Datos SACI'!$C$5:$C$1076,E$5,'Base de Datos SACI'!$F$5:$F$1076,$B21,'Base de Datos SACI'!$G$5:$G$1076,"<>*No disponible*") -> 5 | F21: =COUNTIFS('Base de Datos SACI'!$C$5:$C$1076,F$5,'Base de Datos SACI'!$F$5:$F$1076,$B21,'Base de Datos SACI'!$G$5:$G$1076,"<>*No disponible*") -> 0 | G21: =COUNTIFS('Base de Datos SACI'!$C$5:$C$1076,G$5,'Base de Datos SACI'!$F$5:$F$1076,$B21,'Base de Datos SACI'!$G$5:$G$1076,"<>*No disponible*") -> 5 | H21: =COUNTIFS('Base de Datos SACI'!$C$5:$C$1076,H$5,'Base de Datos SACI'!$F$5:$F$1076,$B21,'Base de Datos SACI'!$G$5:$G$1076,"<>*No disponible*") -> 5 | I21: =COUNTIFS('Base de Datos SACI'!$C$5:$C$1076,I$5,'Base de Datos SACI'!$F$5:$F$1076,$B21,'Base de Datos SACI'!$G$5:$G$1076,"<>*No disponible*") -> 5 | J21: =COUNTIFS('Base de Datos SACI'!$C$5:$C$1076,J$5,'Base de Datos SACI'!$F$5:$F$1076,$B21,'Base de Datos SACI'!$G$5:$G$1076,"<>*No disponible*") -> 0 | ... T21: =COUNTIFS('Base de Datos SACI'!$C$5:$C$1076,T$5,'Base de Datos SACI'!$F$5:$F$1076,$B21,'Base de Datos SACI'!$G$5:$G$1076,"<>*No disponible*") -> 5 | U21: =SUM(C21:T21) -> 50
B22: Modelos activos por marca | C22: =SUM(C6:C21) -> 75 | D22: =SUM(D6:D21) -> 75 | E22: =SUM(E6:E21) -> 70 | F22: =SUM(F6:F21) -> 65 | G22: =SUM(G6:G21) -> 65 | H22: =SUM(H6:H21) -> 65 | I22: =SUM(I6:I21) -> 60 | J22: =SUM(J6:J21) -> 60 | ... U22: =SUM(U6:U21) -> 980
B25: Cobertura SADI — Detectores y Centrales de Incendios
B26: Tipo de Dispositivo \ Marca | C26: Honeywell Fire | D26: Siemens | E26: Bosch Fire | F26: Edwards (EST) | G26: Simplex (JCI) | H26: Morley-IAS (Honeywell) | I26: Apollo Fire Detectors | J26: Hochiki | K26: System Sensor | L26: GST | M26: Fire-Lite (Honeywell) | N26: Zeta Alarm Systems | O26: Gent (Honeywell) | P26: Xtralis (Honeywell) | Q26: Det-Tronics | R26: Fire Sentry (Honeywell) | S26: Total
B27: Panel direccionable | C27: =COUNTIFS('Base de Datos SADI'!$C$5:$C$716,C$26,'Base de Datos SADI'!$F$5:$F$716,$B27,'Base de Datos SADI'!$G$5:$G$716,"<>*No disponible*") -> 5 | D27: =COUNTIFS('Base de Datos SADI'!$C$5:$C$716,D$26,'Base de Datos SADI'!$F$5:$F$716,$B27,'Base de Datos SADI'!$G$5:$G$716,"<>*No disponible*") -> 5 | E27: =COUNTIFS('Base de Datos SADI'!$C$5:$C$716,E$26,'Base de Datos SADI'!$F$5:$F$716,$B27,'Base de Datos SADI'!$G$5:$G$716,"<>*No disponible*") -> 5 | F27: =COUNTIFS('Base de Datos SADI'!$C$5:$C$716,F$26,'Base de Datos SADI'!$F$5:$F$716,$B27,'Base de Datos SADI'!$G$5:$G$716,"<>*No disponible*") -> 5 | G27: =COUNTIFS('Base de Datos SADI'!$C$5:$C$716,G$26,'Base de Datos SADI'!$F$5:$F$716,$B27,'Base de Datos SADI'!$G$5:$G$716,"<>*No disponible*") -> 5 | H27: =COUNTIFS('Base de Datos SADI'!$C$5:$C$716,H$26,'Base de Datos SADI'!$F$5:$F$716,$B27,'Base de Datos SADI'!$G$5:$G$716,"<>*No disponible*") -> 5 | I27: =COUNTIFS('Base de Datos SADI'!$C$5:$C$716,I$26,'Base de Datos SADI'!$F$5:$F$716,$B27,'Base de Datos SADI'!$G$5:$G$716,"<>*No disponible*") -> 0 | J27: =COUNTIFS('Base de Datos SADI'!$C$5:$C$716,J$26,'Base de Datos SADI'!$F$5:$F$716,$B27,'Base de Datos SADI'!$G$5:$G$716,"<>*No disponible*") -> 0 | ... R27: =COUNTIFS('Base de Datos SADI'!$C$5:$C$716,R$26,'Base de Datos SADI'!$F$5:$F$716,$B27,'Base de Datos SADI'!$G$5:$G$716,"<>*No disponible*") -> 0 | S27: =SUM(C27:R27) -> 50
B28: Panel convencional | C28: =COUNTIFS('Base de Datos SADI'!$C$5:$C$716,C$26,'Base de Datos SADI'!$F$5:$F$716,$B28,'Base de Datos SADI'!$G$5:$G$716,"<>*No disponible*") -> 0 | D28: =COUNTIFS('Base de Datos SADI'!$C$5:$C$716,D$26,'Base de Datos SADI'!$F$5:$F$716,$B28,'Base de Datos SADI'!$G$5:$G$716,"<>*No disponible*") -> 0 | E28: =COUNTIFS('Base de Datos SADI'!$C$5:$C$716,E$26,'Base de Datos SADI'!$F$5:$F$716,$B28,'Base de Datos SADI'!$G$5:$G$716,"<>*No disponible*") -> 5 | F28: =COUNTIFS('Base de Datos SADI'!$C$5:$C$716,F$26,'Base de Datos SADI'!$F$5:$F$716,$B28,'Base de Datos SADI'!$G$5:$G$716,"<>*No disponible*") -> 5 | G28: =COUNTIFS('Base de Datos SADI'!$C$5:$C$716,G$26,'Base de Datos SADI'!$F$5:$F$716,$B28,'Base de Datos SADI'!$G$5:$G$716,"<>*No disponible*") -> 5 | H28: =COUNTIFS('Base de Datos SADI'!$C$5:$C$716,H$26,'Base de Datos SADI'!$F$5:$F$716,$B28,'Base de Datos SADI'!$G$5:$G$716,"<>*No disponible*") -> 5 | I28: =COUNTIFS('Base de Datos SADI'!$C$5:$C$716,I$26,'Base de Datos SADI'!$F$5:$F$716,$B28,'Base de Datos SADI'!$G$5:$G$716,"<>*No disponible*") -> 0 | J28: =COUNTIFS('Base de Datos SADI'!$C$5:$C$716,J$26,'Base de Datos SADI'!$F$5:$F$716,$B28,'Base de Datos SADI'!$G$5:$G$716,"<>*No disponible*") -> 0 | ... R28: =COUNTIFS('Base de Datos SADI'!$C$5:$C$716,R$26,'Base de Datos SADI'!$F$5:$F$716,$B28,'Base de Datos SADI'!$G$5:$G$716,"<>*No disponible*") -> 0 | S28: =SUM(C28:R28) -> 40
B29: Humo convencional | C29: =COUNTIFS('Base de Datos SADI'!$C$5:$C$716,C$26,'Base de Datos SADI'!$F$5:$F$716,$B29,'Base de Datos SADI'!$G$5:$G$716,"<>*No disponible*") -> 0 | D29: =COUNTIFS('Base de Datos SADI'!$C$5:$C$716,D$26,'Base de Datos SADI'!$F$5:$F$716,$B29,'Base de Datos SADI'!$G$5:$G$716,"<>*No disponible*") -> 5 | E29: =COUNTIFS('Base de Datos SADI'!$C$5:$C$716,E$26,'Base de Datos SADI'!$F$5:$F$716,$B29,'Base de Datos SADI'!$G$5:$G$716,"<>*No disponible*") -> 5 | F29: =COUNTIFS('Base de Datos SADI'!$C$5:$C$716,F$26,'Base de Datos SADI'!$F$5:$F$716,$B29,'Base de Datos SADI'!$G$5:$G$716,"<>*No disponible*") -> 0 | G29: =COUNTIFS('Base de Datos SADI'!$C$5:$C$716,G$26,'Base de Datos SADI'!$F$5:$F$716,$B29,'Base de Datos SADI'!$G$5:$G$716,"<>*No disponible*") -> 0 | H29: =COUNTIFS('Base de Datos SADI'!$C$5:$C$716,H$26,'Base de Datos SADI'!$F$5:$F$716,$B29,'Base de Datos SADI'!$G$5:$G$716,"<>*No disponible*") -> 5 | I29: =COUNTIFS('Base de Datos SADI'!$C$5:$C$716,I$26,'Base de Datos SADI'!$F$5:$F$716,$B29,'Base de Datos SADI'!$G$5:$G$716,"<>*No disponible*") -> 5 | J29: =COUNTIFS('Base de Datos SADI'!$C$5:$C$716,J$26,'Base de Datos SADI'!$F$5:$F$716,$B29,'Base de Datos SADI'!$G$5:$G$716,"<>*No disponible*") -> 5 | ... R29: =COUNTIFS('Base de Datos SADI'!$C$5:$C$716,R$26,'Base de Datos SADI'!$F$5:$F$716,$B29,'Base de Datos SADI'!$G$5:$G$716,"<>*No disponible*") -> 0 | S29: =SUM(C29:R29) -> 40
B30: Humo direccionable | C30: =COUNTIFS('Base de Datos SADI'!$C$5:$C$716,C$26,'Base de Datos SADI'!$F$5:$F$716,$B30,'Base de Datos SADI'!$G$5:$G$716,"<>*No disponible*") -> 5 | D30: =COUNTIFS('Base de Datos SADI'!$C$5:$C$716,D$26,'Base de Datos SADI'!$F$5:$F$716,$B30,'Base de Datos SADI'!$G$5:$G$716,"<>*No disponible*") -> 5 | E30: =COUNTIFS('Base de Datos SADI'!$C$5:$C$716,E$26,'Base de Datos SADI'!$F$5:$F$716,$B30,'Base de Datos SADI'!$G$5:$G$716,"<>*No disponible*") -> 5 | F30: =COUNTIFS('Base de Datos SADI'!$C$5:$C$716,F$26,'Base de Datos SADI'!$F$5:$F$716,$B30,'Base de Datos SADI'!$G$5:$G$716,"<>*No disponible*") -> 5 | G30: =COUNTIFS('Base de Datos SADI'!$C$5:$C$716,G$26,'Base de Datos SADI'!$F$5:$F$716,$B30,'Base de Datos SADI'!$G$5:$G$716,"<>*No disponible*") -> 5 | H30: =COUNTIFS('Base de Datos SADI'!$C$5:$C$716,H$26,'Base de Datos SADI'!$F$5:$F$716,$B30,'Base de Datos SADI'!$G$5:$G$716,"<>*No disponible*") -> 5 | I30: =COUNTIFS('Base de Datos SADI'!$C$5:$C$716,I$26,'Base de Datos SADI'!$F$5:$F$716,$B30,'Base de Datos SADI'!$G$5:$G$716,"<>*No disponible*") -> 5 | J30: =COUNTIFS('Base de Datos SADI'!$C$5:$C$716,J$26,'Base de Datos SADI'!$F$5:$F$716,$B30,'Base de Datos SADI'!$G$5:$G$716,"<>*No disponible*") -> 5 | ... R30: =COUNTIFS('Base de Datos SADI'!$C$5:$C$716,R$26,'Base de Datos SADI'!$F$5:$F$716,$B30,'Base de Datos SADI'!$G$5:$G$716,"<>*No disponible*") -> 0 | S30: =SUM(C30:R30) -> 55
B31: Térmico direccionable | C31: =COUNTIFS('Base de Datos SADI'!$C$5:$C$716,C$26,'Base de Datos SADI'!$F$5:$F$716,$B31,'Base de Datos SADI'!$G$5:$G$716,"<>*No disponible*") -> 5 | D31: =COUNTIFS('Base de Datos SADI'!$C$5:$C$716,D$26,'Base de Datos SADI'!$F$5:$F$716,$B31,'Base de Datos SADI'!$G$5:$G$716,"<>*No disponible*") -> 5 | E31: =COUNTIFS('Base de Datos SADI'!$C$5:$C$716,E$26,'Base de Datos SADI'!$F$5:$F$716,$B31,'Base de Datos SADI'!$G$5:$G$716,"<>*No disponible*") -> 5 | F31: =COUNTIFS('Base de Datos SADI'!$C$5:$C$716,F$26,'Base de Datos SADI'!$F$5:$F$716,$B31,'Base de Datos SADI'!$G$5:$G$716,"<>*No disponible*") -> 5 | G31: =COUNTIFS('Base de Datos SADI'!$C$5:$C$716,G$26,'Base de Datos SADI'!$F$5:$F$716,$B31,'Base de Datos SADI'!$G$5:$G$716,"<>*No disponible*") -> 5 | H31: =COUNTIFS('Base de Datos SADI'!$C$5:$C$716,H$26,'Base de Datos SADI'!$F$5:$F$716,$B31,'Base de Datos SADI'!$G$5:$G$716,"<>*No disponible*") -> 5 | I31: =COUNTIFS('Base de Datos SADI'!$C$5:$C$716,I$26,'Base de Datos SADI'!$F$5:$F$716,$B31,'Base de Datos SADI'!$G$5:$G$716,"<>*No disponible*") -> 5 | J31: =COUNTIFS('Base de Datos SADI'!$C$5:$C$716,J$26,'Base de Datos SADI'!$F$5:$F$716,$B31,'Base de Datos SADI'!$G$5:$G$716,"<>*No disponible*") -> 5 | ... R31: =COUNTIFS('Base de Datos SADI'!$C$5:$C$716,R$26,'Base de Datos SADI'!$F$5:$F$716,$B31,'Base de Datos SADI'!$G$5:$G$716,"<>*No disponible*") -> 0 | S31: =SUM(C31:R31) -> 50
B32: Multicriterio | C32: =COUNTIFS('Base de Datos SADI'!$C$5:$C$716,C$26,'Base de Datos SADI'!$F$5:$F$716,$B32,'Base de Datos SADI'!$G$5:$G$716,"<>*No disponible*") -> 5 | D32: =COUNTIFS('Base de Datos SADI'!$C$5:$C$716,D$26,'Base de Datos SADI'!$F$5:$F$716,$B32,'Base de Datos SADI'!$G$5:$G$716,"<>*No disponible*") -> 0 | E32: =COUNTIFS('Base de Datos SADI'!$C$5:$C$716,E$26,'Base de Datos SADI'!$F$5:$F$716,$B32,'Base de Datos SADI'!$G$5:$G$716,"<>*No disponible*") -> 5 | F32: =COUNTIFS('Base de Datos SADI'!$C$5:$C$716,F$26,'Base de Datos SADI'!$F$5:$F$716,$B32,'Base de Datos SADI'!$G$5:$G$716,"<>*No disponible*") -> 5 | G32: =COUNTIFS('Base de Datos SADI'!$C$5:$C$716,G$26,'Base de Datos SADI'!$F$5:$F$716,$B32,'Base de Datos SADI'!$G$5:$G$716,"<>*No disponible*") -> 5 | H32: =COUNTIFS('Base de Datos SADI'!$C$5:$C$716,H$26,'Base de Datos SADI'!$F$5:$F$716,$B32,'Base de Datos SADI'!$G$5:$G$716,"<>*No disponible*") -> 0 | I32: =COUNTIFS('Base de Datos SADI'!$C$5:$C$716,I$26,'Base de Datos SADI'!$F$5:$F$716,$B32,'Base de Datos SADI'!$G$5:$G$716,"<>*No disponible*") -> 5 | J32: =COUNTIFS('Base de Datos SADI'!$C$5:$C$716,J$26,'Base de Datos SADI'!$F$5:$F$716,$B32,'Base de Datos SADI'!$G$5:$G$716,"<>*No disponible*") -> 5 | ... R32: =COUNTIFS('Base de Datos SADI'!$C$5:$C$716,R$26,'Base de Datos SADI'!$F$5:$F$716,$B32,'Base de Datos SADI'!$G$5:$G$716,"<>*No disponible*") -> 0 | S32: =SUM(C32:R32) -> 35
B33: Detector de llama | C33: =COUNTIFS('Base de Datos SADI'!$C$5:$C$716,C$26,'Base de Datos SADI'!$F$5:$F$716,$B33,'Base de Datos SADI'!$G$5:$G$716,"<>*No disponible*") -> 0 | D33: =COUNTIFS('Base de Datos SADI'!$C$5:$C$716,D$26,'Base de Datos SADI'!$F$5:$F$716,$B33,'Base de Datos SADI'!$G$5:$G$716,"<>*No disponible*") -> 5 | E33: =COUNTIFS('Base de Datos SADI'!$C$5:$C$716,E$26,'Base de Datos SADI'!$F$5:$F$716,$B33,'Base de Datos SADI'!$G$5:$G$716,"<>*No disponible*") -> 0 | F33: =COUNTIFS('Base de Datos SADI'!$C$5:$C$716,F$26,'Base de Datos SADI'!$F$5:$F$716,$B33,'Base de Datos SADI'!$G$5:$G$716,"<>*No disponible*") -> 0 | G33: =COUNTIFS('Base de Datos SADI'!$C$5:$C$716,G$26,'Base de Datos SADI'!$F$5:$F$716,$B33,'Base de Datos SADI'!$G$5:$G$716,"<>*No disponible*") -> 0 | H33: =COUNTIFS('Base de Datos SADI'!$C$5:$C$716,H$26,'Base de Datos SADI'!$F$5:$F$716,$B33,'Base de Datos SADI'!$G$5:$G$716,"<>*No disponible*") -> 0 | I33: =COUNTIFS('Base de Datos SADI'!$C$5:$C$716,I$26,'Base de Datos SADI'!$F$5:$F$716,$B33,'Base de Datos SADI'!$G$5:$G$716,"<>*No disponible*") -> 0 | J33: =COUNTIFS('Base de Datos SADI'!$C$5:$C$716,J$26,'Base de Datos SADI'!$F$5:$F$716,$B33,'Base de Datos SADI'!$G$5:$G$716,"<>*No disponible*") -> 0 | ... R33: =COUNTIFS('Base de Datos SADI'!$C$5:$C$716,R$26,'Base de Datos SADI'!$F$5:$F$716,$B33,'Base de Datos SADI'!$G$5:$G$716,"<>*No disponible*") -> 5 | S33: =SUM(C33:R33) -> 15
B34: Aspiración (ASD) | C34: =COUNTIFS('Base de Datos SADI'!$C$5:$C$716,C$26,'Base de Datos SADI'!$F$5:$F$716,$B34,'Base de Datos SADI'!$G$5:$G$716,"<>*No disponible*") -> 5 | D34: =COUNTIFS('Base de Datos SADI'!$C$5:$C$716,D$26,'Base de Datos SADI'!$F$5:$F$716,$B34,'Base de Datos SADI'!$G$5:$G$716,"<>*No disponible*") -> 0 | E34: =COUNTIFS('Base de Datos SADI'!$C$5:$C$716,E$26,'Base de Datos SADI'!$F$5:$F$716,$B34,'Base de Datos SADI'!$G$5:$G$716,"<>*No disponible*") -> 0 | F34: =COUNTIFS('Base de Datos SADI'!$C$5:$C$716,F$26,'Base de Datos SADI'!$F$5:$F$716,$B34,'Base de Datos SADI'!$G$5:$G$716,"<>*No disponible*") -> 0 | G34: =COUNTIFS('Base de Datos SADI'!$C$5:$C$716,G$26,'Base de Datos SADI'!$F$5:$F$716,$B34,'Base de Datos SADI'!$G$5:$G$716,"<>*No disponible*") -> 0 | H34: =COUNTIFS('Base de Datos SADI'!$C$5:$C$716,H$26,'Base de Datos SADI'!$F$5:$F$716,$B34,'Base de Datos SADI'!$G$5:$G$716,"<>*No disponible*") -> 0 | I34: =COUNTIFS('Base de Datos SADI'!$C$5:$C$716,I$26,'Base de Datos SADI'!$F$5:$F$716,$B34,'Base de Datos SADI'!$G$5:$G$716,"<>*No disponible*") -> 0 | J34: =COUNTIFS('Base de Datos SADI'!$C$5:$C$716,J$26,'Base de Datos SADI'!$F$5:$F$716,$B34,'Base de Datos SADI'!$G$5:$G$716,"<>*No disponible*") -> 0 | ... R34: =COUNTIFS('Base de Datos SADI'!$C$5:$C$716,R$26,'Base de Datos SADI'!$F$5:$F$716,$B34,'Base de Datos SADI'!$G$5:$G$716,"<>*No disponible*") -> 0 | S34: =SUM(C34:R34) -> 10
B35: Lineal de haz | C35: =COUNTIFS('Base de Datos SADI'!$C$5:$C$716,C$26,'Base de Datos SADI'!$F$5:$F$716,$B35,'Base de Datos SADI'!$G$5:$G$716,"<>*No disponible*") -> 5 | D35: =COUNTIFS('Base de Datos SADI'!$C$5:$C$716,D$26,'Base de Datos SADI'!$F$5:$F$716,$B35,'Base de Datos SADI'!$G$5:$G$716,"<>*No disponible*") -> 0 | E35: =COUNTIFS('Base de Datos SADI'!$C$5:$C$716,E$26,'Base de Datos SADI'!$F$5:$F$716,$B35,'Base de Datos SADI'!$G$5:$G$716,"<>*No disponible*") -> 5 | F35: =COUNTIFS('Base de Datos SADI'!$C$5:$C$716,F$26,'Base de Datos SADI'!$F$5:$F$716,$B35,'Base de Datos SADI'!$G$5:$G$716,"<>*No disponible*") -> 0 | G35: =COUNTIFS('Base de Datos SADI'!$C$5:$C$716,G$26,'Base de Datos SADI'!$F$5:$F$716,$B35,'Base de Datos SADI'!$G$5:$G$716,"<>*No disponible*") -> 0 | H35: =COUNTIFS('Base de Datos SADI'!$C$5:$C$716,H$26,'Base de Datos SADI'!$F$5:$F$716,$B35,'Base de Datos SADI'!$G$5:$G$716,"<>*No disponible*") -> 0 | I35: =COUNTIFS('Base de Datos SADI'!$C$5:$C$716,I$26,'Base de Datos SADI'!$F$5:$F$716,$B35,'Base de Datos SADI'!$G$5:$G$716,"<>*No disponible*") -> 5 | J35: =COUNTIFS('Base de Datos SADI'!$C$5:$C$716,J$26,'Base de Datos SADI'!$F$5:$F$716,$B35,'Base de Datos SADI'!$G$5:$G$716,"<>*No disponible*") -> 0 | ... R35: =COUNTIFS('Base de Datos SADI'!$C$5:$C$716,R$26,'Base de Datos SADI'!$F$5:$F$716,$B35,'Base de Datos SADI'!$G$5:$G$716,"<>*No disponible*") -> 0 | S35: =SUM(C35:R35) -> 20
B36: Estación manual | C36: =COUNTIFS('Base de Datos SADI'!$C$5:$C$716,C$26,'Base de Datos SADI'!$F$5:$F$716,$B36,'Base de Datos SADI'!$G$5:$G$716,"<>*No disponible*") -> 5 | D36: =COUNTIFS('Base de Datos SADI'!$C$5:$C$716,D$26,'Base de Datos SADI'!$F$5:$F$716,$B36,'Base de Datos SADI'!$G$5:$G$716,"<>*No disponible*") -> 5 | E36: =COUNTIFS('Base de Datos SADI'!$C$5:$C$716,E$26,'Base de Datos SADI'!$F$5:$F$716,$B36,'Base de Datos SADI'!$G$5:$G$716,"<>*No disponible*") -> 5 | F36: =COUNTIFS('Base de Datos SADI'!$C$5:$C$716,F$26,'Base de Datos SADI'!$F$5:$F$716,$B36,'Base de Datos SADI'!$G$5:$G$716,"<>*No disponible*") -> 5 | G36: =COUNTIFS('Base de Datos SADI'!$C$5:$C$716,G$26,'Base de Datos SADI'!$F$5:$F$716,$B36,'Base de Datos SADI'!$G$5:$G$716,"<>*No disponible*") -> 5 | H36: =COUNTIFS('Base de Datos SADI'!$C$5:$C$716,H$26,'Base de Datos SADI'!$F$5:$F$716,$B36,'Base de Datos SADI'!$G$5:$G$716,"<>*No disponible*") -> 5 | I36: =COUNTIFS('Base de Datos SADI'!$C$5:$C$716,I$26,'Base de Datos SADI'!$F$5:$F$716,$B36,'Base de Datos SADI'!$G$5:$G$716,"<>*No disponible*") -> 0 | J36: =COUNTIFS('Base de Datos SADI'!$C$5:$C$716,J$26,'Base de Datos SADI'!$F$5:$F$716,$B36,'Base de Datos SADI'!$G$5:$G$716,"<>*No disponible*") -> 5 | ... R36: =COUNTIFS('Base de Datos SADI'!$C$5:$C$716,R$26,'Base de Datos SADI'!$F$5:$F$716,$B36,'Base de Datos SADI'!$G$5:$G$716,"<>*No disponible*") -> 0 | S36: =SUM(C36:R36) -> 55
B37: Sirena con estrobo | C37: =COUNTIFS('Base de Datos SADI'!$C$5:$C$716,C$26,'Base de Datos SADI'!$F$5:$F$716,$B37,'Base de Datos SADI'!$G$5:$G$716,"<>*No disponible*") -> 0 | D37: =COUNTIFS('Base de Datos SADI'!$C$5:$C$716,D$26,'Base de Datos SADI'!$F$5:$F$716,$B37,'Base de Datos SADI'!$G$5:$G$716,"<>*No disponible*") -> 0 | E37: =COUNTIFS('Base de Datos SADI'!$C$5:$C$716,E$26,'Base de Datos SADI'!$F$5:$F$716,$B37,'Base de Datos SADI'!$G$5:$G$716,"<>*No disponible*") -> 0 | F37: =COUNTIFS('Base de Datos SADI'!$C$5:$C$716,F$26,'Base de Datos SADI'!$F$5:$F$716,$B37,'Base de Datos SADI'!$G$5:$G$716,"<>*No disponible*") -> 5 | G37: =COUNTIFS('Base de Datos SADI'!$C$5:$C$716,G$26,'Base de Datos SADI'!$F$5:$F$716,$B37,'Base de Datos SADI'!$G$5:$G$716,"<>*No disponible*") -> 5 | H37: =COUNTIFS('Base de Datos SADI'!$C$5:$C$716,H$26,'Base de Datos SADI'!$F$5:$F$716,$B37,'Base de Datos SADI'!$G$5:$G$716,"<>*No disponible*") -> 0 | I37: =COUNTIFS('Base de Datos SADI'!$C$5:$C$716,I$26,'Base de Datos SADI'!$F$5:$F$716,$B37,'Base de Datos SADI'!$G$5:$G$716,"<>*No disponible*") -> 0 | J37: =COUNTIFS('Base de Datos SADI'!$C$5:$C$716,J$26,'Base de Datos SADI'!$F$5:$F$716,$B37,'Base de Datos SADI'!$G$5:$G$716,"<>*No disponible*") -> 5 | ... R37: =COUNTIFS('Base de Datos SADI'!$C$5:$C$716,R$26,'Base de Datos SADI'!$F$5:$F$716,$B37,'Base de Datos SADI'!$G$5:$G$716,"<>*No disponible*") -> 0 | S37: =SUM(C37:R37) -> 35
B38: Módulo de monitoreo | C38: =COUNTIFS('Base de Datos SADI'!$C$5:$C$716,C$26,'Base de Datos SADI'!$F$5:$F$716,$B38,'Base de Datos SADI'!$G$5:$G$716,"<>*No disponible*") -> 5 | D38: =COUNTIFS('Base de Datos SADI'!$C$5:$C$716,D$26,'Base de Datos SADI'!$F$5:$F$716,$B38,'Base de Datos SADI'!$G$5:$G$716,"<>*No disponible*") -> 5 | E38: =COUNTIFS('Base de Datos SADI'!$C$5:$C$716,E$26,'Base de Datos SADI'!$F$5:$F$716,$B38,'Base de Datos SADI'!$G$5:$G$716,"<>*No disponible*") -> 5 | F38: =COUNTIFS('Base de Datos SADI'!$C$5:$C$716,F$26,'Base de Datos SADI'!$F$5:$F$716,$B38,'Base de Datos SADI'!$G$5:$G$716,"<>*No disponible*") -> 5 | G38: =COUNTIFS('Base de Datos SADI'!$C$5:$C$716,G$26,'Base de Datos SADI'!$F$5:$F$716,$B38,'Base de Datos SADI'!$G$5:$G$716,"<>*No disponible*") -> 5 | H38: =COUNTIFS('Base de Datos SADI'!$C$5:$C$716,H$26,'Base de Datos SADI'!$F$5:$F$716,$B38,'Base de Datos SADI'!$G$5:$G$716,"<>*No disponible*") -> 5 | I38: =COUNTIFS('Base de Datos SADI'!$C$5:$C$716,I$26,'Base de Datos SADI'!$F$5:$F$716,$B38,'Base de Datos SADI'!$G$5:$G$716,"<>*No disponible*") -> 5 | J38: =COUNTIFS('Base de Datos SADI'!$C$5:$C$716,J$26,'Base de Datos SADI'!$F$5:$F$716,$B38,'Base de Datos SADI'!$G$5:$G$716,"<>*No disponible*") -> 5 | ... R38: =COUNTIFS('Base de Datos SADI'!$C$5:$C$716,R$26,'Base de Datos SADI'!$F$5:$F$716,$B38,'Base de Datos SADI'!$G$5:$G$716,"<>*No disponible*") -> 0 | S38: =SUM(C38:R38) -> 50
... B42: Aislador/base lazo | C42: =COUNTIFS('Base de Datos SADI'!$C$5:$C$716,C$26,'Base de Datos SADI'!$F$5:$F$716,$B42,'Base de Datos SADI'!$G$5:$G$716,"<>*No disponible*") -> 5 | D42: =COUNTIFS('Base de Datos SADI'!$C$5:$C$716,D$26,'Base de Datos SADI'!$F$5:$F$716,$B42,'Base de Datos SADI'!$G$5:$G$716,"<>*No disponible*") -> 5 | E42: =COUNTIFS('Base de Datos SADI'!$C$5:$C$716,E$26,'Base de Datos SADI'!$F$5:$F$716,$B42,'Base de Datos SADI'!$G$5:$G$716,"<>*No disponible*") -> 0 | F42: =COUNTIFS('Base de Datos SADI'!$C$5:$C$716,F$26,'Base de Datos SADI'!$F$5:$F$716,$B42,'Base de Datos SADI'!$G$5:$G$716,"<>*No disponible*") -> 5 | G42: =COUNTIFS('Base de Datos SADI'!$C$5:$C$716,G$26,'Base de Datos SADI'!$F$5:$F$716,$B42,'Base de Datos SADI'!$G$5:$G$716,"<>*No disponible*") -> 0 | H42: =COUNTIFS('Base de Datos SADI'!$C$5:$C$716,H$26,'Base de Datos SADI'!$F$5:$F$716,$B42,'Base de Datos SADI'!$G$5:$G$716,"<>*No disponible*") -> 0 | I42: =COUNTIFS('Base de Datos SADI'!$C$5:$C$716,I$26,'Base de Datos SADI'!$F$5:$F$716,$B42,'Base de Datos SADI'!$G$5:$G$716,"<>*No disponible*") -> 5 | J42: =COUNTIFS('Base de Datos SADI'!$C$5:$C$716,J$26,'Base de Datos SADI'!$F$5:$F$716,$B42,'Base de Datos SADI'!$G$5:$G$716,"<>*No disponible*") -> 5 | ... R42: =COUNTIFS('Base de Datos SADI'!$C$5:$C$716,R$26,'Base de Datos SADI'!$F$5:$F$716,$B42,'Base de Datos SADI'!$G$5:$G$716,"<>*No disponible*") -> 0 | S42: =SUM(C42:R42) -> 30
B43: Modelos activos por marca | C43: =SUM(C27:C42) -> 55 | D43: =SUM(D27:D42) -> 55 | E43: =SUM(E27:E42) -> 50 | F43: =SUM(F27:F42) -> 50 | G43: =SUM(G27:G42) -> 45 | H43: =SUM(H27:H42) -> 40 | I43: =SUM(I27:I42) -> 40 | J43: =SUM(J27:J42) -> 50 | ... S43: =SUM(S27:S42) -> 570
B46: Estadísticas SACI por marca (precio USD)
B47: Marca | C47: Nivel | D47: País | E47: Modelos activos | F47: Precio mín. (USD) | G47: Precio máx. (USD) | H47: Precio promedio (USD)
B48: Honeywell Security | C48: Alta | D48: EE. UU. | E48: =COUNTIFS('Base de Datos SACI'!$C$5:$C$1076,$B48,'Base de Datos SACI'!$G$5:$G$1076,"<>*No disponible*") -> 75 | F48: =MIN('Base de Datos SACI'!$U$5:$U$80) -> 8 | G48: =MAX('Base de Datos SACI'!$U$5:$U$80) -> 645 | H48: =IFERROR(ROUND(AVERAGE('Base de Datos SACI'!$U$5:$U$80),0),"—") -> 112
B49: DSC | C49: Alta | D49: Canadá | E49: =COUNTIFS('Base de Datos SACI'!$C$5:$C$1076,$B49,'Base de Datos SACI'!$G$5:$G$1076,"<>*No disponible*") -> 75 | F49: =MIN('Base de Datos SACI'!$U$81:$U$156) -> 12 | G49: =MAX('Base de Datos SACI'!$U$81:$U$156) -> 680 | H49: =IFERROR(ROUND(AVERAGE('Base de Datos SACI'!$U$81:$U$156),0),"—") -> 109
B50: Paradox | C50: Alta | D50: Canadá | E50: =COUNTIFS('Base de Datos SACI'!$C$5:$C$1076,$B50,'Base de Datos SACI'!$G$5:$G$1076,"<>*No disponible*") -> 70 | F50: =MIN('Base de Datos SACI'!$U$157:$U$228) -> 12 | G50: =MAX('Base de Datos SACI'!$U$157:$U$228) -> 625 | H50: =IFERROR(ROUND(AVERAGE('Base de Datos SACI'!$U$157:$U$228),0),"—") -> 94
B51: Bosch Security | C51: Alta | D51: Alemania | E51: =COUNTIFS('Base de Datos SACI'!$C$5:$C$1076,$B51,'Base de Datos SACI'!$G$5:$G$1076,"<>*No disponible*") -> 65 | F51: =MIN('Base de Datos SACI'!$U$229:$U$296) -> 16 | G51: =MAX('Base de Datos SACI'!$U$229:$U$296) -> 580 | H51: =IFERROR(ROUND(AVERAGE('Base de Datos SACI'!$U$229:$U$296),0),"—") -> 122
B52: Ajax Systems | C52: Alta | D52: Ucrania | E52: =COUNTIFS('Base de Datos SACI'!$C$5:$C$1076,$B52,'Base de Datos SACI'!$G$5:$G$1076,"<>*No disponible*") -> 65 | F52: =MIN('Base de Datos SACI'!$U$297:$U$364) -> 12 | G52: =MAX('Base de Datos SACI'!$U$297:$U$364) -> 680 | H52: =IFERROR(ROUND(AVERAGE('Base de Datos SACI'!$U$297:$U$364),0),"—") -> 88
B53: Visonic | C53: Alta | D53: Israel | E53: =COUNTIFS('Base de Datos SACI'!$C$5:$C$1076,$B53,'Base de Datos SACI'!$G$5:$G$1076,"<>*No disponible*") -> 65 | F53: =MIN('Base de Datos SACI'!$U$365:$U$432) -> 8 | G53: =MAX('Base de Datos SACI'!$U$365:$U$432) -> 645 | H53: =IFERROR(ROUND(AVERAGE('Base de Datos SACI'!$U$365:$U$432),0),"—") -> 88
B54: Texecom | C54: Alta | D54: Reino Unido | E54: =COUNTIFS('Base de Datos SACI'!$C$5:$C$1076,$B54,'Base de Datos SACI'!$G$5:$G$1076,"<>*No disponible*") -> 60 | F54: =MIN('Base de Datos SACI'!$U$433:$U$496) -> 17 | G54: =MAX('Base de Datos SACI'!$U$433:$U$496) -> 580 | H54: =IFERROR(ROUND(AVERAGE('Base de Datos SACI'!$U$433:$U$496),0),"—") -> 99
B55: Risco | C55: Alta | D55: Israel | E55: =COUNTIFS('Base de Datos SACI'!$C$5:$C$1076,$B55,'Base de Datos SACI'!$G$5:$G$1076,"<>*No disponible*") -> 60 | F55: =MIN('Base de Datos SACI'!$U$497:$U$560) -> 15 | G55: =MAX('Base de Datos SACI'!$U$497:$U$560) -> 690 | H55: =IFERROR(ROUND(AVERAGE('Base de Datos SACI'!$U$497:$U$560),0),"—") -> 123
B56: Crow | C56: Media | D56: Israel | E56: =COUNTIFS('Base de Datos SACI'!$C$5:$C$1076,$B56,'Base de Datos SACI'!$G$5:$G$1076,"<>*No disponible*") -> 60 | F56: =MIN('Base de Datos SACI'!$U$561:$U$624) -> 8 | G56: =MAX('Base de Datos SACI'!$U$561:$U$624) -> 345 | H56: =IFERROR(ROUND(AVERAGE('Base de Datos SACI'!$U$561:$U$624),0),"—") -> 73
B57: Jablotron | C57: Media | D57: Rep. Checa | E57: =COUNTIFS('Base de Datos SACI'!$C$5:$C$1076,$B57,'Base de Datos SACI'!$G$5:$G$1076,"<>*No disponible*") -> 60 | F57: =MIN('Base de Datos SACI'!$U$625:$U$688) -> 13 | G57: =MAX('Base de Datos SACI'!$U$625:$U$688) -> 470 | H57: =IFERROR(ROUND(AVERAGE('Base de Datos SACI'!$U$625:$U$688),0),"—") -> 92
B58: Satel | C58: Media | D58: Polonia | E58: =COUNTIFS('Base de Datos SACI'!$C$5:$C$1076,$B58,'Base de Datos SACI'!$G$5:$G$1076,"<>*No disponible*") -> 65 | F58: =MIN('Base de Datos SACI'!$U$689:$U$756) -> 12 | G58: =MAX('Base de Datos SACI'!$U$689:$U$756) -> 715 | H58: =IFERROR(ROUND(AVERAGE('Base de Datos SACI'!$U$689:$U$756),0),"—") -> 112
B59: Pyronix (Hikvision) | C59: Media | D59: Reino Unido | E59: =COUNTIFS('Base de Datos SACI'!$C$5:$C$1076,$B59,'Base de Datos SACI'!$G$5:$G$1076,"<>*No disponible*") -> 55 | F59: =MIN('Base de Datos SACI'!$U$757:$U$816) -> 14 | G59: =MAX('Base de Datos SACI'!$U$757:$U$816) -> 425 | H59: =IFERROR(ROUND(AVERAGE('Base de Datos SACI'!$U$757:$U$816),0),"—") -> 88
B60: Hikvision | C60: Media | D60: China | E60: =COUNTIFS('Base de Datos SACI'!$C$5:$C$1076,$B60,'Base de Datos SACI'!$G$5:$G$1076,"<>*No disponible*") -> 40 | F60: =MIN('Base de Datos SACI'!$U$817:$U$864) -> 12 | G60: =MAX('Base de Datos SACI'!$U$817:$U$864) -> 495 | H60: =IFERROR(ROUND(AVERAGE('Base de Datos SACI'!$U$817:$U$864),0),"—") -> 78
B61: Qolsys | C61: Media | D61: EE. UU. | E61: =COUNTIFS('Base de Datos SACI'!$C$5:$C$1076,$B61,'Base de Datos SACI'!$G$5:$G$1076,"<>*No disponible*") -> 25 | F61: =MIN('Base de Datos SACI'!$U$865:$U$900) -> 19 | G61: =MAX('Base de Datos SACI'!$U$865:$U$900) -> 680 | H61: =IFERROR(ROUND(AVERAGE('Base de Datos SACI'!$U$865:$U$900),0),"—") -> 138
B62: ELDES | C62: Entrada | D62: Lituania | E62: =COUNTIFS('Base de Datos SACI'!$C$5:$C$1076,$B62,'Base de Datos SACI'!$G$5:$G$1076,"<>*No disponible*") -> 35 | F62: =MIN('Base de Datos SACI'!$U$901:$U$944) -> 8 | G62: =MAX('Base de Datos SACI'!$U$901:$U$944) -> 535 | H62: =IFERROR(ROUND(AVERAGE('Base de Datos SACI'!$U$901:$U$944),0),"—") -> 95
B63: Chuango | C63: Entrada | D63: China | E63: =COUNTIFS('Base de Datos SACI'!$C$5:$C$1076,$B63,'Base de Datos SACI'!$G$5:$G$1076,"<>*No disponible*") -> 35 | F63: =MIN('Base de Datos SACI'!$U$945:$U$988) -> 8 | G63: =MAX('Base de Datos SACI'!$U$945:$U$988) -> 240 | H63: =IFERROR(ROUND(AVERAGE('Base de Datos SACI'!$U$945:$U$988),0),"—") -> 35
B64: Optex | C64: Alta | D64: Japón | E64: =COUNTIFS('Base de Datos SACI'!$C$5:$C$1076,$B64,'Base de Datos SACI'!$G$5:$G$1076,"<>*No disponible*") -> 15 | F64: =MIN('Base de Datos SACI'!$U$989:$U$1016) -> 19 | G64: =MAX('Base de Datos SACI'!$U$989:$U$1016) -> 680 | H64: =IFERROR(ROUND(AVERAGE('Base de Datos SACI'!$U$989:$U$1016),0),"—") -> 182
B65: Siemens | C65: Alta | D65: Alemania | E65: =COUNTIFS('Base de Datos SACI'!$C$5:$C$1076,$B65,'Base de Datos SACI'!$G$5:$G$1076,"<>*No disponible*") -> 55 | F65: =MIN('Base de Datos SACI'!$U$1017:$U$1076) -> 12 | G65: =MAX('Base de Datos SACI'!$U$1017:$U$1076) -> 1250 | H65: =IFERROR(ROUND(AVERAGE('Base de Datos SACI'!$U$1017:$U$1076),0),"—") -> 144
B66: TOTAL / GENERAL | E66: =SUM(E48:E65) -> 980 | F66: =MIN(F48:F65) -> 8 | G66: =MAX(G48:G65) -> 1250 | H66: =IFERROR(ROUND(AVERAGE('Base de Datos SACI'!$U$5:$U$1076),0),"—") -> 102
B69: Estadísticas SADI por marca (precio USD)
B70: Marca | C70: Nivel | D70: País | E70: Modelos activos | F70: Precio mín. (USD) | G70: Precio máx. (USD) | H70: Precio promedio (USD)
B71: Honeywell Fire | C71: Alta | D71: EE. UU. | E71: =COUNTIFS('Base de Datos SADI'!$C$5:$C$716,$B71,'Base de Datos SADI'!$G$5:$G$716,"<>*No disponible*") -> 55 | F71: =MIN('Base de Datos SADI'!$U$5:$U$64) -> 19 | G71: =MAX('Base de Datos SADI'!$U$5:$U$64) -> 8470 | H71: =IFERROR(ROUND(AVERAGE('Base de Datos SADI'!$U$5:$U$64),0),"—") -> 751
B72: Siemens | C72: Alta | D72: Alemania | E72: =COUNTIFS('Base de Datos SADI'!$C$5:$C$716,$B72,'Base de Datos SADI'!$G$5:$G$716,"<>*No disponible*") -> 55 | F72: =MIN('Base de Datos SADI'!$U$65:$U$124) -> 9 | G72: =MAX('Base de Datos SADI'!$U$65:$U$124) -> 3190 | H72: =IFERROR(ROUND(AVERAGE('Base de Datos SADI'!$U$65:$U$124),0),"—") -> 404
B73: Bosch Fire | C73: Alta | D73: Alemania | E73: =COUNTIFS('Base de Datos SADI'!$C$5:$C$716,$B73,'Base de Datos SADI'!$G$5:$G$716,"<>*No disponible*") -> 50 | F73: =MIN('Base de Datos SADI'!$U$125:$U$180) -> 16 | G73: =MAX('Base de Datos SADI'!$U$125:$U$180) -> 3190 | H73: =IFERROR(ROUND(AVERAGE('Base de Datos SADI'!$U$125:$U$180),0),"—") -> 355
B74: Edwards (EST) | C74: Alta | D74: EE. UU. | E74: =COUNTIFS('Base de Datos SADI'!$C$5:$C$716,$B74,'Base de Datos SADI'!$G$5:$G$716,"<>*No disponible*") -> 50 | F74: =MIN('Base de Datos SADI'!$U$181:$U$236) -> 20 | G74: =MAX('Base de Datos SADI'!$U$181:$U$236) -> 6270 | H74: =IFERROR(ROUND(AVERAGE('Base de Datos SADI'!$U$181:$U$236),0),"—") -> 482
B75: Simplex (JCI) | C75: Alta | D75: EE. UU. | E75: =COUNTIFS('Base de Datos SADI'!$C$5:$C$716,$B75,'Base de Datos SADI'!$G$5:$G$716,"<>*No disponible*") -> 45 | F75: =MIN('Base de Datos SADI'!$U$237:$U$288) -> 35 | G75: =MAX('Base de Datos SADI'!$U$237:$U$288) -> 7040 | H75: =IFERROR(ROUND(AVERAGE('Base de Datos SADI'!$U$237:$U$288),0),"—") -> 606
B76: Morley-IAS (Honeywell) | C76: Media | D76: Reino Unido | E76: =COUNTIFS('Base de Datos SADI'!$C$5:$C$716,$B76,'Base de Datos SADI'!$G$5:$G$716,"<>*No disponible*") -> 40 | F76: =MIN('Base de Datos SADI'!$U$289:$U$336) -> 17 | G76: =MAX('Base de Datos SADI'!$U$289:$U$336) -> 2310 | H76: =IFERROR(ROUND(AVERAGE('Base de Datos SADI'!$U$289:$U$336),0),"—") -> 233
B77: Apollo Fire Detectors | C77: Alta | D77: Reino Unido | E77: =COUNTIFS('Base de Datos SADI'!$C$5:$C$716,$B77,'Base de Datos SADI'!$G$5:$G$716,"<>*No disponible*") -> 40 | F77: =MIN('Base de Datos SADI'!$U$337:$U$384) -> 9 | G77: =MAX('Base de Datos SADI'!$U$337:$U$384) -> 1405 | H77: =IFERROR(ROUND(AVERAGE('Base de Datos SADI'!$U$337:$U$384),0),"—") -> 142
B78: Hochiki | C78: Alta | D78: Japón | E78: =COUNTIFS('Base de Datos SADI'!$C$5:$C$716,$B78,'Base de Datos SADI'!$G$5:$G$716,"<>*No disponible*") -> 50 | F78: =MIN('Base de Datos SADI'!$U$385:$U$440) -> 11 | G78: =MAX('Base de Datos SADI'!$U$385:$U$440) -> 360 | H78: =IFERROR(ROUND(AVERAGE('Base de Datos SADI'!$U$385:$U$440),0),"—") -> 68
B79: System Sensor | C79: Media | D79: EE. UU. | E79: =COUNTIFS('Base de Datos SADI'!$C$5:$C$716,$B79,'Base de Datos SADI'!$G$5:$G$716,"<>*No disponible*") -> 20 | F79: =MIN('Base de Datos SADI'!$U$441:$U$472) -> 13 | G79: =MAX('Base de Datos SADI'!$U$441:$U$472) -> 1360 | H79: =IFERROR(ROUND(AVERAGE('Base de Datos SADI'!$U$441:$U$472),0),"—") -> 265
B80: GST | C80: Media | D80: China | E80: =COUNTIFS('Base de Datos SADI'!$C$5:$C$716,$B80,'Base de Datos SADI'!$G$5:$G$716,"<>*No disponible*") -> 45 | F80: =MIN('Base de Datos SADI'!$U$473:$U$524) -> 8 | G80: =MAX('Base de Datos SADI'!$U$473:$U$524) -> 2155 | H80: =IFERROR(ROUND(AVERAGE('Base de Datos SADI'!$U$473:$U$524),0),"—") -> 192
B81: Fire-Lite (Honeywell) | C81: Media | D81: EE. UU. | E81: =COUNTIFS('Base de Datos SADI'!$C$5:$C$716,$B81,'Base de Datos SADI'!$G$5:$G$716,"<>*No disponible*") -> 45 | F81: =MIN('Base de Datos SADI'!$U$525:$U$576) -> 11 | G81: =MAX('Base de Datos SADI'!$U$525:$U$576) -> 2530 | H81: =IFERROR(ROUND(AVERAGE('Base de Datos SADI'!$U$525:$U$576),0),"—") -> 303
B82: Zeta Alarm Systems | C82: Entrada | D82: Reino Unido | E82: =COUNTIFS('Base de Datos SADI'!$C$5:$C$716,$B82,'Base de Datos SADI'!$G$5:$G$716,"<>*No disponible*") -> 25 | F82: =MIN('Base de Datos SADI'!$U$577:$U$612) -> 8 | G82: =MAX('Base de Datos SADI'!$U$577:$U$612) -> 680 | H82: =IFERROR(ROUND(AVERAGE('Base de Datos SADI'!$U$577:$U$612),0),"—") -> 128
B83: Gent (Honeywell) | C83: Alta | D83: Reino Unido | E83: =COUNTIFS('Base de Datos SADI'!$C$5:$C$716,$B83,'Base de Datos SADI'!$G$5:$G$716,"<>*No disponible*") -> 30 | F83: =MIN('Base de Datos SADI'!$U$613:$U$652) -> 25 | G83: =MAX('Base de Datos SADI'!$U$613:$U$652) -> 2900 | H83: =IFERROR(ROUND(AVERAGE('Base de Datos SADI'!$U$613:$U$652),0),"—") -> 433
B84: Xtralis (Honeywell) | C84: Alta | D84: Irlanda | E84: =COUNTIFS('Base de Datos SADI'!$C$5:$C$716,$B84,'Base de Datos SADI'!$G$5:$G$716,"<>*No disponible*") -> 10 | F84: =MIN('Base de Datos SADI'!$U$653:$U$676) -> 1200 | G84: =MAX('Base de Datos SADI'!$U$653:$U$676) -> 9680 | H84: =IFERROR(ROUND(AVERAGE('Base de Datos SADI'!$U$653:$U$676),0),"—") -> 4046
B85: Det-Tronics | C85: Alta | D85: EE. UU. | E85: =COUNTIFS('Base de Datos SADI'!$C$5:$C$716,$B85,'Base de Datos SADI'!$G$5:$G$716,"<>*No disponible*") -> 5 | F85: =MIN('Base de Datos SADI'!$U$677:$U$696) -> 725 | G85: =MAX('Base de Datos SADI'!$U$677:$U$696) -> 3190 | H85: =IFERROR(ROUND(AVERAGE('Base de Datos SADI'!$U$677:$U$696),0),"—") -> 1725
B86: Fire Sentry (Honeywell) | C86: Alta | D86: EE. UU. | E86: =COUNTIFS('Base de Datos SADI'!$C$5:$C$716,$B86,'Base de Datos SADI'!$G$5:$G$716,"<>*No disponible*") -> 5 | F86: =MIN('Base de Datos SADI'!$U$697:$U$716) -> 640 | G86: =MAX('Base de Datos SADI'!$U$697:$U$716) -> 2815 | H86: =IFERROR(ROUND(AVERAGE('Base de Datos SADI'!$U$697:$U$716),0),"—") -> 1523
B87: TOTAL / GENERAL | E87: =SUM(E71:E86) -> 570 | F87: =MIN(F71:F86) -> 8 | G87: =MAX(G71:G86) -> 9680 | H87: =IFERROR(ROUND(AVERAGE('Base de Datos SADI'!$U$5:$U$716),0),"—") -> 441
B90: Estadísticas de equipamiento común por categoría
B91: Categoría de Equipamiento | C91: Modelos | D91: Precio mín. (USD) | E91: Precio máx. (USD) | F91: Precio promedio (USD)
B92: Baterías de respaldo | C92: =COUNTIF(Equipamiento!$C$5:$C$72,$B92) -> 10 | D92: =MIN(Equipamiento!$O$5:$O$14) -> 14 | E92: =MAX(Equipamiento!$O$5:$O$14) -> 118 | F92: =IFERROR(ROUND(AVERAGE(Equipamiento!$O$5:$O$14),0),"—") -> 52
B93: Fuentes de poder | C93: =COUNTIF(Equipamiento!$C$5:$C$72,$B93) -> 9 | D93: =MIN(Equipamiento!$O$15:$O$23) -> 18 | E93: =MAX(Equipamiento!$O$15:$O$23) -> 265 | F93: =IFERROR(ROUND(AVERAGE(Equipamiento!$O$15:$O$23),0),"—") -> 110
B94: Gabinetes y canastillas | C94: =COUNTIF(Equipamiento!$C$5:$C$72,$B94) -> 7 | D94: =MIN(Equipamiento!$O$24:$O$30) -> 15 | E94: =MAX(Equipamiento!$O$24:$O$30) -> 130 | F94: =IFERROR(ROUND(AVERAGE(Equipamiento!$O$24:$O$30),0),"—") -> 66
B95: Cableado y conductores | C95: =COUNTIF(Equipamiento!$C$5:$C$72,$B95) -> 10 | D95: =MIN(Equipamiento!$O$31:$O$40) -> 8 | E95: =MAX(Equipamiento!$O$31:$O$40) -> 82 | F95: =IFERROR(ROUND(AVERAGE(Equipamiento!$O$31:$O$40),0),"—") -> 45
B96: Herramientas y pruebas | C96: =COUNTIF(Equipamiento!$C$5:$C$72,$B96) -> 8 | D96: =MIN(Equipamiento!$O$41:$O$48) -> 14 | E96: =MAX(Equipamiento!$O$41:$O$48) -> 320 | F96: =IFERROR(ROUND(AVERAGE(Equipamiento!$O$41:$O$48),0),"—") -> 117
B97: Comunicación y monitoreo | C97: =COUNTIF(Equipamiento!$C$5:$C$72,$B97) -> 7 | D97: =MIN(Equipamiento!$O$49:$O$55) -> 88 | E97: =MAX(Equipamiento!$O$49:$O$55) -> 2400 | F97: =IFERROR(ROUND(AVERAGE(Equipamiento!$O$49:$O$55),0),"—") -> 989
B98: Accesorios de instalación | C98: =COUNTIF(Equipamiento!$C$5:$C$72,$B98) -> 11 | D98: =MIN(Equipamiento!$O$56:$O$66) -> 6 | E98: =MAX(Equipamiento!$O$56:$O$66) -> 38 | F98: =IFERROR(ROUND(AVERAGE(Equipamiento!$O$56:$O$66),0),"—") -> 15
B99: Protección eléctrica | C99: =COUNTIF(Equipamiento!$C$5:$C$72,$B99) -> 6 | D99: =MIN(Equipamiento!$O$67:$O$72) -> 6 | E99: =MAX(Equipamiento!$O$67:$O$72) -> 385 | F99: =IFERROR(ROUND(AVERAGE(Equipamiento!$O$67:$O$72),0),"—") -> 80
B100: TOTAL / GENERAL | C100: =SUM(C92:C99) -> 68 | D100: =MIN(D92:D99) -> 6 | E100: =MAX(E92:E99) -> 2400 | F100: =IFERROR(ROUND(AVERAGE(Equipamiento!$O$5:$O$72),0),"—") -> 161
B102: Nota: las matrices cuentan modelos activos (excluyen filas «No disponible en portafolio»); cada marca × tipo activo incluye 5 variantes de gama. Celda 0 = la marca no fabrica ese tipo; en Base de Datos se sugiere el equivalente. Las estadísticas de precio leen el bloque de filas de cada marca en su hoja (SACI/SADI) y las del equipamiento el bloque de cada categoría en la hoja Equipamiento; si reordena los registros, ajuste los rangos.

Sheet Base de Datos SACI
B2: Base de Datos Técnica — SACI · Sistemas de Alarma Contra Intrusos (18 marcas × 16 tipos × 5 variantes)
B4: N° | C4: Marca | D4: Nivel | E4: País | F4: Tipo de Dispositivo | G4: Modelo | H4: Capacidad / Alcance | I4: Tecnología de Detección | J4: Anti-Falsa Alarma / Inmunidad | K4: Comunicación de Eventos | L4: Protocolo / Frecuencia | M4: Alimentación | N4: Consumo | O4: Protección | P4: Temp. Operación | Q4: Dimensiones | R4: Peso | S4: Certificaciones | T4: Uso Recomendado | U4: Precio Ref. (USD) | V4: Proveedor | W4: Stock | X4: Observaciones | Y4: Consumo en Reposo (A) | Z4: Consumo en Alarma (A) | AA4: Tensión de Alimentación (V) | AB4: Protocolos Compatibles | AC4: Centrales Compatibles | AD4: Consumo en Reposo de la Central (A) | AE4: Consumo en Alarma de la Central (A) | AF4: Corriente Nominal de la Fuente (A) | AG4: Zonas de la Central | AH4: Particiones | AI4: Área de Cobertura (m²) | AJ4: Radio de Cobertura (m) | AK4: Alcance (m) | AL4: Apertura del Sector (grados) | AM4: Forma de Cobertura | AN4: Potencia Acústica (W) | AO4: Altura Mínima de Montaje (m) | AP4: Altura Máxima de Montaje (m)
B5: 1 | C5: Honeywell Security | D5: Alta | E5: EE. UU. | F5: Panel híbrido | G5: VISTA-20P | H5: 128 zonas / 8 particiones | I5: Híbrido: 8 zonas alámbricas de base + bus ECP | J5: Auto-Stay / Instant; detección de sabotaje por zona | K5: Contact ID a central o CSDC | L5: Contact ID / SIA DC-09 (AlarmNet) | M5: 16.5 VAC 40 VA · batería 12 V 7 Ah | N5: 700 mA máx con respaldo | O5: — | P5: 0 °C a +49 °C | Q5: 312 × 360 × 80 mm | R5: 3.4 kg | S5: UL 1023/1610, CE, FCC | T5: Residencial y comercial mediano | U5: 145 | X5: Variante económica de la gama | Y5: 0.08 | Z5: 0.7 | AA5: 12 | AB5: Contact ID / SIA DC-09 (AlarmNet) | AC5: Central maestra — admite periféricos del ecosistema VISTA/ProA7 (bus ECP) | AD5: 0.08 | AE5: 0.7 | AF5: 1.7 | AG5: 8 | AH5: 2 | AI5: N/A | AJ5: N/A | AK5: N/A | AL5: N/A | AM5: N/A | AN5: N/A | AO5: N/A | AP5: N/A
B6: 2 | C6: Honeywell Security | D6: Alta | E6: EE. UU. | F6: Panel híbrido | G6: VISTA-48LA | H6: 128 zonas / 8 particiones | I6: Híbrido: 8 zonas alámbricas de base + bus ECP | J6: Auto-Stay / Instant; detección de sabotaje por zona | K6: Contact ID a central o CSDC | L6: Contact ID / SIA DC-09 (AlarmNet) | M6: 16.5 VAC 40 VA · batería 12 V 7 Ah | N6: 700 mA máx con respaldo | O6: — | P6: 0 °C a +49 °C | Q6: 312 × 360 × 80 mm | R6: 3.4 kg | S6: UL 1023/1610, CE, FCC | T6: Residencial y comercial mediano | U6: 220 | X6: Gama de entrada | Y6: 0.079 | Z6: 0.7 | AA6: 12 | AB6: Contact ID / SIA DC-09 (AlarmNet) | AC6: Central maestra — admite periféricos del ecosistema VISTA/ProA7 (bus ECP) | AD6: 0.079 | AE6: 0.7 | AF6: 3 | AG6: 48 | AH6: 4 | AI6: N/A | AJ6: N/A | AK6: N/A | AL6: N/A | AM6: N/A | AN6: N/A | AO6: N/A | AP6: N/A
B7: 3 | C7: Honeywell Security | D7: Alta | E7: EE. UU. | F7: Panel híbrido | G7: VISTA-128BPT | H7: 128 zonas / 8 particiones | I7: Híbrido: 8 zonas alámbricas de base + bus ECP | J7: Auto-Stay / Instant; detección de sabotaje por zona | K7: Contact ID a central o CSDC | L7: Contact ID / SIA DC-09 (AlarmNet) | M7: 16.5 VAC 40 VA · batería 12 V 7 Ah | N7: 700 mA máx con respaldo | O7: — | P7: 0 °C a +49 °C | Q7: 312 × 360 × 80 mm | R7: 3.4 kg | S7: UL 1023/1610, CE, FCC | T7: Residencial y comercial mediano | U7: 295 | X7: Panel clásico del mercado, expansión modular ECP | Y7: 0.101 | Z7: 0.7 | AA7: 12 | AB7: Contact ID / SIA DC-09 (AlarmNet) | AC7: Central maestra — admite periféricos del ecosistema VISTA/ProA7 (bus ECP) | AD7: 0.101 | AE7: 0.7 | AF7: 3.5 | AG7: 128 | AH7: 8 | AI7: N/A | AJ7: N/A | AK7: N/A | AL7: N/A | AM7: N/A | AN7: N/A | AO7: N/A | AP7: N/A
B8: 4 | C8: Honeywell Security | D8: Alta | E8: EE. UU. | F8: Panel híbrido | G8: VISTA-128FBP | H8: 128 zonas / 8 particiones | I8: Híbrido: 8 zonas alámbricas de base + bus ECP | J8: Auto-Stay / Instant; detección de sabotaje por zona | K8: Contact ID a central o CSDC | L8: Contact ID / SIA DC-09 (AlarmNet) | M8: 16.5 VAC 40 VA · batería 12 V 7 Ah | N8: 700 mA máx con respaldo | O8: — | P8: 0 °C a +49 °C | Q8: 312 × 360 × 80 mm | R8: 3.4 kg | S8: UL 1023/1610, CE, FCC | T8: Residencial y comercial mediano | U8: 440 | X8: Capacidad y rendimiento mejorados | Y8: 0.054 | Z8: 0.7 | AA8: 12 | AB8: Contact ID / SIA DC-09 (AlarmNet) | AC8: Central maestra — admite periféricos del ecosistema VISTA/ProA7 (bus ECP) | AD8: 0.054 | AE8: 0.7 | AF8: 3.5 | AG8: 128 | AH8: 8 | AI8: N/A | AJ8: N/A | AK8: N/A | AL8: N/A | AM8: N/A | AN8: N/A | AO8: N/A | AP8: N/A
B9: 5 | C9: Honeywell Security | D9: Alta | E9: EE. UU. | F9: Panel híbrido | G9: ProA7Plus | H9: 128 zonas / 8 particiones | I9: Híbrido: 8 zonas alámbricas de base + bus ECP | J9: Auto-Stay / Instant; detección de sabotaje por zona | K9: Contact ID a central o CSDC | L9: Contact ID / SIA DC-09 (AlarmNet) | M9: 16.5 VAC 40 VA · batería 12 V 7 Ah | N9: 700 mA máx con respaldo | O9: — | P9: 0 °C a +49 °C | Q9: 312 × 360 × 80 mm | R9: 3.4 kg | S9: UL 1023/1610, CE, FCC | T9: Residencial y comercial mediano | U9: 645 | X9: Tope de gama — máxima especificación | Y9: 0.079 | Z9: 0.7 | AA9: 12 | AB9: Contact ID / SIA DC-09 (AlarmNet) | AC9: Central maestra — admite periféricos del ecosistema VISTA/ProA7 (bus ECP) | AD9: 0.079 | AE9: 0.7 | AF9: 3.5 | AG9: 100 | AH9: 4 | AI9: N/A | AJ9: N/A | AK9: N/A | AL9: N/A | AM9: N/A | AN9: N/A | AO9: N/A | AP9: N/A
B10: 6 | C10: Honeywell Security | D10: Alta | E10: EE. UU. | F10: Panel alámbrico | G10: VISTA-20P | H10: 48 zonas / 4 particiones | I10: Alámbrico con expansión inalámbrica 5800 opcional | J10: Detección de sabotaje, salida PGM programable | K10: Contact ID integrado (dialer 56k) | L10: Contact ID / SIA DC-09 (AlarmNet) | M10: 16.5 VAC 40 VA · batería 12 V 7 Ah | N10: 600 mA máx | O10: — | P10: 0 °C a +49 °C | Q10: 262 × 300 × 78 mm | R10: 2.6 kg | S10: UL 1023/1610, CE, FCC | T10: Residencial y PYME | U10: 85 | X10: Variante económica de la gama | Y10: 0.08 | Z10: 0.6 | AA10: 12 | AB10: Contact ID / SIA DC-09 (AlarmNet) | AC10: Central maestra — admite periféricos del ecosistema VISTA/ProA7 (bus ECP) | AD10: 0.08 | AE10: 0.6 | AF10: 1.7 | AG10: 8 | AH10: 2 | AI10: N/A | AJ10: N/A | AK10: N/A | AL10: N/A | AM10: N/A | AN10: N/A | AO10: N/A | AP10: N/A
B11: 7 | C11: Honeywell Security | D11: Alta | E11: EE. UU. | F11: Panel alámbrico | G11: VISTA-48LA | H11: 48 zonas / 4 particiones | I11: Alámbrico con expansión inalámbrica 5800 opcional | J11: Detección de sabotaje, salida PGM programable | K11: Contact ID integrado (dialer 56k) | L11: Contact ID / SIA DC-09 (AlarmNet) | M11: 16.5 VAC 40 VA · batería 12 V 7 Ah | N11: 600 mA máx | O11: — | P11: 0 °C a +49 °C | Q11: 262 × 300 × 78 mm | R11: 2.6 kg | S11: UL 1023/1610, CE, FCC | T11: Residencial y PYME | U11: 130 | X11: Gama de entrada | Y11: 0.079 | Z11: 0.6 | AA11: 12 | AB11: Contact ID / SIA DC-09 (AlarmNet) | AC11: Central maestra — admite periféricos del ecosistema VISTA/ProA7 (bus ECP) | AD11: 0.079 | AE11: 0.6 | AF11: 3 | AG11: 48 | AH11: 4 | AI11: N/A | AJ11: N/A | AK11: N/A | AL11: N/A | AM11: N/A | AN11: N/A | AO11: N/A | AP11: N/A
B12: 8 | C12: Honeywell Security | D12: Alta | E12: EE. UU. | F12: Panel alámbrico | G12: VISTA-128BPT | H12: 48 zonas / 4 particiones | I12: Alámbrico con expansión inalámbrica 5800 opcional | J12: Detección de sabotaje, salida PGM programable | K12: Contact ID integrado (dialer 56k) | L12: Contact ID / SIA DC-09 (AlarmNet) | M12: 16.5 VAC 40 VA · batería 12 V 7 Ah | N12: 600 mA máx | O12: — | P12: 0 °C a +49 °C | Q12: 262 × 300 × 78 mm | R12: 2.6 kg | S12: UL 1023/1610, CE, FCC | T12: Residencial y PYME | U12: 175 | X12: Versión latinoamericana del VISTA 48 | Y12: 0.101 | Z12: 0.6 | AA12: 12 | AB12: Contact ID / SIA DC-09 (AlarmNet) | AC12: Central maestra — admite periféricos del ecosistema VISTA/ProA7 (bus ECP) | AD12: 0.101 | AE12: 0.6 | AF12: 3.5 | AG12: 128 | AH12: 8 | AI12: N/A | AJ12: N/A | AK12: N/A | AL12: N/A | AM12: N/A | AN12: N/A | AO12: N/A | AP12: N/A
B13: 9 | C13: Honeywell Security | D13: Alta | E13: EE. UU. | F13: Panel alámbrico | G13: VISTA-250FBP | H13: 48 zonas / 4 particiones | I13: Alámbrico con expansión inalámbrica 5800 opcional | J13: Detección de sabotaje, salida PGM programable | K13: Contact ID integrado (dialer 56k) | L13: Contact ID / SIA DC-09 (AlarmNet) | M13: 16.5 VAC 40 VA · batería 12 V 7 Ah | N13: 600 mA máx | O13: — | P13: 0 °C a +49 °C | Q13: 262 × 300 × 78 mm | R13: 2.6 kg | S13: UL 1023/1610, CE, FCC | T13: Residencial y PYME | U13: 260 | X13: Capacidad y rendimiento mejorados | Y13: 0.102 | Z13: 0.6 | AA13: 12 | AB13: Contact ID / SIA DC-09 (AlarmNet) | AC13: Central maestra — admite periféricos del ecosistema VISTA/ProA7 (bus ECP) | AD13: 0.102 | AE13: 0.6 | AF13: 3.5 | AG13: 250 | AH13: 8 | AI13: N/A | AJ13: N/A | AK13: N/A | AL13: N/A | AM13: N/A | AN13: N/A | AO13: N/A | AP13: N/A
B14: 10 | C14: Honeywell Security | D14: Alta | E14: EE. UU. | F14: Panel alámbrico | G14: ProA7Plus | H14: 48 zonas / 4 particiones | I14: Alámbrico con expansión inalámbrica 5800 opcional | J14: Detección de sabotaje, salida PGM programable | K14: Contact ID integrado (dialer 56k) | L14: Contact ID / SIA DC-09 (AlarmNet) | M14: 16.5 VAC 40 VA · batería 12 V 7 Ah | N14: 600 mA máx | O14: — | P14: 0 °C a +49 °C | Q14: 262 × 300 × 78 mm | R14: 2.6 kg | S14: UL 1023/1610, CE, FCC | T14: Residencial y PYME | U14: 385 | X14: Tope de gama — máxima especificación | Y14: 0.079 | Z14: 0.6 | AA14: 12 | AB14: Contact ID / SIA DC-09 (AlarmNet) | AC14: Central maestra — admite periféricos del ecosistema VISTA/ProA7 (bus ECP) | AD14: 0.079 | AE14: 0.6 | AF14: 3.5 | AG14: 100 | AH14: 4 | AI14: N/A | AJ14: N/A | AK14: N/A | AL14: N/A | AM14: N/A | AN14: N/A | AO14: N/A | AP14: N/A
B15: 11 | C15: Honeywell Security | D15: Alta | E15: EE. UU. | F15: Panel inalámbrico / Hub | G15: ProA7 | H15: Hasta 100 zonas inalámbricas | I15: Inalámbrico 319.5 MHz con radio SiX | J15: Cifrado SiX Two-Way, foto-verificación | K15: LTE + Wi-Fi integrado (AlarmNet) | L15: Contact ID / SIA DC-09 (AlarmNet) | M15: 26 VAC 40 VA · batería 12 V | N15: 450 mA máx | O15: — | P15: 0 °C a +49 °C | Q15: 250 × 230 × 75 mm | R15: 2.2 kg | S15: UL 1023/1610, CE, FCC | T15: Residencial smart | U15: 130 | X15: Variante económica de la gama | Y15: 0.075 | Z15: 0.45 | AA15: 12 | AB15: Contact ID / SIA DC-09 (AlarmNet) | AC15: Central maestra — admite periféricos del ecosistema VISTA/ProA7 (bus ECP) | AD15: 0.075 | AE15: 0.45 | AF15: 2 | AG15: 100 | AH15: 4 | AI15: N/A | AJ15: N/A | AK15: N/A | AL15: N/A | AM15: N/A | AN15: N/A | AO15: N/A | AP15: N/A
B16: 12 | C16: Honeywell Security | D16: Alta | E16: EE. UU. | F16: Panel inalámbrico / Hub | G16: ProA7Plus | H16: Hasta 100 zonas inalámbricas | I16: Inalámbrico 319.5 MHz con radio SiX | J16: Cifrado SiX Two-Way, foto-verificación | K16: LTE + Wi-Fi integrado (AlarmNet) | L16: Contact ID / SIA DC-09 (AlarmNet) | M16: 26 VAC 40 VA · batería 12 V | N16: 450 mA máx | O16: — | P16: 0 °C a +49 °C | Q16: 250 × 230 × 75 mm | R16: 2.2 kg | S16: UL 1023/1610, CE, FCC | T16: Residencial smart | U16: 195 | X16: Gama de entrada | Y16: 0.079 | Z16: 0.45 | AA16: 12 | AB16: Contact ID / SIA DC-09 (AlarmNet) | AC16: Central maestra — admite periféricos del ecosistema VISTA/ProA7 (bus ECP) | AD16: 0.079 | AE16: 0.45 | AF16: 2 | AG16: 100 | AH16: 4 | AI16: N/A | AJ16: N/A | AK16: N/A | AL16: N/A | AM16: N/A | AN16: N/A | AO16: N/A | AP16: N/A
... B19: 15 | C19: Honeywell Security | D19: Alta | E19: EE. UU. | F19: Panel inalámbrico / Hub | G19: L5000C | H19: Hasta 100 zonas inalámbricas | I19: Inalámbrico 319.5 MHz con radio SiX | J19: Cifrado SiX Two-Way, foto-verificación | K19: LTE + Wi-Fi integrado (AlarmNet) | L19: Contact ID / SIA DC-09 (AlarmNet) | M19: 26 VAC 40 VA · batería 12 V | N19: 450 mA máx | O19: — | P19: 0 °C a +49 °C | Q19: 250 × 230 × 75 mm | R19: 2.2 kg | S19: UL 1023/1610, CE, FCC | T19: Residencial smart | U19: 580 | X19: Tope de gama — máxima especificación | Y19: 0.055 | Z19: 0.45 | AA19: 12 | AB19: Contact ID / SIA DC-09 (AlarmNet) | AC19: Central maestra — admite periféricos del ecosistema VISTA/ProA7 (bus ECP) | AD19: 0.055 | AE19: 0.45 | AF19: 2 | AG19: 100 | AH19: 4 | AI19: N/A | AJ19: N/A | AK19: N/A | AL19: N/A | AM19: N/A | AN19: N/A | AO19: N/A | AP19: N/A
B20: 16 | C20: Honeywell Security | D20: Alta | E20: EE. UU. | F20: Teclado de control | G20: 6150 | H20: Controla hasta 48 zonas del sistema | I20: Teclado alfanumérico LCD 2×16 | J20: Transceptor 5800 integrado para zonas inalámbricas | K20: Bus ECP | L20: Contact ID / SIA DC-09 (AlarmNet) | M20: 12 VDC desde panel | N20: 110 mA | O20: — | P20: 0 °C a +49 °C | Q20: 146 × 111 × 32 mm | R20: 310 g | S20: UL 1023/1610, CE, FCC | T20: Uso general | U20: 45 | X20: Variante económica de la gama | Y20: 0.039 | Z20: 0.075 | AA20: 12 | AB20: Contact ID / SIA DC-09 (AlarmNet) | AC20: Centrales VISTA/ProA7 (bus ECP) (mismo bus) | AD20: N/A | AE20: N/A | AF20: N/A | AG20: N/A | AH20: N/A | AI20: N/A | AJ20: N/A | AK20: N/A | AL20: N/A | AM20: N/A | AN20: N/A | AO20: 1.2 | AP20: 1.6
B21: 17 | C21: Honeywell Security | D21: Alta | E21: EE. UU. | F21: Teclado de control | G21: 6150RF | H21: Controla hasta 48 zonas del sistema | I21: Teclado alfanumérico LCD 2×16 | J21: Transceptor 5800 integrado para zonas inalámbricas | K21: Bus ECP | L21: Contact ID / SIA DC-09 (AlarmNet) | M21: 12 VDC desde panel | N21: 110 mA | O21: — | P21: 0 °C a +49 °C | Q21: 146 × 111 × 32 mm | R21: 310 g | S21: UL 1023/1610, CE, FCC | T21: Uso general | U21: 70 | X21: Gama de entrada | Y21: 0.048 | Z21: 0.09 | AA21: 12 | AB21: Contact ID / SIA DC-09 (AlarmNet) | AC21: Centrales VISTA/ProA7 (bus ECP) (mismo bus) | AD21: N/A | AE21: N/A | AF21: N/A | AG21: N/A | AH21: N/A | AI21: N/A | AJ21: N/A | AK21: N/A | AL21: N/A | AM21: N/A | AN21: N/A | AO21: 1.2 | AP21: 1.6
B22: 18 | C22: Honeywell Security | D22: Alta | E22: EE. UU. | F22: Teclado de control | G22: 6160RF | H22: Controla hasta 48 zonas del sistema | I22: Teclado alfanumérico LCD 2×16 | J22: Transceptor 5800 integrado para zonas inalámbricas | K22: Bus ECP | L22: Contact ID / SIA DC-09 (AlarmNet) | M22: 12 VDC desde panel | N22: 110 mA | O22: — | P22: 0 °C a +49 °C | Q22: 146 × 111 × 32 mm | R22: 310 g | S22: UL 1023/1610, CE, FCC | T22: Uso general | U22: 95 | X22: Teclado premium con proximity opcional | Y22: 0.046 | Z22: 0.087 | AA22: 12 | AB22: Contact ID / SIA DC-09 (AlarmNet) | AC22: Centrales VISTA/ProA7 (bus ECP) (mismo bus) | AD22: N/A | AE22: N/A | AF22: N/A | AG22: N/A | AH22: N/A | AI22: N/A | AJ22: N/A | AK22: N/A | AL22: N/A | AM22: N/A | AN22: N/A | AO22: 1.2 | AP22: 1.6
B23: 19 | C23: Honeywell Security | D23: Alta | E23: EE. UU. | F23: Teclado de control | G23: 6270CV | H23: Controla hasta 48 zonas del sistema | I23: Teclado alfanumérico LCD 2×16 | J23: Transceptor 5800 integrado para zonas inalámbricas | K23: Bus ECP | L23: Contact ID / SIA DC-09 (AlarmNet) | M23: 12 VDC desde panel | N23: 110 mA | O23: — | P23: 0 °C a +49 °C | Q23: 146 × 111 × 32 mm | R23: 310 g | S23: UL 1023/1610, CE, FCC | T23: Uso general | U23: 140 | X23: Capacidad y rendimiento mejorados | Y23: 0.031 | Z23: 0.062 | AA23: 12 | AB23: Contact ID / SIA DC-09 (AlarmNet) | AC23: Centrales VISTA/ProA7 (bus ECP) (mismo bus) | AD23: N/A | AE23: N/A | AF23: N/A | AG23: N/A | AH23: N/A | AI23: N/A | AJ23: N/A | AK23: N/A | AL23: N/A | AM23: N/A | AN23: N/A | AO23: 1.2 | AP23: 1.6
B24: 20 | C24: Honeywell Security | D24: Alta | E24: EE. UU. | F24: Teclado de control | G24: Tuxedo Touch | H24: Controla hasta 48 zonas del sistema | I24: Teclado alfanumérico LCD 2×16 | J24: Transceptor 5800 integrado para zonas inalámbricas | K24: Bus ECP | L24: Contact ID / SIA DC-09 (AlarmNet) | M24: 12 VDC desde panel | N24: 110 mA | O24: — | P24: 0 °C a +49 °C | Q24: 146 × 111 × 32 mm | R24: 310 g | S24: UL 1023/1610, CE, FCC | T24: Uso general | U24: 205 | X24: Tope de gama — máxima especificación | Y24: 0.041 | Z24: 0.078 | AA24: 12 | AB24: Contact ID / SIA DC-09 (AlarmNet) | AC24: Centrales VISTA/ProA7 (bus ECP) (mismo bus) | AD24: N/A | AE24: N/A | AF24: N/A | AG24: N/A | AH24: N/A | AI24: N/A | AJ24: N/A | AK24: N/A | AL24: N/A | AM24: N/A | AN24: N/A | AO24: 1.2 | AP24: 1.6
B25: 21 | C25: Honeywell Security | D25: Alta | E25: EE. UU. | F25: Detector PIR interior | G25: IS-2120 | H25: 8 m · 90° | I25: PIR doble elemento con procesamiento T | J25: Inmunidad a mascotas hasta 36 kg (lente opcional) | K25: Zona alámbrica | L25: Contact ID / SIA DC-09 (AlarmNet) | M25: 12 VDC | N25: 14 mA | O25: — | P25: 0 °C a +49 °C | Q25: 80 × 50 × 38 mm | R25: 85 g | S25: UL 1023/1610, CE, FCC | T25: Interior salas y pasillos | U25: 14 | X25: Variante económica de la gama | Y25: 0.009 | Z25: 0.013 | AA25: 12 | AB25: Contact ID / SIA DC-09 (AlarmNet) | AC25: Zona 12 V universal — centrales VISTA/ProA7 (bus ECP) y compatibles | AD25: N/A | AE25: N/A | AF25: N/A | AG25: N/A | AH25: N/A | AI25: N/A | AJ25: 8 | AK25: N/A | AL25: 90 | AM25: Volumétrica rectangular (lentes múltiples) | AN25: N/A | AO25: 2 | AP25: 2.7
B26: 22 | C26: Honeywell Security | D26: Alta | E26: EE. UU. | F26: Detector PIR interior | G26: IS-2135 | H26: 10 m · 90° | I26: PIR doble elemento con procesamiento T | J26: Inmunidad a mascotas hasta 36 kg (lente opcional) | K26: Zona alámbrica | L26: Contact ID / SIA DC-09 (AlarmNet) | M26: 12 VDC | N26: 14 mA | O26: — | P26: 0 °C a +49 °C | Q26: 80 × 50 × 38 mm | R26: 85 g | S26: UL 1023/1610, CE, FCC | T26: Interior salas y pasillos | U26: 20 | X26: Gama de entrada | Y26: 0.011 | Z26: 0.016 | AA26: 12 | AB26: Contact ID / SIA DC-09 (AlarmNet) | AC26: Zona 12 V universal — centrales VISTA/ProA7 (bus ECP) y compatibles | AD26: N/A | AE26: N/A | AF26: N/A | AG26: N/A | AH26: N/A | AI26: N/A | AJ26: 10 | AK26: N/A | AL26: 90 | AM26: Volumétrica rectangular (lentes múltiples) | AN26: N/A | AO26: 2 | AP26: 2.7
B27: 23 | C27: Honeywell Security | D27: Alta | E27: EE. UU. | F27: Detector PIR interior | G27: IS-215T | H27: 12 m · 90° | I27: PIR doble elemento con procesamiento T | J27: Inmunidad a mascotas hasta 36 kg (lente opcional) | K27: Zona alámbrica | L27: Contact ID / SIA DC-09 (AlarmNet) | M27: 12 VDC | N27: 14 mA | O27: — | P27: 0 °C a +49 °C | Q27: 80 × 50 × 38 mm | R27: 85 g | S27: UL 1023/1610, CE, FCC | T27: Interior salas y pasillos | U27: 25 | X27: Lente espejo Fresnel reemplazable | Y27: 0.011 | Z27: 0.015 | AA27: 12 | AB27: Contact ID / SIA DC-09 (AlarmNet) | AC27: Zona 12 V universal — centrales VISTA/ProA7 (bus ECP) y compatibles | AD27: N/A | AE27: N/A | AF27: N/A | AG27: N/A | AH27: N/A | AI27: N/A | AJ27: 12 | AK27: N/A | AL27: 90 | AM27: Volumétrica rectangular (lentes múltiples) | AN27: N/A | AO27: 2 | AP27: 2.7
B28: 24 | C28: Honeywell Security | D28: Alta | E28: EE. UU. | F28: Detector PIR interior | G28: IS-25100TC | H28: 12 m · 110° | I28: PIR doble elemento con procesamiento T | J28: Inmunidad a mascotas hasta 36 kg (lente opcional) | K28: Zona alámbrica | L28: Contact ID / SIA DC-09 (AlarmNet) | M28: 12 VDC | N28: 14 mA | O28: — | P28: 0 °C a +49 °C | Q28: 80 × 50 × 38 mm | R28: 85 g | S28: UL 1023/1610, CE, FCC | T28: Interior salas y pasillos | U28: 40 | X28: Capacidad y rendimiento mejorados | Y28: 0.008 | Z28: 0.013 | AA28: 12 | AB28: Contact ID / SIA DC-09 (AlarmNet) | AC28: Zona 12 V universal — centrales VISTA/ProA7 (bus ECP) y compatibles | AD28: N/A | AE28: N/A | AF28: N/A | AG28: N/A | AH28: N/A | AI28: N/A | AJ28: 12 | AK28: N/A | AL28: 110 | AM28: Volumétrica rectangular (lentes múltiples) | AN28: N/A | AO28: 2 | AP28: 2.7
B29: 25 | C29: Honeywell Security | D29: Alta | E29: EE. UU. | F29: Detector PIR interior | G29: AURORA PIR | H29: 15 m · 110° | I29: PIR doble elemento con procesamiento T | J29: Inmunidad a mascotas hasta 36 kg (lente opcional) | K29: Zona alámbrica | L29: Contact ID / SIA DC-09 (AlarmNet) | M29: 12 VDC | N29: 14 mA | O29: — | P29: 0 °C a +49 °C | Q29: 80 × 50 × 38 mm | R29: 85 g | S29: UL 1023/1610, CE, FCC | T29: Interior salas y pasillos | U29: 60 | X29: Tope de gama — máxima especificación | Y29: 0.013 | Z29: 0.018 | AA29: 12 | AB29: Contact ID / SIA DC-09 (AlarmNet) | AC29: Zona 12 V universal — centrales VISTA/ProA7 (bus ECP) y compatibles | AD29: N/A | AE29: N/A | AF29: N/A | AG29: N/A | AH29: N/A | AI29: N/A | AJ29: 15 | AK29: N/A | AL29: 110 | AM29: Volumétrica rectangular (lentes múltiples) | AN29: N/A | AO29: 2 | AP29: 2.7
B30: 26 | C30: Honeywell Security | D30: Alta | E30: EE. UU. | F30: PIR inalámbrico | G30: 5800PIR-RES | H30: 8 m · 90° | I30: PIR inalámbrico 319.5 MHz | J30: Pet-inmune hasta 18 kg, supervisión radio | K30: Transmisión 5800 a panel | L30: Contact ID / SIA DC-09 (AlarmNet) | M30: Batería CR123A (3 V) | N30: 15 µA en reposo | O30: — | P30: 0 °C a +49 °C | Q30: 73 × 50 × 40 mm | R30: 70 g | S30: UL 1023/1610, CE, FCC | T30: Interior residencial | U30: 20 | X30: Variante económica de la gama | Y30: 1.889e-05 | Z30: 4.445e-05 | AA30: 3 | AB30: Contact ID / SIA DC-09 (AlarmNet) | AC30: Exclusivo radio de marca: radio SiX/5800 (ProA7, VISTA + transceptor) | AD30: N/A | AE30: N/A | AF30: N/A | AG30: N/A | AH30: N/A | AI30: N/A | AJ30: 8 | AK30: N/A | AL30: 90 | AM30: Volumétrica rectangular (lentes múltiples) | AN30: N/A | AO30: 2 | AP30: 2.7
B31: 27 | C31: Honeywell Security | D31: Alta | E31: EE. UU. | F31: PIR inalámbrico | G31: 5800PIR-OD | H31: 10 m · 90° | I31: PIR inalámbrico 319.5 MHz | J31: Pet-inmune hasta 18 kg, supervisión radio | K31: Transmisión 5800 a panel | L31: Contact ID / SIA DC-09 (AlarmNet) | M31: Batería CR123A (3 V) | N31: 15 µA en reposo | O31: — | P31: 0 °C a +49 °C | Q31: 73 × 50 × 40 mm | R31: 70 g | S31: UL 1023/1610, CE, FCC | T31: Interior residencial | U31: 25 | X31: Gama de entrada | Y31: 1.929e-05 | Z31: 4.516e-05 | AA31: 3 | AB31: Contact ID / SIA DC-09 (AlarmNet) | AC31: Exclusivo radio de marca: radio SiX/5800 (ProA7, VISTA + transceptor) | AD31: N/A | AE31: N/A | AF31: N/A | AG31: N/A | AH31: N/A | AI31: N/A | AJ31: 10 | AK31: N/A | AL31: 90 | AM31: Volumétrica rectangular (lentes múltiples) | AN31: N/A | AO31: 2 | AP31: 2.7
B32: 28 | C32: Honeywell Security | D32: Alta | E32: EE. UU. | F32: PIR inalámbrico | G32: 5800PIR-VEC | H32: 12 m · 90° | I32: PIR inalámbrico 319.5 MHz | J32: Pet-inmune hasta 18 kg, supervisión radio | K32: Transmisión 5800 a panel | L32: Contact ID / SIA DC-09 (AlarmNet) | M32: Batería CR123A (3 V) | N32: 15 µA en reposo | O32: — | P32: 0 °C a +49 °C | Q32: 73 × 50 × 40 mm | R32: 70 g | S32: UL 1023/1610, CE, FCC | T32: Interior residencial | U32: 35 | X32: Montaje pared, esquina o plano sin ajustes | Y32: 1.851e-05 | Z32: 4.377e-05 | AA32: 3 | AB32: Contact ID / SIA DC-09 (AlarmNet) | AC32: Exclusivo radio de marca: radio SiX/5800 (ProA7, VISTA + transceptor) | AD32: N/A | AE32: N/A | AF32: N/A | AG32: N/A | AH32: N/A | AI32: N/A | AJ32: 12 | AK32: N/A | AL32: 90 | AM32: Volumétrica rectangular (lentes múltiples) | AN32: N/A | AO32: 2 | AP32: 2.7
B33: 29 | C33: Honeywell Security | D33: Alta | E33: EE. UU. | F33: PIR inalámbrico | G33: 5800-2 | H33: 12 m · 90° pet | I33: PIR inalámbrico 319.5 MHz | J33: Pet-inmune hasta 18 kg, supervisión radio | K33: Transmisión 5800 a panel | L33: Contact ID / SIA DC-09 (AlarmNet) | M33: Batería CR123A (3 V) | N33: 15 µA en reposo | O33: — | P33: 0 °C a +49 °C | Q33: 73 × 50 × 40 mm | R33: 70 g | S33: UL 1023/1610, CE, FCC | T33: Interior residencial | U33: 55 | X33: Capacidad y rendimiento mejorados | Y33: 1.125e-05 | Z33: 3.08e-05 | AA33: 3 | AB33: Contact ID / SIA DC-09 (AlarmNet) | AC33: Exclusivo radio de marca: radio SiX/5800 (ProA7, VISTA + transceptor) | AD33: N/A | AE33: N/A | AF33: N/A | AG33: N/A | AH33: N/A | AI33: N/A | AJ33: 12 | AK33: N/A | AL33: 90 | AM33: Volumétrica rectangular (lentes múltiples) | AN33: N/A | AO33: 2 | AP33: 2.7
B34: 30 | C34: Honeywell Security | D34: Alta | E34: EE. UU. | F34: PIR inalámbrico | G34: 5898 | H34: 15 m · 90° pet | I34: PIR inalámbrico 319.5 MHz | J34: Pet-inmune hasta 18 kg, supervisión radio | K34: Transmisión 5800 a panel | L34: Contact ID / SIA DC-09 (AlarmNet) | M34: Batería CR123A (3 V) | N34: 15 µA en reposo | O34: — | P34: 0 °C a +49 °C | Q34: 73 × 50 × 40 mm | R34: 70 g | S34: UL 1023/1610, CE, FCC | T34: Interior residencial | U34: 85 | X34: Tope de gama — máxima especificación | Y34: 2.112e-05 | Z34: 4.844e-05 | AA34: 3 | AB34: Contact ID / SIA DC-09 (AlarmNet) | AC34: Exclusivo radio de marca: radio SiX/5800 (ProA7, VISTA + transceptor) | AD34: N/A | AE34: N/A | AF34: N/A | AG34: N/A | AH34: N/A | AI34: N/A | AJ34: 15 | AK34: N/A | AL34: 90 | AM34: Volumétrica rectangular (lentes múltiples) | AN34: N/A | AO34: 2 | AP34: 2.7
B35: 31 | C35: Honeywell Security | D35: Alta | E35: EE. UU. | F35: Doble tecnología / exterior | G35: DT-8035 | H35: 10 m | I35: IR pasivo + microondas (dual tech) | J35: Análisis de señal bidireccional, anti-falsa alarma avanzada | K35: Zona alámbrica | L35: Contact ID / SIA DC-09 (AlarmNet) | M35: 12 VDC | N35: 20 mA | O35: — | P35: 0 °C a +49 °C | Q35: 118 × 70 × 48 mm | R35: 210 g | S35: UL 1023/1610, CE, FCC | T35: Interior hostil (talleres, depósitos) | U35: 25 | X35: Variante económica de la gama | Y35: 0.019 | Z35: 0.029 | AA35: 12 | AB35: Contact ID / SIA DC-09 (AlarmNet) | AC35: Zona 12 V universal — centrales VISTA/ProA7 (bus ECP) y compatibles | AD35: N/A | AE35: N/A | AF35: N/A | AG35: N/A | AH35: N/A | AI35: N/A | AJ35: N/A | AK35: 10 | AL35: 90 | AM35: Volumétrica rectangular (IR + microondas) | AN35: N/A | AO35: 2 | AP35: 3
B36: 32 | C36: Honeywell Security | D36: Alta | E36: EE. UU. | F36: Doble tecnología / exterior | G36: DT-8050 | H36: 12 m | I36: IR pasivo + microondas (dual tech) | J36: Análisis de señal bidireccional, anti-falsa alarma avanzada | K36: Zona alámbrica | L36: Contact ID / SIA DC-09 (AlarmNet) | M36: 12 VDC | N36: 20 mA | O36: — | P36: 0 °C a +49 °C | Q36: 118 × 70 × 48 mm | R36: 210 g | S36: UL 1023/1610, CE, FCC | T36: Interior hostil (talleres, depósitos) | U36: 40 | X36: Gama de entrada | Y36: 0.02 | Z36: 0.03 | AA36: 12 | AB36: Contact ID / SIA DC-09 (AlarmNet) | AC36: Zona 12 V universal — centrales VISTA/ProA7 (bus ECP) y compatibles | AD36: N/A | AE36: N/A | AF36: N/A | AG36: N/A | AH36: N/A | AI36: N/A | AJ36: N/A | AK36: 12 | AL36: 90 | AM36: Volumétrica rectangular (IR + microondas) | AN36: N/A | AO36: 2 | AP36: 3
B37: 33 | C37: Honeywell Security | D37: Alta | E37: EE. UU. | F37: Doble tecnología / exterior | G37: DT-8060 | H37: 12 m · IP54 | I37: IR pasivo + microondas (dual tech) | J37: Análisis de señal bidireccional, anti-falsa alarma avanzada | K37: Zona alámbrica | L37: Contact ID / SIA DC-09 (AlarmNet) | M37: 12 VDC | N37: 20 mA | O37: — | P37: 0 °C a +49 °C | Q37: 118 × 70 × 48 mm | R37: 210 g | S37: UL 1023/1610, CE, FCC | T37: Interior hostil (talleres, depósitos) | U37: 55 | X37: K-band microondas con rango ajustable | Y37: 0.024 | Z37: 0.034 | AA37: 12 | AB37: Contact ID / SIA DC-09 (AlarmNet) | AC37: Zona 12 V universal — centrales VISTA/ProA7 (bus ECP) y compatibles | AD37: N/A | AE37: N/A | AF37: N/A | AG37: N/A | AH37: N/A | AI37: N/A | AJ37: N/A | AK37: 12 | AL37: 90 | AM37: Volumétrica rectangular (IR + microondas) | AN37: N/A | AO37: 2 | AP37: 3
B38: 34 | C38: Honeywell Security | D38: Alta | E38: EE. UU. | F38: Doble tecnología / exterior | G38: IS-312 | H38: 15 m · IP55 | I38: IR pasivo + microondas (dual tech) | J38: Análisis de señal bidireccional, anti-falsa alarma avanzada | K38: Zona alámbrica | L38: Contact ID / SIA DC-09 (AlarmNet) | M38: 12 VDC | N38: 20 mA | O38: — | P38: 0 °C a +49 °C | Q38: 118 × 70 × 48 mm | R38: 210 g | S38: UL 1023/1610, CE, FCC | T38: Interior hostil (talleres, depósitos) | U38: 80 | X38: Capacidad y rendimiento mejorados | Y38: 0.028 | Z38: 0.038 | AA38: 12 | AB38: Contact ID / SIA DC-09 (AlarmNet) | AC38: Zona 12 V universal — centrales VISTA/ProA7 (bus ECP) y compatibles | AD38: N/A | AE38: N/A | AF38: N/A | AG38: N/A | AH38: N/A | AI38: N/A | AJ38: N/A | AK38: 15 | AL38: 90 | AM38: Volumétrica rectangular (IR + microondas) | AN38: N/A | AO38: 2 | AP38: 3
B39: 35 | C39: Honeywell Security | D39: Alta | E39: EE. UU. | F39: Doble tecnología / exterior | G39: AURORA DT | H39: 20 m · IP55 | I39: IR pasivo + microondas (dual tech) | J39: Análisis de señal bidireccional, anti-falsa alarma avanzada | K39: Zona alámbrica | L39: Contact ID / SIA DC-09 (AlarmNet) | M39: 12 VDC | N39: 20 mA | O39: — | P39: 0 °C a +49 °C | Q39: 118 × 70 × 48 mm | R39: 210 g | S39: UL 1023/1610, CE, FCC | T39: Interior hostil (talleres, depósitos) | U39: 120 | X39: Tope de gama — máxima especificación | Y39: 0.027 | Z39: 0.037 | AA39: 12 | AB39: Contact ID / SIA DC-09 (AlarmNet) | AC39: Zona 12 V universal — centrales VISTA/ProA7 (bus ECP) y compatibles | AD39: N/A | AE39: N/A | AF39: N/A | AG39: N/A | AH39: N/A | AI39: N/A | AJ39: N/A | AK39: 20 | AL39: 90 | AM39: Volumétrica rectangular (IR + microondas) | AN39: N/A | AO39: 2 | AP39: 3
B40: 36 | C40: Honeywell Security | D40: Alta | E40: EE. UU. | F40: Contacto magnético | G40: 944 | H40: Disparo 10 mm | I40: Contacto magnético con terminales atornillados | J40: Contacto reed conmutable NA/NC | K40: Zona alámbrica | L40: Contact ID / SIA DC-09 (AlarmNet) | M40: Pasivo (seco) | N40: — | O40: — | P40: 0 °C a +49 °C | Q40: 63 × 12 × 12 mm | R40: 20 g | S40: UL 1023/1610, CE, FCC | T40: Puertas y ventanas | U40: 8 | X40: Variante económica de la gama | Y40: 0 | Z40: 0 | AA40: N/A | AB40: Contact ID / SIA DC-09 (AlarmNet) | AC40: Zona 12 V universal — centrales VISTA/ProA7 (bus ECP) y compatibles | AD40: N/A | AE40: N/A | AF40: N/A | AG40: N/A | AH40: N/A | AI40: N/A | AJ40: N/A | AK40: N/A | AL40: N/A | AM40: Perimetral (apertura de puerta/ventana) | AN40: N/A | AO40: N/A | AP40: N/A
B41: 37 | C41: Honeywell Security | D41: Alta | E41: EE. UU. | F41: Contacto magnético | G41: 943 | H41: Disparo 15 mm | I41: Contacto magnético con terminales atornillados | J41: Contacto reed conmutable NA/NC | K41: Zona alámbrica | L41: Contact ID / SIA DC-09 (AlarmNet) | M41: Pasivo (seco) | N41: — | O41: — | P41: 0 °C a +49 °C | Q41: 63 × 12 × 12 mm | R41: 20 g | S41: UL 1023/1610, CE, FCC | T41: Puertas y ventanas | U41: 8 | X41: Gama de entrada | Y41: 0 | Z41: 0 | AA41: N/A | AB41: Contact ID / SIA DC-09 (AlarmNet) | AC41: Zona 12 V universal — centrales VISTA/ProA7 (bus ECP) y compatibles | AD41: N/A | AE41: N/A | AF41: N/A | AG41: N/A | AH41: N/A | AI41: N/A | AJ41: N/A | AK41: N/A | AL41: N/A | AM41: Perimetral (apertura de puerta/ventana) | AN41: N/A | AO41: N/A | AP41: N/A
B42: 38 | C42: Honeywell Security | D42: Alta | E42: EE. UU. | F42: Contacto magnético | G42: 956RPT | H42: Disparo 20 mm | I42: Contacto magnético con terminales atornillados | J42: Contacto reed conmutable NA/NC | K42: Zona alámbrica | L42: Contact ID / SIA DC-09 (AlarmNet) | M42: Pasivo (seco) | N42: — | O42: — | P42: 0 °C a +49 °C | Q42: 63 × 12 × 12 mm | R42: 20 g | S42: UL 1023/1610, CE, FCC | T42: Puertas y ventanas | U42: 8 | X42: Incluye imán y carcasa con sabotaje | Y42: 0 | Z42: 0 | AA42: N/A | AB42: Contact ID / SIA DC-09 (AlarmNet) | AC42: Zona 12 V universal — centrales VISTA/ProA7 (bus ECP) y compatibles | AD42: N/A | AE42: N/A | AF42: N/A | AG42: N/A | AH42: N/A | AI42: N/A | AJ42: N/A | AK42: N/A | AL42: N/A | AM42: Perimetral (apertura de puerta/ventana) | AN42: N/A | AO42: N/A | AP42: N/A
B43: 39 | C43: Honeywell Security | D43: Alta | E43: EE. UU. | F43: Contacto magnético | G43: 941-G | H43: Disparo 25 mm | I43: Contacto magnético con terminales atornillados | J43: Contacto reed conmutable NA/NC | K43: Zona alámbrica | L43: Contact ID / SIA DC-09 (AlarmNet) | M43: Pasivo (seco) | N43: — | O43: — | P43: 0 °C a +49 °C | Q43: 63 × 12 × 12 mm | R43: 20 g | S43: UL 1023/1610, CE, FCC | T43: Puertas y ventanas | U43: 12 | X43: Capacidad y rendimiento mejorados | Y43: 0 | Z43: 0 | AA43: N/A | AB43: Contact ID / SIA DC-09 (AlarmNet) | AC43: Zona 12 V universal — centrales VISTA/ProA7 (bus ECP) y compatibles | AD43: N/A | AE43: N/A | AF43: N/A | AG43: N/A | AH43: N/A | AI43: N/A | AJ43: N/A | AK43: N/A | AL43: N/A | AM43: Perimetral (apertura de puerta/ventana) | AN43: N/A | AO43: N/A | AP43: N/A
B44: 40 | C44: Honeywell Security | D44: Alta | E44: EE. UU. | F44: Contacto magnético | G44: 7939WG-WH | H44: Disparo 40 mm | I44: Contacto magnético con terminales atornillados | J44: Contacto reed conmutable NA/NC | K44: Zona alámbrica | L44: Contact ID / SIA DC-09 (AlarmNet) | M44: Pasivo (seco) | N44: — | O44: — | P44: 0 °C a +49 °C | Q44: 63 × 12 × 12 mm | R44: 20 g | S44: UL 1023/1610, CE, FCC | T44: Puertas y ventanas | U44: 18 | X44: Tope de gama — máxima especificación | Y44: 0 | Z44: 0 | AA44: N/A | AB44: Contact ID / SIA DC-09 (AlarmNet) | AC44: Zona 12 V universal — centrales VISTA/ProA7 (bus ECP) y compatibles | AD44: N/A | AE44: N/A | AF44: N/A | AG44: N/A | AH44: N/A | AI44: N/A | AJ44: N/A | AK44: N/A | AL44: N/A | AM44: Perimetral (apertura de puerta/ventana) | AN44: N/A | AO44: N/A | AP44: N/A
B45: 41 | C45: Honeywell Security | D45: Alta | E45: EE. UU. | F45: Ruptura de vidrio | G45: 5150MN | H45: 6 m | I45: Micro-procesamiento de audio (espectro de vidrio) | J45: Filtra compresores, campanas y música | K45: Zona alámbrica | L45: Contact ID / SIA DC-09 (AlarmNet) | M45: 12 VDC | N45: 18 mA | O45: — | P45: 0 °C a +49 °C | Q45: Ø 88 × 28 mm | R45: 130 g | S45: UL 1023/1610, CE, FCC | T45: Interior frente a vidrios | U45: 19 | X45: Variante económica de la gama | Y45: 0.015 | Z45: 0.023 | AA45: 12 | AB45: Contact ID / SIA DC-09 (AlarmNet) | AC45: Zona 12 V universal — centrales VISTA/ProA7 (bus ECP) y compatibles | AD45: N/A | AE45: N/A | AF45: N/A | AG45: N/A | AH45: N/A | AI45: N/A | AJ45: 6 | AK45: N/A | AL45: N/A | AM45: Hemisférica omnidireccional (audio) | AN45: N/A | AO45: 2 | AP45: 4.6
B46: 42 | C46: Honeywell Security | D46: Alta | E46: EE. UU. | F46: Ruptura de vidrio | G46: Flex 100 | H46: 7.6 m | I46: Micro-procesamiento de audio (espectro de vidrio) | J46: Filtra compresores, campanas y música | K46: Zona alámbrica | L46: Contact ID / SIA DC-09 (AlarmNet) | M46: 12 VDC | N46: 18 mA | O46: — | P46: 0 °C a +49 °C | Q46: Ø 88 × 28 mm | R46: 130 g | S46: UL 1023/1610, CE, FCC | T46: Interior frente a vidrios | U46: 25 | X46: Gama de entrada | Y46: 0.019 | Z46: 0.029 | AA46: 12 | AB46: Contact ID / SIA DC-09 (AlarmNet) | AC46: Zona 12 V universal — centrales VISTA/ProA7 (bus ECP) y compatibles | AD46: N/A | AE46: N/A | AF46: N/A | AG46: N/A | AH46: N/A | AI46: N/A | AJ46: 7.6 | AK46: N/A | AL46: N/A | AM46: Hemisférica omnidireccional (audio) | AN46: N/A | AO46: 2 | AP46: 4.6
B47: 43 | C47: Honeywell Security | D47: Alta | E47: EE. UU. | F47: Ruptura de vidrio | G47: FG-730 | H47: 7.6 m filtrado digital | I47: Micro-procesamiento de audio (espectro de vidrio) | J47: Filtra compresores, campanas y música | K47: Zona alámbrica | L47: Contact ID / SIA DC-09 (AlarmNet) | M47: 12 VDC | N47: 18 mA | O47: — | P47: 0 °C a +49 °C | Q47: Ø 88 × 28 mm | R47: 130 g | S47: UL 1023/1610, CE, FCC | T47: Interior frente a vidrios | U47: 35 | X47: Auto-verificación LED y modo de prueba | Y47: 0.013 | Z47: 0.021 | AA47: 12 | AB47: Contact ID / SIA DC-09 (AlarmNet) | AC47: Zona 12 V universal — centrales VISTA/ProA7 (bus ECP) y compatibles | AD47: N/A | AE47: N/A | AF47: N/A | AG47: N/A | AH47: N/A | AI47: N/A | AJ47: 7.6 | AK47: N/A | AL47: N/A | AM47: Hemisférica omnidireccional (audio) | AN47: N/A | AO47: 2 | AP47: 4.6
B48: 44 | C48: Honeywell Security | D48: Alta | E48: EE. UU. | F48: Ruptura de vidrio | G48: 5150WA | H48: 9 m | I48: Micro-procesamiento de audio (espectro de vidrio) | J48: Filtra compresores, campanas y música | K48: Zona alámbrica | L48: Contact ID / SIA DC-09 (AlarmNet) | M48: 12 VDC | N48: 18 mA | O48: — | P48: 0 °C a +49 °C | Q48: Ø 88 × 28 mm | R48: 130 g | S48: UL 1023/1610, CE, FCC | T48: Interior frente a vidrios | U48: 55 | X48: Capacidad y rendimiento mejorados | Y48: 0.016 | Z48: 0.025 | AA48: 12 | AB48: Contact ID / SIA DC-09 (AlarmNet) | AC48: Zona 12 V universal — centrales VISTA/ProA7 (bus ECP) y compatibles | AD48: N/A | AE48: N/A | AF48: N/A | AG48: N/A | AH48: N/A | AI48: N/A | AJ48: 9 | AK48: N/A | AL48: N/A | AM48: Hemisférica omnidireccional (audio) | AN48: N/A | AO48: 2 | AP48: 4.6
B49: 45 | C49: Honeywell Security | D49: Alta | E49: EE. UU. | F49: Ruptura de vidrio | G49: FG-1625 | H49: 9 m filtrado digital | I49: Micro-procesamiento de audio (espectro de vidrio) | J49: Filtra compresores, campanas y música | K49: Zona alámbrica | L49: Contact ID / SIA DC-09 (AlarmNet) | M49: 12 VDC | N49: 18 mA | O49: — | P49: 0 °C a +49 °C | Q49: Ø 88 × 28 mm | R49: 130 g | S49: UL 1023/1610, CE, FCC | T49: Interior frente a vidrios | U49: 80 | X49: Tope de gama — máxima especificación | Y49: 0.013 | Z49: 0.021 | AA49: 12 | AB49: Contact ID / SIA DC-09 (AlarmNet) | AC49: Zona 12 V universal — centrales VISTA/ProA7 (bus ECP) y compatibles | AD49: N/A | AE49: N/A | AF49: N/A | AG49: N/A | AH49: N/A | AI49: N/A | AJ49: 9 | AK49: N/A | AL49: N/A | AM49: Hemisférica omnidireccional (audio) | AN49: N/A | AO49: 2 | AP49: 4.6
B50: 46 | C50: Honeywell Security | D50: Alta | E50: EE. UU. | F50: Sirena exterior | G50: 748LC | H50: 105 dB | I50: Sirena autocontenida con batería de respaldo | J50: Caja hermética anti-sabotaje (tapa y arrancado) | K50: Activación 12 VDC | L50: Contact ID / SIA DC-09 (AlarmNet) | M50: 12 VDC + batería interna 9 V | N50: 280 mA sirena | O50: IP34 | P50: 0 °C a +49 °C | Q50: 270 × 135 × 82 mm | R50: 1.6 kg | S50: UL 1023/1610, CE, FCC | T50: Exterior fachada | U50: 20 | X50: Variante económica de la gama | Y50: 0.011 | Z50: 0.497 | AA50: 12 | AB50: Contact ID / SIA DC-09 (AlarmNet) | AC50: Zona 12 V universal — centrales VISTA/ProA7 (bus ECP) y compatibles | AD50: N/A | AE50: N/A | AF50: N/A | AG50: N/A | AH50: N/A | AI50: N/A | AJ50: N/A | AK50: N/A | AL50: N/A | AM50: N/A | AN50: 23.8 | AO50: 2.5 | AP50: 4.5
B51: 47 | C51: Honeywell Security | D51: Alta | E51: EE. UU. | F51: Sirena exterior | G51: SSX52S | H51: 108 dB | I51: Sirena autocontenida con batería de respaldo | J51: Caja hermética anti-sabotaje (tapa y arrancado) | K51: Activación 12 VDC | L51: Contact ID / SIA DC-09 (AlarmNet) | M51: 12 VDC + batería interna 9 V | N51: 280 mA sirena | O51: IP34 | P51: 0 °C a +49 °C | Q51: 270 × 135 × 82 mm | R51: 1.6 kg | S51: UL 1023/1610, CE, FCC | T51: Exterior fachada | U51: 30 | X51: Gama de entrada | Y51: 0.008 | Z51: 0.374 | AA51: 12 | AB51: Contact ID / SIA DC-09 (AlarmNet) | AC51: Zona 12 V universal — centrales VISTA/ProA7 (bus ECP) y compatibles | AD51: N/A | AE51: N/A | AF51: N/A | AG51: N/A | AH51: N/A | AI51: N/A | AJ51: N/A | AK51: N/A | AL51: N/A | AM51: N/A | AN51: 18.8 | AO51: 2.5 | AP51: 4.5
B52: 48 | C52: Honeywell Security | D52: Alta | E52: EE. UU. | F52: Sirena exterior | G52: AB-4 | H52: 110 dB | I52: Sirena autocontenida con batería de respaldo | J52: Caja hermética anti-sabotaje (tapa y arrancado) | K52: Activación 12 VDC | L52: Contact ID / SIA DC-09 (AlarmNet) | M52: 12 VDC + batería interna 9 V | N52: 280 mA sirena | O52: IP34 | P52: 0 °C a +49 °C | Q52: 270 × 135 × 82 mm | R52: 1.6 kg | S52: UL 1023/1610, CE, FCC | T52: Exterior fachada | U52: 45 | X52: Opción con LED blanco o azul | Y52: 0.01 | Z52: 0.468 | AA52: 12 | AB52: Contact ID / SIA DC-09 (AlarmNet) | AC52: Zona 12 V universal — centrales VISTA/ProA7 (bus ECP) y compatibles | AD52: N/A | AE52: N/A | AF52: N/A | AG52: N/A | AH52: N/A | AI52: N/A | AJ52: N/A | AK52: N/A | AL52: N/A | AM52: N/A | AN52: 22.6 | AO52: 2.5 | AP52: 4.5
B53: 49 | C53: Honeywell Security | D53: Alta | E53: EE. UU. | F53: Sirena exterior | G53: 746SS | H53: 113 dB | I53: Sirena autocontenida con batería de respaldo | J53: Caja hermética anti-sabotaje (tapa y arrancado) | K53: Activación 12 VDC | L53: Contact ID / SIA DC-09 (AlarmNet) | M53: 12 VDC + batería interna 9 V | N53: 280 mA sirena | O53: IP34 | P53: 0 °C a +49 °C | Q53: 270 × 135 × 82 mm | R53: 1.6 kg | S53: UL 1023/1610, CE, FCC | T53: Exterior fachada | U53: 65 | X53: Capacidad y rendimiento mejorados | Y53: 0.008 | Z53: 0.38 | AA53: 12 | AB53: Contact ID / SIA DC-09 (AlarmNet) | AC53: Zona 12 V universal — centrales VISTA/ProA7 (bus ECP) y compatibles | AD53: N/A | AE53: N/A | AF53: N/A | AG53: N/A | AH53: N/A | AI53: N/A | AJ53: N/A | AK53: N/A | AL53: N/A | AM53: N/A | AN53: 19.1 | AO53: 2.5 | AP53: 4.5
B54: 50 | C54: Honeywell Security | D54: Alta | E54: EE. UU. | F54: Sirena exterior | G54: SS-52 | H54: 118 dB | I54: Sirena autocontenida con batería de respaldo | J54: Caja hermética anti-sabotaje (tapa y arrancado) | K54: Activación 12 VDC | L54: Contact ID / SIA DC-09 (AlarmNet) | M54: 12 VDC + batería interna 9 V | N54: 280 mA sirena | O54: IP34 | P54: 0 °C a +49 °C | Q54: 270 × 135 × 82 mm | R54: 1.6 kg | S54: UL 1023/1610, CE, FCC | T54: Exterior fachada | U54: 100 | X54: Tope de gama — máxima especificación | Y54: 0.007 | Z54: 0.362 | AA54: 12 | AB54: Contact ID / SIA DC-09 (AlarmNet) | AC54: Zona 12 V universal — centrales VISTA/ProA7 (bus ECP) y compatibles | AD54: N/A | AE54: N/A | AF54: N/A | AG54: N/A | AH54: N/A | AI54: N/A | AJ54: N/A | AK54: N/A | AL54: N/A | AM54: N/A | AN54: 18.3 | AO54: 2.5 | AP54: 4.5
B55: 51 | C55: Honeywell Security | D55: Alta | E55: EE. UU. | F55: Sirena interior | G55: 7473 | H55: 95 dB | I55: Sirena autocontenida compacta | J55: Tapa anti-sabotaje, tono estándar | K55: Activación 12 VDC | L55: Contact ID / SIA DC-09 (AlarmNet) | M55: 12 VDC | N55: 350 mA | O55: — | P55: 0 °C a +49 °C | Q55: 110 × 110 × 55 mm | R55: 280 g | S55: UL 1023/1610, CE, FCC | T55: Interior pasillo/cuarto técnico | U55: 13 | X55: Variante económica de la gama | Y55: 0.004 | Z55: 0.243 | AA55: 12 | AB55: Contact ID / SIA DC-09 (AlarmNet) | AC55: Zona 12 V universal — centrales VISTA/ProA7 (bus ECP) y compatibles | AD55: N/A | AE55: N/A | AF55: N/A | AG55: N/A | AH55: N/A | AI55: N/A | AJ55: N/A | AK55: N/A | AL55: N/A | AM55: N/A | AN55: 13.7 | AO55: 2 | AP55: 3
B56: 52 | C56: Honeywell Security | D56: Alta | E56: EE. UU. | F56: Sirena interior | G56: 719 | H56: 100 dB | I56: Sirena autocontenida compacta | J56: Tapa anti-sabotaje, tono estándar | K56: Activación 12 VDC | L56: Contact ID / SIA DC-09 (AlarmNet) | M56: 12 VDC | N56: 350 mA | O56: — | P56: 0 °C a +49 °C | Q56: 110 × 110 × 55 mm | R56: 280 g | S56: UL 1023/1610, CE, FCC | T56: Interior pasillo/cuarto técnico | U56: 20 | X56: Gama de entrada | Y56: 0.007 | Z56: 0.325 | AA56: 12 | AB56: Contact ID / SIA DC-09 (AlarmNet) | AC56: Zona 12 V universal — centrales VISTA/ProA7 (bus ECP) y compatibles | AD56: N/A | AE56: N/A | AF56: N/A | AG56: N/A | AH56: N/A | AI56: N/A | AJ56: N/A | AK56: N/A | AL56: N/A | AM56: N/A | AN56: 17 | AO56: 2 | AP56: 3
B57: 53 | C57: Honeywell Security | D57: Alta | E57: EE. UU. | F57: Sirena interior | G57: 7415 | H57: 102 dB | I57: Sirena autocontenida compacta | J57: Tapa anti-sabotaje, tono estándar | K57: Activación 12 VDC | L57: Contact ID / SIA DC-09 (AlarmNet) | M57: 12 VDC | N57: 350 mA | O57: — | P57: 0 °C a +49 °C | Q57: 110 × 110 × 55 mm | R57: 280 g | S57: UL 1023/1610, CE, FCC | T57: Interior pasillo/cuarto técnico | U57: 25 | X57: Montaje en pared o techo | Y57: 0.007 | Z57: 0.31 | AA57: 12 | AB57: Contact ID / SIA DC-09 (AlarmNet) | AC57: Zona 12 V universal — centrales VISTA/ProA7 (bus ECP) y compatibles | AD57: N/A | AE57: N/A | AF57: N/A | AG57: N/A | AH57: N/A | AI57: N/A | AJ57: N/A | AK57: N/A | AL57: N/A | AM57: N/A | AN57: 16.4 | AO57: 2 | AP57: 3
B58: 54 | C58: Honeywell Security | D58: Alta | E58: EE. UU. | F58: Sirena interior | G58: Wave-2 | H58: 105 dB | I58: Sirena autocontenida compacta | J58: Tapa anti-sabotaje, tono estándar | K58: Activación 12 VDC | L58: Contact ID / SIA DC-09 (AlarmNet) | M58: 12 VDC | N58: 350 mA | O58: — | P58: 0 °C a +49 °C | Q58: 110 × 110 × 55 mm | R58: 280 g | S58: UL 1023/1610, CE, FCC | T58: Interior pasillo/cuarto técnico | U58: 35 | X58: Capacidad y rendimiento mejorados | Y58: 0.008 | Z58: 0.355 | AA58: 12 | AB58: Contact ID / SIA DC-09 (AlarmNet) | AC58: Zona 12 V universal — centrales VISTA/ProA7 (bus ECP) y compatibles | AD58: N/A | AE58: N/A | AF58: N/A | AG58: N/A | AH58: N/A | AI58: N/A | AJ58: N/A | AK58: N/A | AL58: N/A | AM58: N/A | AN58: 18.2 | AO58: 2 | AP58: 3
B59: 55 | C59: Honeywell Security | D59: Alta | E59: EE. UU. | F59: Sirena interior | G59: WS-100 | H59: 110 dB | I59: Sirena autocontenida compacta | J59: Tapa anti-sabotaje, tono estándar | K59: Activación 12 VDC | L59: Contact ID / SIA DC-09 (AlarmNet) | M59: 12 VDC | N59: 350 mA | O59: — | P59: 0 °C a +49 °C | Q59: 110 × 110 × 55 mm | R59: 280 g | S59: UL 1023/1610, CE, FCC | T59: Interior pasillo/cuarto técnico | U59: 55 | X59: Tope de gama — máxima especificación | Y59: 0.003 | Z59: 0.206 | AA59: 12 | AB59: Contact ID / SIA DC-09 (AlarmNet) | AC59: Zona 12 V universal — centrales VISTA/ProA7 (bus ECP) y compatibles | AD59: N/A | AE59: N/A | AF59: N/A | AG59: N/A | AH59: N/A | AI59: N/A | AJ59: N/A | AK59: N/A | AL59: N/A | AM59: N/A | AN59: 12.2 | AO59: 2 | AP59: 3
B60: 56 | C60: Honeywell Security | D60: Alta | E60: EE. UU. | F60: Comunicador de eventos | G60: 7845i-ENT | H60: Solo IP | I60: Transmisor de eventos AlarmNet | J60: Cifrado AES 128-bit, supervisión remota | K60: Contact ID / SIA sobre IP y LTE | L60: Contact ID / SIA DC-09 (AlarmNet) | M60: 12 VDC desde panel | N60: 95 mA IP / 190 mA LTE | O60: — | P60: 0 °C a +49 °C | Q60: 88 × 152 × 30 mm | R60: 300 g | S60: UL 1023/1610, CE, FCC | T60: Central de monitoreo / residencial premium | U60: 90 | X60: Variante económica de la gama | Y60: 0.085 | Z60: 0.312 | AA60: 12 | AB60: Contact ID / SIA DC-09 (AlarmNet) | AC60: Centrales VISTA/ProA7 (bus ECP) (mismo bus) | AD60: N/A | AE60: N/A | AF60: N/A | AG60: N/A | AH60: N/A | AI60: N/A | AJ60: N/A | AK60: N/A | AL60: N/A | AM60: N/A | AN60: N/A | AO60: N/A | AP60: N/A
B61: 57 | C61: Honeywell Security | D61: Alta | E61: EE. UU. | F61: Comunicador de eventos | G61: 7847i | H61: IP + GPRS | I61: Transmisor de eventos AlarmNet | J61: Cifrado AES 128-bit, supervisión remota | K61: Contact ID / SIA sobre IP y LTE | L61: Contact ID / SIA DC-09 (AlarmNet) | M61: 12 VDC desde panel | N61: 95 mA IP / 190 mA LTE | O61: — | P61: 0 °C a +49 °C | Q61: 88 × 152 × 30 mm | R61: 300 g | S61: UL 1023/1610, CE, FCC | T61: Central de monitoreo / residencial premium | U61: 135 | X61: Gama de entrada | Y61: 0.086 | Z61: 0.316 | AA61: 12 | AB61: Contact ID / SIA DC-09 (AlarmNet) | AC61: Centrales VISTA/ProA7 (bus ECP) (mismo bus) | AD61: N/A | AE61: N/A | AF61: N/A | AG61: N/A | AH61: N/A | AI61: N/A | AJ61: N/A | AK61: N/A | AL61: N/A | AM61: N/A | AN61: N/A | AO61: N/A | AP61: N/A
B62: 58 | C62: Honeywell Security | D62: Alta | E62: EE. UU. | F62: Comunicador de eventos | G62: 7847i-L | H62: IP + LTE | I62: Transmisor de eventos AlarmNet | J62: Cifrado AES 128-bit, supervisión remota | K62: Contact ID / SIA sobre IP y LTE | L62: Contact ID / SIA DC-09 (AlarmNet) | M62: 12 VDC desde panel | N62: 95 mA IP / 190 mA LTE | O62: — | P62: 0 °C a +49 °C | Q62: 88 × 152 × 30 mm | R62: 300 g | S62: UL 1023/1610, CE, FCC | T62: Central de monitoreo / residencial premium | U62: 185 | X62: Compatible con paneles VISTA y ECP | Y62: 0.053 | Z62: 0.233 | AA62: 12 | AB62: Contact ID / SIA DC-09 (AlarmNet) | AC62: Centrales VISTA/ProA7 (bus ECP) (mismo bus) | AD62: N/A | AE62: N/A | AF62: N/A | AG62: N/A | AH62: N/A | AI62: N/A | AJ62: N/A | AK62: N/A | AL62: N/A | AM62: N/A | AN62: N/A | AO62: N/A | AP62: N/A
B63: 59 | C63: Honeywell Security | D63: Alta | E63: EE. UU. | F63: Comunicador de eventos | G63: LTE-XV | H63: LTE dual-SIM | I63: Transmisor de eventos AlarmNet | J63: Cifrado AES 128-bit, supervisión remota | K63: Contact ID / SIA sobre IP y LTE | L63: Contact ID / SIA DC-09 (AlarmNet) | M63: 12 VDC desde panel | N63: 95 mA IP / 190 mA LTE | O63: — | P63: 0 °C a +49 °C | Q63: 88 × 152 × 30 mm | R63: 300 g | S63: UL 1023/1610, CE, FCC | T63: Central de monitoreo / residencial premium | U63: 275 | X63: Capacidad y rendimiento mejorados | Y63: 0.052 | Z63: 0.23 | AA63: 12 | AB63: Contact ID / SIA DC-09 (AlarmNet) | AC63: Centrales VISTA/ProA7 (bus ECP) (mismo bus) | AD63: N/A | AE63: N/A | AF63: N/A | AG63: N/A | AH63: N/A | AI63: N/A | AJ63: N/A | AK63: N/A | AL63: N/A | AM63: N/A | AN63: N/A | AO63: N/A | AP63: N/A
B64: 60 | C64: Honeywell Security | D64: Alta | E64: EE. UU. | F64: Comunicador de eventos | G64: LTE-IA | H64: LTE + IP + dialer | I64: Transmisor de eventos AlarmNet | J64: Cifrado AES 128-bit, supervisión remota | K64: Contact ID / SIA sobre IP y LTE | L64: Contact ID / SIA DC-09 (AlarmNet) | M64: 12 VDC desde panel | N64: 95 mA IP / 190 mA LTE | O64: — | P64: 0 °C a +49 °C | Q64: 88 × 152 × 30 mm | R64: 300 g | S64: UL 1023/1610, CE, FCC | T64: Central de monitoreo / residencial premium | U64: 405 | X64: Tope de gama — máxima especificación | Y64: 0.094 | Z64: 0.334 | AA64: 12 | AB64: Contact ID / SIA DC-09 (AlarmNet) | AC64: Centrales VISTA/ProA7 (bus ECP) (mismo bus) | AD64: N/A | AE64: N/A | AF64: N/A | AG64: N/A | AH64: N/A | AI64: N/A | AJ64: N/A | AK64: N/A | AL64: N/A | AM64: N/A | AN64: N/A | AO64: N/A | AP64: N/A
B65: 61 | C65: Honeywell Security | D65: Alta | E65: EE. UU. | F65: Perimetral exterior | G65: No disponible en portafolio | X65: Honeywell no fabrica barreras IR; referencia Optex AX-200TTO compatible con zonas alámbricas | Y65: N/A | Z65: N/A | AA65: N/A | AB65: N/A | AC65: N/A | AD65: N/A | AE65: N/A | AF65: N/A | AG65: N/A | AH65: N/A | AI65: N/A | AJ65: N/A | AK65: N/A | AL65: N/A | AM65: N/A | AN65: N/A | AO65: N/A | AP65: N/A
B66: 62 | C66: Honeywell Security | D66: Alta | E66: EE. UU. | F66: Expansor / receptor | G66: 4204 | H66: 4 zonas | I66: Expansor de zonas por bus ECP | J66: Soporta contactos y PIR cableados en caseta | K66: Bus ECP | L66: Contact ID / SIA DC-09 (AlarmNet) | M66: 12 VDC desde panel | N66: 45 mA + zonas | O66: — | P66: 0 °C a +49 °C | Q66: 165 × 100 × 35 mm | R66: 230 g | S66: UL 1023/1610, CE, FCC | T66: Ampliación de paneles VISTA | U66: 35 | X66: Variante económica de la gama | Y66: 0.049 | Z66: 0.075 | AA66: 12 | AB66: Contact ID / SIA DC-09 (AlarmNet) | AC66: Centrales VISTA/ProA7 (bus ECP) (mismo bus) | AD66: N/A | AE66: N/A | AF66: N/A | AG66: 4 | AH66: N/A | AI66: N/A | AJ66: N/A | AK66: N/A | AL66: N/A | AM66: N/A | AN66: N/A | AO66: N/A | AP66: N/A
B67: 63 | C67: Honeywell Security | D67: Alta | E67: EE. UU. | F67: Expansor / receptor | G67: 4229 | H67: 8 zonas | I67: Expansor de zonas por bus ECP | J67: Soporta contactos y PIR cableados en caseta | K67: Bus ECP | L67: Contact ID / SIA DC-09 (AlarmNet) | M67: 12 VDC desde panel | N67: 45 mA + zonas | O67: — | P67: 0 °C a +49 °C | Q67: 165 × 100 × 35 mm | R67: 230 g | S67: UL 1023/1610, CE, FCC | T67: Ampliación de paneles VISTA | U67: 55 | X67: Gama de entrada | Y67: 0.059 | Z67: 0.088 | AA67: 12 | AB67: Contact ID / SIA DC-09 (AlarmNet) | AC67: Centrales VISTA/ProA7 (bus ECP) (mismo bus) | AD67: N/A | AE67: N/A | AF67: N/A | AG67: 8 | AH67: N/A | AI67: N/A | AJ67: N/A | AK67: N/A | AL67: N/A | AM67: N/A | AN67: N/A | AO67: N/A | AP67: N/A
B68: 64 | C68: Honeywell Security | D68: Alta | E68: EE. UU. | F68: Expansor / receptor | G68: 4219 | H68: 8 zonas + 2 salidas | I68: Expansor de zonas por bus ECP | J68: Soporta contactos y PIR cableados en caseta | K68: Bus ECP | L68: Contact ID / SIA DC-09 (AlarmNet) | M68: 12 VDC desde panel | N68: 45 mA + zonas | O68: — | P68: 0 °C a +49 °C | Q68: 165 × 100 × 35 mm | R68: 230 g | S68: UL 1023/1610, CE, FCC | T68: Ampliación de paneles VISTA | U68: 75 | X68: Cada zona admite EOL y sabotaje | Y68: 0.06 | Z68: 0.09 | AA68: 12 | AB68: Contact ID / SIA DC-09 (AlarmNet) | AC68: Centrales VISTA/ProA7 (bus ECP) (mismo bus) | AD68: N/A | AE68: N/A | AF68: N/A | AG68: 8 | AH68: N/A | AI68: N/A | AJ68: N/A | AK68: N/A | AL68: N/A | AM68: N/A | AN68: N/A | AO68: N/A | AP68: N/A
B69: 65 | C69: Honeywell Security | D69: Alta | E69: EE. UU. | F69: Expansor / receptor | G69: 5881ENH | H69: 16 zonas | I69: Expansor de zonas por bus ECP | J69: Soporta contactos y PIR cableados en caseta | K69: Bus ECP | L69: Contact ID / SIA DC-09 (AlarmNet) | M69: 12 VDC desde panel | N69: 45 mA + zonas | O69: — | P69: 0 °C a +49 °C | Q69: 165 × 100 × 35 mm | R69: 230 g | S69: UL 1023/1610, CE, FCC | T69: Ampliación de paneles VISTA | U69: 115 | X69: Capacidad y rendimiento mejorados | Y69: 0.031 | Z69: 0.052 | AA69: 12 | AB69: Contact ID / SIA DC-09 (AlarmNet) | AC69: Centrales VISTA/ProA7 (bus ECP) (mismo bus) | AD69: N/A | AE69: N/A | AF69: N/A | AG69: 16 | AH69: N/A | AI69: N/A | AJ69: N/A | AK69: N/A | AL69: N/A | AM69: N/A | AN69: N/A | AO69: N/A | AP69: N/A
B70: 66 | C70: Honeywell Security | D70: Alta | E70: EE. UU. | F70: Expansor / receptor | G70: 5800RP | H70: 16 zonas + 4 salidas | I70: Expansor de zonas por bus ECP | J70: Soporta contactos y PIR cableados en caseta | K70: Bus ECP | L70: Contact ID / SIA DC-09 (AlarmNet) | M70: 12 VDC desde panel | N70: 45 mA + zonas | O70: — | P70: 0 °C a +49 °C | Q70: 165 × 100 × 35 mm | R70: 230 g | S70: UL 1023/1610, CE, FCC | T70: Ampliación de paneles VISTA | U70: 170 | X70: Tope de gama — máxima especificación | Y70: 0.04 | Z70: 0.064 | AA70: 12 | AB70: Contact ID / SIA DC-09 (AlarmNet) | AC70: Centrales VISTA/ProA7 (bus ECP) (mismo bus) | AD70: N/A | AE70: N/A | AF70: N/A | AG70: 16 | AH70: N/A | AI70: N/A | AJ70: N/A | AK70: N/A | AL70: N/A | AM70: N/A | AN70: N/A | AO70: N/A | AP70: N/A
B71: 67 | C71: Honeywell Security | D71: Alta | E71: EE. UU. | F71: Botón de pánico | G71: 5802 | H71: Colgante básico | I71: Transmisor de pánico 319.5 MHz con retén | J71: Botón con cierre de seguridad, señal supervisada | K71: Zona inalámbrica 5800 | L71: Contact ID / SIA DC-09 (AlarmNet) | M71: Batería CR2032 (3 V) | N71: 10 µA en reposo | O71: — | P71: 0 °C a +49 °C | Q71: 50 × 33 × 13 mm | R71: 25 g | S71: UL 1023/1610, CE, FCC | T71: Comercio, bancario y adultos mayores | U71: 30 | X71: Variante económica de la gama | Y71: 5.58e-06 | Z71: 2.385e-05 | AA71: 3 | AB71: Contact ID / SIA DC-09 (AlarmNet) | AC71: Zona 12 V universal — centrales VISTA/ProA7 (bus ECP) y compatibles | AD71: N/A | AE71: N/A | AF71: N/A | AG71: N/A | AH71: N/A | AI71: N/A | AJ71: N/A | AK71: N/A | AL71: N/A | AM71: N/A | AN71: N/A | AO71: N/A | AP71: N/A
B72: 68 | C72: Honeywell Security | D72: Alta | E72: EE. UU. | F72: Botón de pánico | G72: 5802LX | H72: Colgante supervisado | I72: Transmisor de pánico 319.5 MHz con retén | J72: Botón con cierre de seguridad, señal supervisada | K72: Zona inalámbrica 5800 | L72: Contact ID / SIA DC-09 (AlarmNet) | M72: Batería CR2032 (3 V) | N72: 10 µA en reposo | O72: — | P72: 0 °C a +49 °C | Q72: 50 × 33 × 13 mm | R72: 25 g | S72: UL 1023/1610, CE, FCC | T72: Comercio, bancario y adultos mayores | U72: 45 | X72: Gama de entrada | Y72: 7.8e-06 | Z72: 3.409e-05 | AA72: 3 | AB72: Contact ID / SIA DC-09 (AlarmNet) | AC72: Zona 12 V universal — centrales VISTA/ProA7 (bus ECP) y compatibles | AD72: N/A | AE72: N/A | AF72: N/A | AG72: N/A | AH72: N/A | AI72: N/A | AJ72: N/A | AK72: N/A | AL72: N/A | AM72: N/A | AN72: N/A | AO72: N/A | AP72: N/A
B73: 69 | C73: Honeywell Security | D73: Alta | E73: EE. UU. | F73: Botón de pánico | G73: 5802LXT2 | H73: Botón de pared | I73: Transmisor de pánico 319.5 MHz con retén | J73: Botón con cierre de seguridad, señal supervisada | K73: Zona inalámbrica 5800 | L73: Contact ID / SIA DC-09 (AlarmNet) | M73: Batería CR2032 (3 V) | N73: 10 µA en reposo | O73: — | P73: 0 °C a +49 °C | Q73: 50 × 33 × 13 mm | R73: 25 g | S73: UL 1023/1610, CE, FCC | T73: Comercio, bancario y adultos mayores | U73: 65 | X73: Versión alámbrica 269R para hold-up en caja | Y73: 0 | Z73: 0 | AA73: N/A | AB73: Contact ID / SIA DC-09 (AlarmNet) | AC73: Zona 12 V universal — centrales VISTA/ProA7 (bus ECP) y compatibles | AD73: N/A | AE73: N/A | AF73: N/A | AG73: N/A | AH73: N/A | AI73: N/A | AJ73: N/A | AK73: N/A | AL73: N/A | AM73: N/A | AN73: N/A | AO73: 1.1 | AP73: 1.5
B74: 70 | C74: Honeywell Security | D74: Alta | E74: EE. UU. | F74: Botón de pánico | G74: 269R | H74: Con carcasa sabotaje | I74: Transmisor de pánico 319.5 MHz con retén | J74: Botón con cierre de seguridad, señal supervisada | K74: Zona inalámbrica 5800 | L74: Contact ID / SIA DC-09 (AlarmNet) | M74: Batería CR2032 (3 V) | N74: 10 µA en reposo | O74: — | P74: 0 °C a +49 °C | Q74: 50 × 33 × 13 mm | R74: 25 g | S74: UL 1023/1610, CE, FCC | T74: Comercio, bancario y adultos mayores | U74: 95 | X74: Capacidad y rendimiento mejorados | Y74: 0 | Z74: 0 | AA74: N/A | AB74: Contact ID / SIA DC-09 (AlarmNet) | AC74: Zona 12 V universal — centrales VISTA/ProA7 (bus ECP) y compatibles | AD74: N/A | AE74: N/A | AF74: N/A | AG74: N/A | AH74: N/A | AI74: N/A | AJ74: N/A | AK74: N/A | AL74: N/A | AM74: N/A | AN74: N/A | AO74: 1.1 | AP74: 1.5
B75: 71 | C75: Honeywell Security | D75: Alta | E75: EE. UU. | F75: Botón de pánico | G75: 5804BD | H75: Hold-up con código | I75: Transmisor de pánico 319.5 MHz con retén | J75: Botón con cierre de seguridad, señal supervisada | K75: Zona inalámbrica 5800 | L75: Contact ID / SIA DC-09 (AlarmNet) | M75: Batería CR2032 (3 V) | N75: 10 µA en reposo | O75: — | P75: 0 °C a +49 °C | Q75: 50 × 33 × 13 mm | R75: 25 g | S75: UL 1023/1610, CE, FCC | T75: Comercio, bancario y adultos mayores | U75: 140 | X75: Tope de gama — máxima especificación | Y75: 0 | Z75: 0 | AA75: N/A | AB75: Contact ID / SIA DC-09 (AlarmNet) | AC75: Zona 12 V universal — centrales VISTA/ProA7 (bus ECP) y compatibles | AD75: N/A | AE75: N/A | AF75: N/A | AG75: N/A | AH75: N/A | AI75: N/A | AJ75: N/A | AK75: N/A | AL75: N/A | AM75: N/A | AN75: N/A | AO75: 1.1 | AP75: 1.5
B76: 72 | C76: Honeywell Security | D76: Alta | E76: EE. UU. | F76: Mando inalámbrico | G76: 5804 | H76: 4 botones | I76: Llave inalámbrica para armado/desarmado | J76: Botones dedicados armado/desarmado + pánico | K76: Zona inalámbrica 5800 | L76: Contact ID / SIA DC-09 (AlarmNet) | M76: Batería CR2032 (3 V) | N76: 5 µA en reposo | O76: — | P76: 0 °C a +49 °C | Q76: 64 × 38 × 13 mm | R76: 30 g | S76: UL 1023/1610, CE, FCC | T76: Armado diario y pánico | U76: 20 | X76: Variante económica de la gama | Y76: 4.57e-06 | Z76: 2.283e-05 | AA76: 3 | AB76: Contact ID / SIA DC-09 (AlarmNet) | AC76: Exclusivo radio de marca: radio SiX/5800 (ProA7, VISTA + transceptor) | AD76: N/A | AE76: N/A | AF76: N/A | AG76: N/A | AH76: N/A | AI76: N/A | AJ76: N/A | AK76: N/A | AL76: N/A | AM76: N/A | AN76: N/A | AO76: N/A | AP76: N/A
B77: 73 | C77: Honeywell Security | D77: Alta | E77: EE. UU. | F77: Mando inalámbrico | G77: 5834-2 | H77: 4 botones + pánico | I77: Llave inalámbrica para armado/desarmado | J77: Botones dedicados armado/desarmado + pánico | K77: Zona inalámbrica 5800 | L77: Contact ID / SIA DC-09 (AlarmNet) | M77: Batería CR2032 (3 V) | N77: 5 µA en reposo | O77: — | P77: 0 °C a +49 °C | Q77: 64 × 38 × 13 mm | R77: 30 g | S77: UL 1023/1610, CE, FCC | T77: Armado diario y pánico | U77: 30 | X77: Gama de entrada | Y77: 5.89e-06 | Z77: 2.945e-05 | AA77: 3 | AB77: Contact ID / SIA DC-09 (AlarmNet) | AC77: Exclusivo radio de marca: radio SiX/5800 (ProA7, VISTA + transceptor) | AD77: N/A | AE77: N/A | AF77: N/A | AG77: N/A | AH77: N/A | AI77: N/A | AJ77: N/A | AK77: N/A | AL77: N/A | AM77: N/A | AN77: N/A | AO77: N/A | AP77: N/A
B78: 74 | C78: Honeywell Security | D78: Alta | E78: EE. UU. | F78: Mando inalámbrico | G78: 5834-4 | H78: 5 botones + pánico | I78: Llave inalámbrica para armado/desarmado | J78: Botones dedicados armado/desarmado + pánico | K78: Zona inalámbrica 5800 | L78: Contact ID / SIA DC-09 (AlarmNet) | M78: Batería CR2032 (3 V) | N78: 5 µA en reposo | O78: — | P78: 0 °C a +49 °C | Q78: 64 × 38 × 13 mm | R78: 30 g | S78: UL 1023/1610, CE, FCC | T78: Armado diario y pánico | U78: 40 | X78: 5804BD = versión bidireccional con confirmación | Y78: 5.45e-06 | Z78: 2.724e-05 | AA78: 3 | AB78: Contact ID / SIA DC-09 (AlarmNet) | AC78: Exclusivo radio de marca: radio SiX/5800 (ProA7, VISTA + transceptor) | AD78: N/A | AE78: N/A | AF78: N/A | AG78: N/A | AH78: N/A | AI78: N/A | AJ78: N/A | AK78: N/A | AL78: N/A | AM78: N/A | AN78: N/A | AO78: N/A | AP78: N/A
B79: 75 | C79: Honeywell Security | D79: Alta | E79: EE. UU. | F79: Mando inalámbrico | G79: 5834-4M | H79: Bidireccional con retroalimentación | I79: Llave inalámbrica para armado/desarmado | J79: Botones dedicados armado/desarmado + pánico | K79: Zona inalámbrica 5800 | L79: Contact ID / SIA DC-09 (AlarmNet) | M79: Batería CR2032 (3 V) | N79: 5 µA en reposo | O79: — | P79: 0 °C a +49 °C | Q79: 64 × 38 × 13 mm | R79: 30 g | S79: UL 1023/1610, CE, FCC | T79: Armado diario y pánico | U79: 60 | X79: Capacidad y rendimiento mejorados | Y79: 4.92e-06 | Z79: 2.459e-05 | AA79: 3 | AB79: Contact ID / SIA DC-09 (AlarmNet) | AC79: Exclusivo radio de marca: radio SiX/5800 (ProA7, VISTA + transceptor) | AD79: N/A | AE79: N/A | AF79: N/A | AG79: N/A | AH79: N/A | AI79: N/A | AJ79: N/A | AK79: N/A | AL79: N/A | AM79: N/A | AN79: N/A | AO79: N/A | AP79: N/A
B80: 76 | C80: Honeywell Security | D80: Alta | E80: EE. UU. | F80: Mando inalámbrico | G80: 5804BD | H80: Bidireccional táctil | I80: Llave inalámbrica para armado/desarmado | J80: Botones dedicados armado/desarmado + pánico | K80: Zona inalámbrica 5800 | L80: Contact ID / SIA DC-09 (AlarmNet) | M80: Batería CR2032 (3 V) | N80: 5 µA en reposo | O80: — | P80: 0 °C a +49 °C | Q80: 64 × 38 × 13 mm | R80: 30 g | S80: UL 1023/1610, CE, FCC | T80: Armado diario y pánico | U80: 85 | X80: Tope de gama — máxima especificación | Y80: 3.07e-06 | Z80: 1.537e-05 | AA80: 3 | AB80: Contact ID / SIA DC-09 (AlarmNet) | AC80: Exclusivo radio de marca: radio SiX/5800 (ProA7, VISTA + transceptor) | AD80: N/A | AE80: N/A | AF80: N/A | AG80: N/A | AH80: N/A | AI80: N/A | AJ80: N/A | AK80: N/A | AL80: N/A | AM80: N/A | AN80: N/A | AO80: N/A | AP80: N/A
B81: 77 | C81: DSC | D81: Alta | E81: Canadá | F81: Panel híbrido | G81: HS2032 | H81: 32 zonas / 2 particiones | I81: Híbrido: 8 alámbricas de base + bus bus conectable | J81: Detector de sabotaje por zona, teclados con proximity | K81: Contact ID/SIA vía módulo TL280 | L81: Contact ID / SIA (vía módulo TL) | M81: 16.5 VAC 40 VA · batería 12 V 7 Ah | N81: 650 mA máx | O81: — | P81: 0 °C a +49 °C | Q81: 300 × 295 × 76 mm | R81: 2.8 kg | S81: UL, CE, EN 50131 grado 2 | T81: Comercial mediano | U81: 155 | X81: Variante económica de la gama | Y81: 0.11 | Z81: 0.65 | AA81: 12 | AB81: Contact ID / SIA (vía módulo TL) | AC81: Central maestra — admite periféricos del ecosistema PowerSeries Neo/PC (Keybus) | AD81: 0.11 | AE81: 0.65 | AF81: 2.5 | AG81: 32 | AH81: 2 | AI81: N/A | AJ81: N/A | AK81: N/A | AL81: N/A | AM81: N/A | AN81: N/A | AO81: N/A | AP81: N/A
B82: 78 | C82: DSC | D82: Alta | E82: Canadá | F82: Panel híbrido | G82: HS2128 | H82: 32 zonas / 2 particiones | I82: Híbrido: 8 alámbricas de base + bus bus conectable | J82: Detector de sabotaje por zona, teclados con proximity | K82: Contact ID/SIA vía módulo TL280 | L82: Contact ID / SIA (vía módulo TL) | M82: 16.5 VAC 40 VA · batería 12 V 7 Ah | N82: 650 mA máx | O82: — | P82: 0 °C a +49 °C | Q82: 300 × 295 × 76 mm | R82: 2.8 kg | S82: UL, CE, EN 50131 grado 2 | T82: Comercial mediano | U82: 230 | X82: Gama de entrada | Y82: 0.119 | Z82: 0.65 | AA82: 12 | AB82: Contact ID / SIA (vía módulo TL) | AC82: Central maestra — admite periféricos del ecosistema PowerSeries Neo/PC (Keybus) | AD82: 0.119 | AE82: 0.65 | AF82: 3.5 | AG82: 128 | AH82: 8 | AI82: N/A | AJ82: N/A | AK82: N/A | AL82: N/A | AM82: N/A | AN82: N/A | AO82: N/A | AP82: N/A
B83: 79 | C83: DSC | D83: Alta | E83: Canadá | F83: Panel híbrido | G83: HS3232 | H83: 32 zonas / 2 particiones | I83: Híbrido: 8 alámbricas de base + bus bus conectable | J83: Detector de sabotaje por zona, teclados con proximity | K83: Contact ID/SIA vía módulo TL280 | L83: Contact ID / SIA (vía módulo TL) | M83: 16.5 VAC 40 VA · batería 12 V 7 Ah | N83: 650 mA máx | O83: — | P83: 0 °C a +49 °C | Q83: 300 × 295 × 76 mm | R83: 2.8 kg | S83: UL, CE, EN 50131 grado 2 | T83: Comercial mediano | U83: 310 | X83: Plataforma Neo con cifrado en teclados | Y83: 0.055 | Z83: 0.65 | AA83: 12 | AB83: Contact ID / SIA (vía módulo TL) | AC83: Central maestra — admite periféricos del ecosistema PowerSeries Neo/PC (Keybus) | AD83: 0.055 | AE83: 0.65 | AF83: 2.5 | AG83: 32 | AH83: 2 | AI83: N/A | AJ83: N/A | AK83: N/A | AL83: N/A | AM83: N/A | AN83: N/A | AO83: N/A | AP83: N/A
B84: 80 | C84: DSC | D84: Alta | E84: Canadá | F84: Panel híbrido | G84: HS3248 | H84: 32 zonas / 2 particiones | I84: Híbrido: 8 alámbricas de base + bus bus conectable | J84: Detector de sabotaje por zona, teclados con proximity | K84: Contact ID/SIA vía módulo TL280 | L84: Contact ID / SIA (vía módulo TL) | M84: 16.5 VAC 40 VA · batería 12 V 7 Ah | N84: 650 mA máx | O84: — | P84: 0 °C a +49 °C | Q84: 300 × 295 × 76 mm | R84: 2.8 kg | S84: UL, CE, EN 50131 grado 2 | T84: Comercial mediano | U84: 465 | X84: Capacidad y rendimiento mejorados | Y84: 0.07 | Z84: 0.65 | AA84: 12 | AB84: Contact ID / SIA (vía módulo TL) | AC84: Central maestra — admite periféricos del ecosistema PowerSeries Neo/PC (Keybus) | AD84: 0.07 | AE84: 0.65 | AF84: 2.5 | AG84: 32 | AH84: 2 | AI84: N/A | AJ84: N/A | AK84: N/A | AL84: N/A | AM84: N/A | AN84: N/A | AO84: N/A | AP84: N/A
B85: 81 | C85: DSC | D85: Alta | E85: Canadá | F85: Panel híbrido | G85: PC1864 | H85: 32 zonas / 2 particiones | I85: Híbrido: 8 alámbricas de base + bus bus conectable | J85: Detector de sabotaje por zona, teclados con proximity | K85: Contact ID/SIA vía módulo TL280 | L85: Contact ID / SIA (vía módulo TL) | M85: 16.5 VAC 40 VA · batería 12 V 7 Ah | N85: 650 mA máx | O85: — | P85: 0 °C a +49 °C | Q85: 300 × 295 × 76 mm | R85: 2.8 kg | S85: UL, CE, EN 50131 grado 2 | T85: Comercial mediano | U85: 680 | X85: Tope de gama — máxima especificación | Y85: 0.109 | Z85: 0.65 | AA85: 12 | AB85: Contact ID / SIA (vía módulo TL) | AC85: Central maestra — admite periféricos del ecosistema PowerSeries Neo/PC (Keybus) | AD85: 0.109 | AE85: 0.65 | AF85: 3 | AG85: 64 | AH85: 8 | AI85: N/A | AJ85: N/A | AK85: N/A | AL85: N/A | AM85: N/A | AN85: N/A | AO85: N/A | AP85: N/A
B86: 82 | C86: DSC | D86: Alta | E86: Canadá | F86: Panel alámbrico | G86: PC1616 | H86: 32 zonas / 2 particiones | I86: Alámbrico con expansores PC5xxx | J86: 8 salidas PGM programables | K86: Contact ID (dialer integrado) | L86: Contact ID / SIA (vía módulo TL) | M86: 16.5 VAC 40 VA · batería 12 V 7 Ah | N86: 550 mA máx | O86: — | P86: 0 °C a +49 °C | Q86: 279 × 279 × 76 mm | R86: 2.4 kg | S86: UL, CE, EN 50131 grado 2 | T86: Residencial y PYME | U86: 90 | X86: Variante económica de la gama | Y86: 0.06 | Z86: 0.55 | AA86: 12 | AB86: Contact ID / SIA (vía módulo TL) | AC86: Central maestra — admite periféricos del ecosistema PowerSeries Neo/PC (Keybus) | AD86: 0.06 | AE86: 0.55 | AF86: 2 | AG86: 16 | AH86: 2 | AI86: N/A | AJ86: N/A | AK86: N/A | AL86: N/A | AM86: N/A | AN86: N/A | AO86: N/A | AP86: N/A
B87: 83 | C87: DSC | D87: Alta | E87: Canadá | F87: Panel alámbrico | G87: PC1832 | H87: 32 zonas / 2 particiones | I87: Alámbrico con expansores PC5xxx | J87: 8 salidas PGM programables | K87: Contact ID (dialer integrado) | L87: Contact ID / SIA (vía módulo TL) | M87: 16.5 VAC 40 VA · batería 12 V 7 Ah | N87: 550 mA máx | O87: — | P87: 0 °C a +49 °C | Q87: 279 × 279 × 76 mm | R87: 2.4 kg | S87: UL, CE, EN 50131 grado 2 | T87: Residencial y PYME | U87: 135 | X87: Gama de entrada | Y87: 0.096 | Z87: 0.55 | AA87: 12 | AB87: Contact ID / SIA (vía módulo TL) | AC87: Central maestra — admite periféricos del ecosistema PowerSeries Neo/PC (Keybus) | AD87: 0.096 | AE87: 0.55 | AF87: 2.5 | AG87: 32 | AH87: 8 | AI87: N/A | AJ87: N/A | AK87: N/A | AL87: N/A | AM87: N/A | AN87: N/A | AO87: N/A | AP87: N/A
B88: 84 | C88: DSC | D88: Alta | E88: Canadá | F88: Panel alámbrico | G88: PC1864 | H88: 32 zonas / 2 particiones | I88: Alámbrico con expansores PC5xxx | J88: 8 salidas PGM programables | K88: Contact ID (dialer integrado) | L88: Contact ID / SIA (vía módulo TL) | M88: 16.5 VAC 40 VA · batería 12 V 7 Ah | N88: 550 mA máx | O88: — | P88: 0 °C a +49 °C | Q88: 279 × 279 × 76 mm | R88: 2.4 kg | S88: UL, CE, EN 50131 grado 2 | T88: Residencial y PYME | U88: 185 | X88: Serie PowerSeries probada, expansión modular | Y88: 0.109 | Z88: 0.55 | AA88: 12 | AB88: Contact ID / SIA (vía módulo TL) | AC88: Central maestra — admite periféricos del ecosistema PowerSeries Neo/PC (Keybus) | AD88: 0.109 | AE88: 0.55 | AF88: 3 | AG88: 64 | AH88: 8 | AI88: N/A | AJ88: N/A | AK88: N/A | AL88: N/A | AM88: N/A | AN88: N/A | AO88: N/A | AP88: N/A
B89: 85 | C89: DSC | D89: Alta | E89: Canadá | F89: Panel alámbrico | G89: PC4020 | H89: 32 zonas / 2 particiones | I89: Alámbrico con expansores PC5xxx | J89: 8 salidas PGM programables | K89: Contact ID (dialer integrado) | L89: Contact ID / SIA (vía módulo TL) | M89: 16.5 VAC 40 VA · batería 12 V 7 Ah | N89: 550 mA máx | O89: — | P89: 0 °C a +49 °C | Q89: 279 × 279 × 76 mm | R89: 2.4 kg | S89: UL, CE, EN 50131 grado 2 | T89: Residencial y PYME | U89: 275 | X89: Capacidad y rendimiento mejorados | Y89: 0.104 | Z89: 0.55 | AA89: 12 | AB89: Contact ID / SIA (vía módulo TL) | AC89: Central maestra — admite periféricos del ecosistema PowerSeries Neo/PC (Keybus) | AD89: 0.104 | AE89: 0.55 | AF89: 3.5 | AG89: 128 | AH89: 32 | AI89: N/A | AJ89: N/A | AK89: N/A | AL89: N/A | AM89: N/A | AN89: N/A | AO89: N/A | AP89: N/A
B90: 86 | C90: DSC | D90: Alta | E90: Canadá | F90: Panel alámbrico | G90: PC9155-433 | H90: 32 zonas / 2 particiones | I90: Alámbrico con expansores PC5xxx | J90: 8 salidas PGM programables | K90: Contact ID (dialer integrado) | L90: Contact ID / SIA (vía módulo TL) | M90: 16.5 VAC 40 VA · batería 12 V 7 Ah | N90: 550 mA máx | O90: — | P90: 0 °C a +49 °C | Q90: 279 × 279 × 76 mm | R90: 2.4 kg | S90: UL, CE, EN 50131 grado 2 | T90: Residencial y PYME | U90: 405 | X90: Tope de gama — máxima especificación | Y90: 0.09 | Z90: 0.55 | AA90: 12 | AB90: Contact ID / SIA (vía módulo TL) | AC90: Central maestra — admite periféricos del ecosistema PowerSeries Neo/PC (Keybus) | AD90: 0.09 | AE90: 0.55 | AF90: 2.5 | AG90: 32 | AH90: 2 | AI90: N/A | AJ90: N/A | AK90: N/A | AL90: N/A | AM90: N/A | AN90: N/A | AO90: N/A | AP90: N/A
B91: 87 | C91: DSC | D91: Alta | E91: Canadá | F91: Panel inalámbrico / Hub | G91: SCW9047G-433 | H91: Hasta 32 zonas inalámbricas 433 MHz | I91: Autocontenido con teclado y sirena | J91: Detección de sabotaje, armado por proximity | K91: GSM opcional + dialer integrado | L91: Contact ID / SIA (vía módulo TL) | M91: 16.5 VAC · batería 12 V | N91: 400 mA máx | O91: — | P91: 0 °C a +49 °C | Q91: 220 × 150 × 60 mm | R91: 1.3 kg | S91: UL, CE, EN 50131 grado 2 | T91: Residencial inalámbrico | U91: 120 | X91: Variante económica de la gama | Y91: 0.059 | Z91: 0.4 | AA91: 12 | AB91: Contact ID / SIA (vía módulo TL) | AC91: Central maestra — admite periféricos del ecosistema PowerSeries Neo/PC (Keybus) | AD91: 0.059 | AE91: 0.4 | AF91: 2 | AG91: 32 | AH91: 4 | AI91: N/A | AJ91: N/A | AK91: N/A | AL91: N/A | AM91: N/A | AN91: N/A | AO91: N/A | AP91: N/A
B92: 88 | C92: DSC | D92: Alta | E92: Canadá | F92: Panel inalámbrico / Hub | G92: SCW9057G-433 | H92: Hasta 32 zonas inalámbricas 433 MHz | I92: Autocontenido con teclado y sirena | J92: Detección de sabotaje, armado por proximity | K92: GSM opcional + dialer integrado | L92: Contact ID / SIA (vía módulo TL) | M92: 16.5 VAC · batería 12 V | N92: 400 mA máx | O92: — | P92: 0 °C a +49 °C | Q92: 220 × 150 × 60 mm | R92: 1.3 kg | S92: UL, CE, EN 50131 grado 2 | T92: Residencial inalámbrico | U92: 185 | X92: Gama de entrada | Y92: 0.096 | Z92: 0.4 | AA92: 12 | AB92: Contact ID / SIA (vía módulo TL) | AC92: Central maestra — admite periféricos del ecosistema PowerSeries Neo/PC (Keybus) | AD92: 0.096 | AE92: 0.4 | AF92: 2 | AG92: 32 | AH92: 4 | AI92: N/A | AJ92: N/A | AK92: N/A | AL92: N/A | AM92: N/A | AN92: N/A | AO92: N/A | AP92: N/A
... B95: 91 | C95: DSC | D95: Alta | E95: Canadá | F95: Panel inalámbrico / Hub | G95: Impassa Kit | H95: Hasta 32 zonas inalámbricas 433 MHz | I95: Autocontenido con teclado y sirena | J95: Detección de sabotaje, armado por proximity | K95: GSM opcional + dialer integrado | L95: Contact ID / SIA (vía módulo TL) | M95: 16.5 VAC · batería 12 V | N95: 400 mA máx | O95: — | P95: 0 °C a +49 °C | Q95: 220 × 150 × 60 mm | R95: 1.3 kg | S95: UL, CE, EN 50131 grado 2 | T95: Residencial inalámbrico | U95: 545 | X95: Tope de gama — máxima especificación | Y95: 0.08 | Z95: 0.4 | AA95: 12 | AB95: Contact ID / SIA (vía módulo TL) | AC95: Central maestra — admite periféricos del ecosistema PowerSeries Neo/PC (Keybus) | AD95: 0.08 | AE95: 0.4 | AF95: 2 | AG95: 32 | AH95: 4 | AI95: N/A | AJ95: N/A | AK95: N/A | AL95: N/A | AM95: N/A | AN95: N/A | AO95: N/A | AP95: N/A
B96: 92 | C96: DSC | D96: Alta | E96: Canadá | F96: Teclado de control | G96: PK5500 | H96: Atiende 64 zonas del sistema | I96: LCD alfanumérico 2×16 | J96: Proximity integrado (armar/desarmar con tag) | K96: Bus bus conectable | L96: Contact ID / SIA (vía módulo TL) | M96: 12 VDC desde panel | N96: 65 mA | O96: — | P96: 0 °C a +49 °C | Q96: 120 × 165 × 28 mm | R96: 230 g | S96: UL, CE, EN 50131 grado 2 | T96: Uso general | U96: 40 | X96: Variante económica de la gama | Y96: 0.042 | Z96: 0.08 | AA96: 12 | AB96: Contact ID / SIA (vía módulo TL) | AC96: Centrales PowerSeries Neo/PC (Keybus) (mismo bus) | AD96: N/A | AE96: N/A | AF96: N/A | AG96: N/A | AH96: N/A | AI96: N/A | AJ96: N/A | AK96: N/A | AL96: N/A | AM96: N/A | AN96: N/A | AO96: 1.2 | AP96: 1.6
B97: 93 | C97: DSC | D97: Alta | E97: Canadá | F97: Teclado de control | G97: HS2LCD | H97: Atiende 64 zonas del sistema | I97: LCD alfanumérico 2×16 | J97: Proximity integrado (armar/desarmar con tag) | K97: Bus bus conectable | L97: Contact ID / SIA (vía módulo TL) | M97: 12 VDC desde panel | N97: 65 mA | O97: — | P97: 0 °C a +49 °C | Q97: 120 × 165 × 28 mm | R97: 230 g | S97: UL, CE, EN 50131 grado 2 | T97: Uso general | U97: 65 | X97: Gama de entrada | Y97: 0.056 | Z97: 0.104 | AA97: 12 | AB97: Contact ID / SIA (vía módulo TL) | AC97: Centrales PowerSeries Neo/PC (Keybus) (mismo bus) | AD97: N/A | AE97: N/A | AF97: N/A | AG97: N/A | AH97: N/A | AI97: N/A | AJ97: N/A | AK97: N/A | AL97: N/A | AM97: N/A | AN97: N/A | AO97: 1.2 | AP97: 1.6
B98: 94 | C98: DSC | D98: Alta | E98: Canadá | F98: Teclado de control | G98: HS2LCDRF | H98: Atiende 64 zonas del sistema | I98: LCD alfanumérico 2×16 | J98: Proximity integrado (armar/desarmar con tag) | K98: Bus bus conectable | L98: Contact ID / SIA (vía módulo TL) | M98: 12 VDC desde panel | N98: 65 mA | O98: — | P98: 0 °C a +49 °C | Q98: 120 × 165 × 28 mm | R98: 230 g | S98: UL, CE, EN 50131 grado 2 | T98: Uso general | U98: 85 | X98: Compatible con toda la serie Neo | Y98: 0.041 | Z98: 0.078 | AA98: 12 | AB98: Contact ID / SIA (vía módulo TL) | AC98: Centrales PowerSeries Neo/PC (Keybus) (mismo bus) | AD98: N/A | AE98: N/A | AF98: N/A | AG98: N/A | AH98: N/A | AI98: N/A | AJ98: N/A | AK98: N/A | AL98: N/A | AM98: N/A | AN98: N/A | AO98: 1.2 | AP98: 1.6
B99: 95 | C99: DSC | D99: Alta | E99: Canadá | F99: Teclado de control | G99: HS2TCHP | H99: Atiende 64 zonas del sistema | I99: LCD alfanumérico 2×16 | J99: Proximity integrado (armar/desarmar con tag) | K99: Bus bus conectable | L99: Contact ID / SIA (vía módulo TL) | M99: 12 VDC desde panel | N99: 65 mA | O99: — | P99: 0 °C a +49 °C | Q99: 120 × 165 × 28 mm | R99: 230 g | S99: UL, CE, EN 50131 grado 2 | T99: Uso general | U99: 130 | X99: Capacidad y rendimiento mejorados | Y99: 0.049 | Z99: 0.092 | AA99: 12 | AB99: Contact ID / SIA (vía módulo TL) | AC99: Centrales PowerSeries Neo/PC (Keybus) (mismo bus) | AD99: N/A | AE99: N/A | AF99: N/A | AG99: N/A | AH99: N/A | AI99: N/A | AJ99: N/A | AK99: N/A | AL99: N/A | AM99: N/A | AN99: N/A | AO99: 1.2 | AP99: 1.6
B100: 96 | C100: DSC | D100: Alta | E100: Canadá | F100: Teclado de control | G100: HS3LCD | H100: Atiende 64 zonas del sistema | I100: LCD alfanumérico 2×16 | J100: Proximity integrado (armar/desarmar con tag) | K100: Bus bus conectable | L100: Contact ID / SIA (vía módulo TL) | M100: 12 VDC desde panel | N100: 65 mA | O100: — | P100: 0 °C a +49 °C | Q100: 120 × 165 × 28 mm | R100: 230 g | S100: UL, CE, EN 50131 grado 2 | T100: Uso general | U100: 190 | X100: Tope de gama — máxima especificación | Y100: 0.043 | Z100: 0.082 | AA100: 12 | AB100: Contact ID / SIA (vía módulo TL) | AC100: Centrales PowerSeries Neo/PC (Keybus) (mismo bus) | AD100: N/A | AE100: N/A | AF100: N/A | AG100: N/A | AH100: N/A | AI100: N/A | AJ100: N/A | AK100: N/A | AL100: N/A | AM100: N/A | AN100: N/A | AO100: 1.2 | AP100: 1.6
B101: 97 | C101: DSC | D101: Alta | E101: Canadá | F101: Detector PIR interior | G101: LC-100-PI | H101: 8 m · 90° | I101: PIR con lente Fresnel espejo | J101: Pet-inmune hasta 27 kg, filtro DigitalFLEX | K101: Zona alámbrica | L101: Contact ID / SIA (vía módulo TL) | M101: 12 VDC | N101: 15 mA | O101: — | P101: 0 °C a +49 °C | Q101: 70 × 45 × 33 mm | R101: 80 g | S101: UL, CE, EN 50131 grado 2 | T101: Interior residencial/comercial | U101: 12 | X101: Variante económica de la gama | Y101: 0.008 | Z101: 0.012 | AA101: 12 | AB101: Contact ID / SIA (vía módulo TL) | AC101: Zona 12 V universal — centrales PowerSeries Neo/PC (Keybus) y compatibles | AD101: N/A | AE101: N/A | AF101: N/A | AG101: N/A | AH101: N/A | AI101: N/A | AJ101: 8 | AK101: N/A | AL101: 90 | AM101: Volumétrica rectangular (lentes múltiples) | AN101: N/A | AO101: 2 | AP101: 2.7
B102: 98 | C102: DSC | D102: Alta | E102: Canadá | F102: Detector PIR interior | G102: LC-103-PMI | H102: 10 m · 90° | I102: PIR con lente Fresnel espejo | J102: Pet-inmune hasta 27 kg, filtro DigitalFLEX | K102: Zona alámbrica | L102: Contact ID / SIA (vía módulo TL) | M102: 12 VDC | N102: 15 mA | O102: — | P102: 0 °C a +49 °C | Q102: 70 × 45 × 33 mm | R102: 80 g | S102: UL, CE, EN 50131 grado 2 | T102: Interior residencial/comercial | U102: 18 | X102: Gama de entrada | Y102: 0.017 | Z102: 0.024 | AA102: 12 | AB102: Contact ID / SIA (vía módulo TL) | AC102: Zona 12 V universal — centrales PowerSeries Neo/PC (Keybus) y compatibles | AD102: N/A | AE102: N/A | AF102: N/A | AG102: N/A | AH102: N/A | AI102: N/A | AJ102: 10 | AK102: N/A | AL102: 90 | AM102: Volumétrica rectangular (lentes múltiples) | AN102: N/A | AO102: 2 | AP102: 2.7
B103: 99 | C103: DSC | D103: Alta | E103: Canadá | F103: Detector PIR interior | G103: ES-423 | H103: 12 m · 90° | I103: PIR con lente Fresnel espejo | J103: Pet-inmune hasta 27 kg, filtro DigitalFLEX | K103: Zona alámbrica | L103: Contact ID / SIA (vía módulo TL) | M103: 12 VDC | N103: 15 mA | O103: — | P103: 0 °C a +49 °C | Q103: 70 × 45 × 33 mm | R103: 80 g | S103: UL, CE, EN 50131 grado 2 | T103: Interior residencial/comercial | U103: 20 | X103: Salida tamper y EOL supervisada | Y103: 0.015 | Z103: 0.021 | AA103: 12 | AB103: Contact ID / SIA (vía módulo TL) | AC103: Zona 12 V universal — centrales PowerSeries Neo/PC (Keybus) y compatibles | AD103: N/A | AE103: N/A | AF103: N/A | AG103: N/A | AH103: N/A | AI103: N/A | AJ103: 12 | AK103: N/A | AL103: 90 | AM103: Volumétrica rectangular (lentes múltiples) | AN103: N/A | AO103: 2 | AP103: 2.7
B104: 100 | C104: DSC | D104: Alta | E104: Canadá | F104: Detector PIR interior | G104: DSC PIR-99 | H104: 12 m · 110° | I104: PIR con lente Fresnel espejo | J104: Pet-inmune hasta 27 kg, filtro DigitalFLEX | K104: Zona alámbrica | L104: Contact ID / SIA (vía módulo TL) | M104: 12 VDC | N104: 15 mA | O104: — | P104: 0 °C a +49 °C | Q104: 70 × 45 × 33 mm | R104: 80 g | S104: UL, CE, EN 50131 grado 2 | T104: Interior residencial/comercial | U104: 35 | X104: Capacidad y rendimiento mejorados | Y104: 0.013 | Z104: 0.018 | AA104: 12 | AB104: Contact ID / SIA (vía módulo TL) | AC104: Zona 12 V universal — centrales PowerSeries Neo/PC (Keybus) y compatibles | AD104: N/A | AE104: N/A | AF104: N/A | AG104: N/A | AH104: N/A | AI104: N/A | AJ104: 12 | AK104: N/A | AL104: 110 | AM104: Volumétrica rectangular (lentes múltiples) | AN104: N/A | AO104: 2 | AP104: 2.7
B105: 101 | C105: DSC | D105: Alta | E105: Canadá | F105: Detector PIR interior | G105: EC-401 | H105: 15 m · 110° | I105: PIR con lente Fresnel espejo | J105: Pet-inmune hasta 27 kg, filtro DigitalFLEX | K105: Zona alámbrica | L105: Contact ID / SIA (vía módulo TL) | M105: 12 VDC | N105: 15 mA | O105: — | P105: 0 °C a +49 °C | Q105: 70 × 45 × 33 mm | R105: 80 g | S105: UL, CE, EN 50131 grado 2 | T105: Interior residencial/comercial | U105: 50 | X105: Tope de gama — máxima especificación | Y105: 0.01 | Z105: 0.014 | AA105: 12 | AB105: Contact ID / SIA (vía módulo TL) | AC105: Zona 12 V universal — centrales PowerSeries Neo/PC (Keybus) y compatibles | AD105: N/A | AE105: N/A | AF105: N/A | AG105: N/A | AH105: N/A | AI105: N/A | AJ105: 15 | AK105: N/A | AL105: 110 | AM105: Volumétrica rectangular (lentes múltiples) | AN105: N/A | AO105: 2 | AP105: 2.7
B106: 102 | C106: DSC | D106: Alta | E106: Canadá | F106: PIR inalámbrico | G106: WS4904 | H106: 8 m · 90° | I106: PIR inalámbrico 433 MHz | J106: Pet-inmune hasta 18 kg | K106: Transmisión 433 a panel | L106: Contact ID / SIA (vía módulo TL) | M106: Batería CR123A | N106: 20 µA reposo | O106: — | P106: 0 °C a +49 °C | Q106: 90 × 60 × 45 mm | R106: 105 g | S106: UL, CE, EN 50131 grado 2 | T106: Interior residencial | U106: 18 | X106: Variante económica de la gama | Y106: 1.021e-05 | Z106: 2.895e-05 | AA106: 3 | AB106: Contact ID / SIA (vía módulo TL) | AC106: Exclusivo radio de marca: Neo RF5132/PowerSeries 433 (Alexor, Impassa) | AD106: N/A | AE106: N/A | AF106: N/A | AG106: N/A | AH106: N/A | AI106: N/A | AJ106: 8 | AK106: N/A | AL106: 90 | AM106: Volumétrica rectangular (lentes múltiples) | AN106: N/A | AO106: 2 | AP106: 2.7
...

Sheet Base de Datos SADI
B2: Base de Datos Técnica — SADI · Sistemas de Detección de Incendios (16 marcas × 16 tipos × 5 variantes)
B4: N° | C4: Marca | D4: Nivel | E4: País | F4: Tipo de Dispositivo | G4: Modelo | H4: Puntos / Lazos · Área | I4: Tecnología / Sensor | J4: Clase / Modo de Operación | K4: Comunicación / Red | L4: Protocolo del Lazo | M4: Alimentación | N4: Consumo | O4: Protección | P4: Temp. Operación | Q4: Dimensiones | R4: Peso | S4: Certificaciones | T4: Uso Recomendado | U4: Precio Ref. (USD) | V4: Proveedor | W4: Stock | X4: Observaciones | Y4: Consumo en Reposo (A) | Z4: Consumo en Alarma (A) | AA4: Tensión de Alimentación (V) | AB4: Protocolos Compatibles | AC4: Centrales Compatibles | AD4: Consumo en Reposo de la Central (A) | AE4: Consumo en Alarma de la Central (A) | AF4: Corriente Nominal de la Fuente (A) | AG4: Zonas de la Central | AH4: Lazos | AI4: Puntos por Lazo | AJ4: Área de Cobertura (m²) | AK4: Radio de Cobertura (m) | AL4: Alcance (m) | AM4: Apertura del Sector (grados) | AN4: Forma de Cobertura | AO4: Potencia Acústica (W) | AP4: Altura Mínima de Montaje (m) | AQ4: Altura Máxima de Montaje (m)
B5: 1 | C5: Honeywell Fire | D5: Alta | E5: EE. UU. | F5: Panel direccionable | G5: MS-9050UD | H5: 2 lazos · 318 puntos | I5: Central direccionable con procesador dual | J5: Sincronización Notifier, LCD-160 display | K5: Red Notifier ONNX / SNMP | L5: Protocolo Notifier (ONNX) | M5: 120/240 VAC · baterías 12 V 18 Ah | N5: 500 mA en reposo | O5: — | P5: 0 °C a +49 °C | Q5: 406 × 457 × 117 mm | R5: 14.5 kg | S5: UL 864 (10.ª ed.), FM, CE | T5: Edificios medianos y grandes | U5: 640 | X5: Variante económica de la gama | Y5: 0.5 | Z5: 1.367 | AA5: 24 | AB5: Protocolo Notifier (ONNX) | AC5: Central maestra — Centrales Notifier (protocolo ONNX/FlashScan) | AD5: 0.5 | AE5: 1.367 | AF5: 6 | AG5: N/A | AH5: 2 | AI5: 318 | AJ5: N/A | AK5: N/A | AL5: N/A | AM5: N/A | AN5: N/A | AO5: N/A | AP5: N/A | AQ5: N/A
B6: 2 | C6: Honeywell Fire | D6: Alta | E6: EE. UU. | F6: Panel direccionable | G6: NFS-320 | H6: 2 lazos · 318 puntos | I6: Central direccionable con procesador dual | J6: Sincronización Notifier, LCD-160 display | K6: Red Notifier ONNX / SNMP | L6: Protocolo Notifier (ONNX) | M6: 120/240 VAC · baterías 12 V 18 Ah | N6: 500 mA en reposo | O6: — | P6: 0 °C a +49 °C | Q6: 406 × 457 × 117 mm | R6: 14.5 kg | S6: UL 864 (10.ª ed.), FM, CE | T6: Edificios medianos y grandes | U6: 960 | X6: Gama de entrada | Y6: 0.5 | Z6: 1.982 | AA6: 24 | AB6: Protocolo Notifier (ONNX) | AC6: Central maestra — Centrales Notifier (protocolo ONNX/FlashScan) | AD6: 0.5 | AE6: 1.982 | AF6: 6 | AG6: N/A | AH6: 2 | AI6: 318 | AJ6: N/A | AK6: N/A | AL6: N/A | AM6: N/A | AN6: N/A | AO6: N/A | AP6: N/A | AQ6: N/A
B7: 3 | C7: Honeywell Fire | D7: Alta | E7: EE. UU. | F7: Panel direccionable | G7: NFS2-640 | H7: 2 lazos · 318 puntos | I7: Central direccionable con procesador dual | J7: Sincronización Notifier, LCD-160 display | K7: Red Notifier ONNX / SNMP | L7: Protocolo Notifier (ONNX) | M7: 120/240 VAC · baterías 12 V 18 Ah | N7: 500 mA en reposo | O7: — | P7: 0 °C a +49 °C | Q7: 406 × 457 × 117 mm | R7: 14.5 kg | S7: UL 864 (10.ª ed.), FM, CE | T7: Edificios medianos y grandes | U7: 1280 | X7: Ampliable a 4 lazos con módulos | Y7: 0.5 | Z7: 2.787 | AA7: 24 | AB7: Protocolo Notifier (ONNX) | AC7: Central maestra — Centrales Notifier (protocolo ONNX/FlashScan) | AD7: 0.5 | AE7: 2.787 | AF7: 6 | AG7: N/A | AH7: 2 | AI7: 318 | AJ7: N/A | AK7: N/A | AL7: N/A | AM7: N/A | AN7: N/A | AO7: N/A | AP7: N/A | AQ7: N/A
B8: 4 | C8: Honeywell Fire | D8: Alta | E8: EE. UU. | F8: Panel direccionable | G8: NFS2-3030 | H8: 2 lazos · 318 puntos | I8: Central direccionable con procesador dual | J8: Sincronización Notifier, LCD-160 display | K8: Red Notifier ONNX / SNMP | L8: Protocolo Notifier (ONNX) | M8: 120/240 VAC · baterías 12 V 18 Ah | N8: 500 mA en reposo | O8: — | P8: 0 °C a +49 °C | Q8: 406 × 457 × 117 mm | R8: 14.5 kg | S8: UL 864 (10.ª ed.), FM, CE | T8: Edificios medianos y grandes | U8: 1920 | X8: Capacidad y rendimiento mejorados | Y8: 0.5 | Z8: 2.783 | AA8: 24 | AB8: Protocolo Notifier (ONNX) | AC8: Central maestra — Centrales Notifier (protocolo ONNX/FlashScan) | AD8: 0.5 | AE8: 2.783 | AF8: 6 | AG8: N/A | AH8: 2 | AI8: 318 | AJ8: N/A | AK8: N/A | AL8: N/A | AM8: N/A | AN8: N/A | AO8: N/A | AP8: N/A | AQ8: N/A
B9: 5 | C9: Honeywell Fire | D9: Alta | E9: EE. UU. | F9: Panel direccionable | G9: NFS-320E | H9: 2 lazos · 318 puntos | I9: Central direccionable con procesador dual | J9: Sincronización Notifier, LCD-160 display | K9: Red Notifier ONNX / SNMP | L9: Protocolo Notifier (ONNX) | M9: 120/240 VAC · baterías 12 V 18 Ah | N9: 500 mA en reposo | O9: — | P9: 0 °C a +49 °C | Q9: 406 × 457 × 117 mm | R9: 14.5 kg | S9: UL 864 (10.ª ed.), FM, CE | T9: Edificios medianos y grandes | U9: 2815 | X9: Tope de gama — máxima especificación | Y9: 0.5 | Z9: 1.869 | AA9: 24 | AB9: Protocolo Notifier (ONNX) | AC9: Central maestra — Centrales Notifier (protocolo ONNX/FlashScan) | AD9: 0.5 | AE9: 1.869 | AF9: 6 | AG9: N/A | AH9: 2 | AI9: 318 | AJ9: N/A | AK9: N/A | AL9: N/A | AM9: N/A | AN9: N/A | AO9: N/A | AP9: N/A | AQ9: N/A
B10: 6 | C10: Honeywell Fire | D10: Alta | E10: EE. UU. | F10: Panel convencional | G10: No disponible en portafolio | X10: Notifier es direccionable; línea convencional bajo Fire-Lite (MS-9050UD) | Y10: N/A | Z10: N/A | AA10: N/A | AB10: N/A | AC10: N/A | AD10: N/A | AE10: N/A | AF10: N/A | AG10: N/A | AH10: N/A | AI10: N/A | AJ10: N/A | AK10: N/A | AL10: N/A | AM10: N/A | AN10: N/A | AO10: N/A | AP10: N/A | AQ10: N/A
B11: 7 | C11: Honeywell Fire | D11: Alta | E11: EE. UU. | F11: Humo convencional | G11: No disponible en portafolio | X11: Línea convencional bajo Fire-Lite / System Sensor i3 | Y11: N/A | Z11: N/A | AA11: N/A | AB11: N/A | AC11: N/A | AD11: N/A | AE11: N/A | AF11: N/A | AG11: N/A | AH11: N/A | AI11: N/A | AJ11: N/A | AK11: N/A | AL11: N/A | AM11: N/A | AN11: N/A | AO11: N/A | AP11: N/A | AQ11: N/A
B12: 8 | C12: Honeywell Fire | D12: Alta | E12: EE. UU. | F12: Humo direccionable | G12: FSP-851 | H12: Área 60 m² | I12: Óptico fotoeléctrico con cámara inmune a polvo | J12: Sensibilidad ajustable, deriva compensada | K12: Lazo Notifier | L12: Protocolo Notifier (ONNX) | M12: Lazo 24 VDC | N12: — | O12: — | P12: 0 °C a +49 °C | Q12: Ø 102 × 42 mm + base | R12: 160 g | S12: UL 864 (10.ª ed.), FM, CE | T12: Interior general (oficinas, aulas) | U12: 40 | X12: Variante económica de la gama | Y12: 7.982e-05 | Z12: 0.003 | AA12: 24 | AB12: Protocolo Notifier (ONNX) | AC12: Centrales Notifier (protocolo ONNX/FlashScan) | AD12: N/A | AE12: N/A | AF12: N/A | AG12: N/A | AH12: N/A | AI12: N/A | AJ12: 60 | AK12: N/A | AL12: N/A | AM12: N/A | AN12: Volumétrica cilíndrica (montaje techo) | AO12: N/A | AP12: 2.5 | AQ12: 6
B13: 9 | C13: Honeywell Fire | D13: Alta | E13: EE. UU. | F13: Humo direccionable | G13: FSP-951 | H13: Área 80 m² | I13: Óptico fotoeléctrico con cámara inmune a polvo | J13: Sensibilidad ajustable, deriva compensada | K13: Lazo Notifier | L13: Protocolo Notifier (ONNX) | M13: Lazo 24 VDC | N13: — | O13: — | P13: 0 °C a +49 °C | Q13: Ø 102 × 42 mm + base | R13: 160 g | S13: UL 864 (10.ª ed.), FM, CE | T13: Interior general (oficinas, aulas) | U13: 60 | X13: Gama de entrada | Y13: 6.772e-05 | Z13: 0.002 | AA13: 24 | AB13: Protocolo Notifier (ONNX) | AC13: Centrales Notifier (protocolo ONNX/FlashScan) | AD13: N/A | AE13: N/A | AF13: N/A | AG13: N/A | AH13: N/A | AI13: N/A | AJ13: 80 | AK13: N/A | AL13: N/A | AM13: N/A | AN13: Volumétrica cilíndrica (montaje techo) | AO13: N/A | AP13: 2.5 | AQ13: 6
B14: 10 | C14: Honeywell Fire | D14: Alta | E14: EE. UU. | F14: Humo direccionable | G14: FSA-951 | H14: Área 100 m² | I14: Óptico fotoeléctrico con cámara inmune a polvo | J14: Sensibilidad ajustable, deriva compensada | K14: Lazo Notifier | L14: Protocolo Notifier (ONNX) | M14: Lazo 24 VDC | N14: — | O14: — | P14: 0 °C a +49 °C | Q14: Ø 102 × 42 mm + base | R14: 160 g | S14: UL 864 (10.ª ed.), FM, CE | T14: Interior general (oficinas, aulas) | U14: 85 | X14: Base B210LP incluida; detector de referencia | Y14: 8.911e-05 | Z14: 0.003 | AA14: 24 | AB14: Protocolo Notifier (ONNX) | AC14: Centrales Notifier (protocolo ONNX/FlashScan) | AD14: N/A | AE14: N/A | AF14: N/A | AG14: N/A | AH14: N/A | AI14: N/A | AJ14: 100 | AK14: N/A | AL14: N/A | AM14: N/A | AN14: Volumétrica cilíndrica (montaje techo) | AO14: N/A | AP14: 2.5 | AQ14: 6
B15: 11 | C15: Honeywell Fire | D15: Alta | E15: EE. UU. | F15: Humo direccionable | G15: FAPT-851 | H15: Área 100 m² + direccionamiento | I15: Óptico fotoeléctrico con cámara inmune a polvo | J15: Sensibilidad ajustable, deriva compensada | K15: Lazo Notifier | L15: Protocolo Notifier (ONNX) | M15: Lazo 24 VDC | N15: — | O15: — | P15: 0 °C a +49 °C | Q15: Ø 102 × 42 mm + base | R15: 160 g | S15: UL 864 (10.ª ed.), FM, CE | T15: Interior general (oficinas, aulas) | U15: 125 | X15: Capacidad y rendimiento mejorados | Y15: 0.00011557 | Z15: 0.005 | AA15: 24 | AB15: Protocolo Notifier (ONNX) | AC15: Centrales Notifier (protocolo ONNX/FlashScan) | AD15: N/A | AE15: N/A | AF15: N/A | AG15: N/A | AH15: N/A | AI15: N/A | AJ15: 100 | AK15: N/A | AL15: N/A | AM15: N/A | AN15: Volumétrica cilíndrica (montaje techo) | AO15: N/A | AP15: 2.5 | AQ15: 6
B16: 12 | C16: Honeywell Fire | D16: Alta | E16: EE. UU. | F16: Humo direccionable | G16: FSA-210B | H16: Área 120 m² | I16: Óptico fotoeléctrico con cámara inmune a polvo | J16: Sensibilidad ajustable, deriva compensada | K16: Lazo Notifier | L16: Protocolo Notifier (ONNX) | M16: Lazo 24 VDC | N16: — | O16: — | P16: 0 °C a +49 °C | Q16: Ø 102 × 42 mm + base | R16: 160 g | S16: UL 864 (10.ª ed.), FM, CE | T16: Interior general (oficinas, aulas) | U16: 185 | X16: Tope de gama — máxima especificación | Y16: 7.025e-05 | Z16: 0.003 | AA16: 24 | AB16: Protocolo Notifier (ONNX) | AC16: Centrales Notifier (protocolo ONNX/FlashScan) | AD16: N/A | AE16: N/A | AF16: N/A | AG16: N/A | AH16: N/A | AI16: N/A | AJ16: 120 | AK16: N/A | AL16: N/A | AM16: N/A | AN16: Volumétrica cilíndrica (montaje techo) | AO16: N/A | AP16: 2.5 | AQ16: 6
B17: 13 | C17: Honeywell Fire | D17: Alta | E17: EE. UU. | F17: Térmico direccionable | G17: FST-851 | H17: Clase A1R | I17: Termovelocimétrico 57 °C con termistor | J17: Clase A1R (EN 54-5), compensación de deriva | K17: Lazo Notifier | L17: Protocolo Notifier (ONNX) | M17: Lazo 24 VDC | N17: — | O17: — | P17: 0 °C a +49 °C | Q17: Ø 102 × 42 mm + base | R17: 155 g | S17: UL 864 (10.ª ed.), FM, CE | T17: Cocinas, cuartos técnicos | U17: 40 | X17: Variante económica de la gama | Y17: 5.087e-05 | Z17: 0.002 | AA17: 24 | AB17: Protocolo Notifier (ONNX) | AC17: Centrales Notifier (protocolo ONNX/FlashScan) | AD17: N/A | AE17: N/A | AF17: N/A | AG17: N/A | AH17: N/A | AI17: N/A | AJ17: 40 | AK17: N/A | AL17: N/A | AM17: N/A | AN17: Volumétrica cilíndrica (montaje techo) | AO17: N/A | AP17: 2.5 | AQ17: 6
B18: 14 | C18: Honeywell Fire | D18: Alta | E18: EE. UU. | F18: Térmico direccionable | G18: FST-951 | H18: Clase A1S | I18: Termovelocimétrico 57 °C con termistor | J18: Clase A1R (EN 54-5), compensación de deriva | K18: Lazo Notifier | L18: Protocolo Notifier (ONNX) | M18: Lazo 24 VDC | N18: — | O18: — | P18: 0 °C a +49 °C | Q18: Ø 102 × 42 mm + base | R18: 155 g | S18: UL 864 (10.ª ed.), FM, CE | T18: Cocinas, cuartos técnicos | U18: 60 | X18: Gama de entrada | Y18: 7.951e-05 | Z18: 0.003 | AA18: 24 | AB18: Protocolo Notifier (ONNX) | AC18: Centrales Notifier (protocolo ONNX/FlashScan) | AD18: N/A | AE18: N/A | AF18: N/A | AG18: N/A | AH18: N/A | AI18: N/A | AJ18: 50 | AK18: N/A | AL18: N/A | AM18: N/A | AN18: Volumétrica cilíndrica (montaje techo) | AO18: N/A | AP18: 2.5 | AQ18: 6
B19: 15 | C19: Honeywell Fire | D19: Alta | E19: EE. UU. | F19: Térmico direccionable | G19: FST-951R | H19: Clase A2S | I19: Termovelocimétrico 57 °C con termistor | J19: Clase A1R (EN 54-5), compensación de deriva | K19: Lazo Notifier | L19: Protocolo Notifier (ONNX) | M19: Lazo 24 VDC | N19: — | O19: — | P19: 0 °C a +49 °C | Q19: Ø 102 × 42 mm + base | R19: 155 g | S19: UL 864 (10.ª ed.), FM, CE | T19: Cocinas, cuartos técnicos | U19: 80 | X19: Opción con aislador FST-951R | Y19: 0.00010221 | Z19: 0.005 | AA19: 24 | AB19: Protocolo Notifier (ONNX) | AC19: Centrales Notifier (protocolo ONNX/FlashScan) | AD19: N/A | AE19: N/A | AF19: N/A | AG19: N/A | AH19: N/A | AI19: N/A | AJ19: 57 | AK19: N/A | AL19: N/A | AM19: N/A | AN19: Volumétrica cilíndrica (montaje techo) | AO19: N/A | AP19: 2.5 | AQ19: 6
B20: 16 | C20: Honeywell Fire | D20: Alta | E20: EE. UU. | F20: Térmico direccionable | G20: FST-951V | H20: A2S + compensación deriva | I20: Termovelocimétrico 57 °C con termistor | J20: Clase A1R (EN 54-5), compensación de deriva | K20: Lazo Notifier | L20: Protocolo Notifier (ONNX) | M20: Lazo 24 VDC | N20: — | O20: — | P20: 0 °C a +49 °C | Q20: Ø 102 × 42 mm + base | R20: 155 g | S20: UL 864 (10.ª ed.), FM, CE | T20: Cocinas, cuartos técnicos | U20: 120 | X20: Capacidad y rendimiento mejorados | Y20: 0.0001003 | Z20: 0.005 | AA20: 24 | AB20: Protocolo Notifier (ONNX) | AC20: Centrales Notifier (protocolo ONNX/FlashScan) | AD20: N/A | AE20: N/A | AF20: N/A | AG20: N/A | AH20: N/A | AI20: N/A | AJ20: 57 | AK20: N/A | AL20: N/A | AM20: N/A | AN20: Volumétrica cilíndrica (montaje techo) | AO20: N/A | AP20: 2.5 | AQ20: 6
B21: 17 | C21: Honeywell Fire | D21: Alta | E21: EE. UU. | F21: Térmico direccionable | G21: FSA-210T | H21: CS + compensación | I21: Termovelocimétrico 57 °C con termistor | J21: Clase A1R (EN 54-5), compensación de deriva | K21: Lazo Notifier | L21: Protocolo Notifier (ONNX) | M21: Lazo 24 VDC | N21: — | O21: — | P21: 0 °C a +49 °C | Q21: Ø 102 × 42 mm + base | R21: 155 g | S21: UL 864 (10.ª ed.), FM, CE | T21: Cocinas, cuartos técnicos | U21: 180 | X21: Tope de gama — máxima especificación | Y21: 5.365e-05 | Z21: 0.002 | AA21: 24 | AB21: Protocolo Notifier (ONNX) | AC21: Centrales Notifier (protocolo ONNX/FlashScan) | AD21: N/A | AE21: N/A | AF21: N/A | AG21: N/A | AH21: N/A | AI21: N/A | AJ21: 41 | AK21: N/A | AL21: N/A | AM21: N/A | AN21: Volumétrica cilíndrica (montaje techo) | AO21: N/A | AP21: 2.5 | AQ21: 6
B22: 18 | C22: Honeywell Fire | D22: Alta | E22: EE. UU. | F22: Multicriterio | G22: FSC-851 | H22: Humo + térmico | I22: Sensor multi-criterio láser-foto VIEW | J22: Algoritmos anti-falsa alarma con verificación doble | K22: Lazo Notifier | L22: Protocolo Notifier (ONNX) | M22: Lazo 24 VDC | N22: — | O22: — | P22: 0 °C a +49 °C | Q22: Ø 102 × 42 mm + base | R22: 165 g | S22: UL 864 (10.ª ed.), FM, CE | T22: Riesgos con falsas alarmas históricas | U22: 55 | X22: Variante económica de la gama | Y22: 0.00011664 | Z22: 0.005 | AA22: 24 | AB22: Protocolo Notifier (ONNX) | AC22: Centrales Notifier (protocolo ONNX/FlashScan) | AD22: N/A | AE22: N/A | AF22: N/A | AG22: N/A | AH22: N/A | AI22: N/A | AJ22: 101 | AK22: N/A | AL22: N/A | AM22: N/A | AN22: Volumétrica multi-sensor (humo+térmico+CO) | AO22: N/A | AP22: 2.5 | AQ22: 6
B23: 19 | C23: Honeywell Fire | D23: Alta | E23: EE. UU. | F23: Multicriterio | G23: FSC-851 (alta sensibilidad) | H23: Humo + térmico + CO | I23: Sensor multi-criterio láser-foto VIEW | J23: Algoritmos anti-falsa alarma con verificación doble | K23: Lazo Notifier | L23: Protocolo Notifier (ONNX) | M23: Lazo 24 VDC | N23: — | O23: — | P23: 0 °C a +49 °C | Q23: Ø 102 × 42 mm + base | R23: 165 g | S23: UL 864 (10.ª ed.), FM, CE | T23: Riesgos con falsas alarmas históricas | U23: 85 | X23: Gama de entrada | Y23: 0.00010981 | Z23: 0.004 | AA23: 24 | AB23: Protocolo Notifier (ONNX) | AC23: Centrales Notifier (protocolo ONNX/FlashScan) | AD23: N/A | AE23: N/A | AF23: N/A | AG23: N/A | AH23: N/A | AI23: N/A | AJ23: 97 | AK23: N/A | AL23: N/A | AM23: N/A | AN23: Volumétrica multi-sensor (humo+térmico+CO) | AO23: N/A | AP23: 2.5 | AQ23: 6
... B26: 22 | C26: Honeywell Fire | D26: Alta | E26: EE. UU. | F26: Multicriterio | G26: FSA-951 (referencia foto) | H26: Multi + verificación doble | I26: Sensor multi-criterio láser-foto VIEW | J26: Algoritmos anti-falsa alarma con verificación doble | K26: Lazo Notifier | L26: Protocolo Notifier (ONNX) | M26: Lazo 24 VDC | N26: — | O26: — | P26: 0 °C a +49 °C | Q26: Ø 102 × 42 mm + base | R26: 165 g | S26: UL 864 (10.ª ed.), FM, CE | T26: Riesgos con falsas alarmas históricas | U26: 255 | X26: Tope de gama — máxima especificación | Y26: 8.202e-05 | Z26: 0.003 | AA26: 24 | AB26: Protocolo Notifier (ONNX) | AC26: Centrales Notifier (protocolo ONNX/FlashScan) | AD26: N/A | AE26: N/A | AF26: N/A | AG26: N/A | AH26: N/A | AI26: N/A | AJ26: 81 | AK26: N/A | AL26: N/A | AM26: N/A | AN26: Volumétrica multi-sensor (humo+térmico+CO) | AO26: N/A | AP26: 2.5 | AQ26: 6
B27: 23 | C27: Honeywell Fire | D27: Alta | E27: EE. UU. | F27: Detector de llama | G27: No disponible en portafolio | X27: Flamas bajo Fire Sentry (Honeywell) FS-24X | Y27: N/A | Z27: N/A | AA27: N/A | AB27: N/A | AC27: N/A | AD27: N/A | AE27: N/A | AF27: N/A | AG27: N/A | AH27: N/A | AI27: N/A | AJ27: N/A | AK27: N/A | AL27: N/A | AM27: N/A | AN27: N/A | AO27: N/A | AP27: N/A | AQ27: N/A
B28: 24 | C28: Honeywell Fire | D28: Alta | E28: EE. UU. | F28: Aspiración (ASD) | G28: FAAST LT-100 | H28: Área 800 m² | I28: Aspiración láser con cámara de detección dual | J28: 4 umbrales de alarma, filtro de reemplazo | K28: Ethernet/IP + lazo opcional | L28: Protocolo Notifier (ONNX) | M28: 24 VDC | N28: 90 W máx con calefacción | O28: IP40 | P28: 0 °C a +49 °C | Q28: 330 × 225 × 130 mm | R28: 4.2 kg | S28: UL 864 (10.ª ed.), FM, CE | T28: Almacenes, centros de datos, atrios | U28: 1925 | X28: Variante económica de la gama | Y28: 1.294 | Z28: 1.991 | AA28: 24 | AB28: Protocolo Notifier (ONNX) | AC28: Autónomo con relés/Ethernet; integrable a Centrales Notifier (protocolo ONNX/FlashScan) vía módulo de monitoreo | AD28: N/A | AE28: N/A | AF28: N/A | AG28: N/A | AH28: N/A | AI28: N/A | AJ28: 800 | AK28: N/A | AL28: N/A | AM28: N/A | AN28: Muestreo por red de tubos (aspiración) | AO28: N/A | AP28: 2.5 | AQ28: 25
B29: 25 | C29: Honeywell Fire | D29: Alta | E29: EE. UU. | F29: Aspiración (ASD) | G29: FAAST LT-200 | H29: Área 1,000 m² | I29: Aspiración láser con cámara de detección dual | J29: 4 umbrales de alarma, filtro de reemplazo | K29: Ethernet/IP + lazo opcional | L29: Protocolo Notifier (ONNX) | M29: 24 VDC | N29: 90 W máx con calefacción | O29: IP40 | P29: 0 °C a +49 °C | Q29: 330 × 225 × 130 mm | R29: 4.2 kg | S29: UL 864 (10.ª ed.), FM, CE | T29: Almacenes, centros de datos, atrios | U29: 2885 | X29: Gama de entrada | Y29: 1.192 | Z29: 1.827 | AA29: 24 | AB29: Protocolo Notifier (ONNX) | AC29: Autónomo con relés/Ethernet; integrable a Centrales Notifier (protocolo ONNX/FlashScan) vía módulo de monitoreo | AD29: N/A | AE29: N/A | AF29: N/A | AG29: N/A | AH29: N/A | AI29: N/A | AJ29: 1000 | AK29: N/A | AL29: N/A | AM29: N/A | AN29: Muestreo por red de tubos (aspiración) | AO29: N/A | AP29: 2.5 | AQ29: 25
B30: 26 | C30: Honeywell Fire | D30: Alta | E30: EE. UU. | F30: Aspiración (ASD) | G30: FAAST XL-50 | H30: Área 1,600 m² | I30: Aspiración láser con cámara de detección dual | J30: 4 umbrales de alarma, filtro de reemplazo | K30: Ethernet/IP + lazo opcional | L30: Protocolo Notifier (ONNX) | M30: 24 VDC | N30: 90 W máx con calefacción | O30: IP40 | P30: 0 °C a +49 °C | Q30: 330 × 225 × 130 mm | R30: 4.2 kg | S30: UL 864 (10.ª ed.), FM, CE | T30: Almacenes, centros de datos, atrios | U30: 3850 | X30: FAAST LT con red Ethernet integrada | Y30: 1.241 | Z30: 1.906 | AA30: 24 | AB30: Protocolo Notifier (ONNX) | AC30: Autónomo con relés/Ethernet; integrable a Centrales Notifier (protocolo ONNX/FlashScan) vía módulo de monitoreo | AD30: N/A | AE30: N/A | AF30: N/A | AG30: N/A | AH30: N/A | AI30: N/A | AJ30: 1600 | AK30: N/A | AL30: N/A | AM30: N/A | AN30: Muestreo por red de tubos (aspiración) | AO30: N/A | AP30: 2.5 | AQ30: 25
B31: 27 | C31: Honeywell Fire | D31: Alta | E31: EE. UU. | F31: Aspiración (ASD) | G31: FAAST 810 | H31: Área 2,000 m² | I31: Aspiración láser con cámara de detección dual | J31: 4 umbrales de alarma, filtro de reemplazo | K31: Ethernet/IP + lazo opcional | L31: Protocolo Notifier (ONNX) | M31: 24 VDC | N31: 90 W máx con calefacción | O31: IP40 | P31: 0 °C a +49 °C | Q31: 330 × 225 × 130 mm | R31: 4.2 kg | S31: UL 864 (10.ª ed.), FM, CE | T31: Almacenes, centros de datos, atrios | U31: 5775 | X31: Capacidad y rendimiento mejorados | Y31: 0.909 | Z31: 1.374 | AA31: 24 | AB31: Protocolo Notifier (ONNX) | AC31: Autónomo con relés/Ethernet; integrable a Centrales Notifier (protocolo ONNX/FlashScan) vía módulo de monitoreo | AD31: N/A | AE31: N/A | AF31: N/A | AG31: N/A | AH31: N/A | AI31: N/A | AJ31: 2000 | AK31: N/A | AL31: N/A | AM31: N/A | AN31: Muestreo por red de tubos (aspiración) | AO31: N/A | AP31: 2.5 | AQ31: 25
B32: 28 | C32: Honeywell Fire | D32: Alta | E32: EE. UU. | F32: Aspiración (ASD) | G32: VESDA VLP-000 | H32: Área 2,500 m² | I32: Aspiración láser con cámara de detección dual | J32: 4 umbrales de alarma, filtro de reemplazo | K32: Ethernet/IP + lazo opcional | L32: Protocolo Notifier (ONNX) | M32: 24 VDC | N32: 90 W máx con calefacción | O32: IP40 | P32: 0 °C a +49 °C | Q32: 330 × 225 × 130 mm | R32: 4.2 kg | S32: UL 864 (10.ª ed.), FM, CE | T32: Almacenes, centros de datos, atrios | U32: 8470 | X32: Tope de gama — máxima especificación | Y32: 1.274 | Z32: 1.959 | AA32: 24 | AB32: Protocolo Notifier (ONNX) | AC32: Autónomo con relés/Ethernet; integrable a Centrales Notifier (protocolo ONNX/FlashScan) vía módulo de monitoreo | AD32: N/A | AE32: N/A | AF32: N/A | AG32: N/A | AH32: N/A | AI32: N/A | AJ32: 2500 | AK32: N/A | AL32: N/A | AM32: N/A | AN32: Muestreo por red de tubos (aspiración) | AO32: N/A | AP32: 2.5 | AQ32: 25
B33: 29 | C33: Honeywell Fire | D33: Alta | E33: EE. UU. | F33: Lineal de haz | G33: FSL-100 | H33: Alcance 50 m | I33: Haz proyectado láser con cámara refleja | J33: Compensación de deriva, anti-obstrucción | K33: Lazo Notifier | L33: Protocolo Notifier (ONNX) | M33: Lazo 24 VDC | N33: — | O33: — | P33: 0 °C a +49 °C | Q33: Transmisor 210 × 125 × 90 mm | R33: 620 g | S33: UL 864 (10.ª ed.), FM, CE | T33: Atrios, naves y grandes alturas | U33: 490 | X33: Variante económica de la gama | Y33: 0.053 | Z33: 0.073 | AA33: 24 | AB33: Protocolo Notifier (ONNX) | AC33: Centrales Notifier (protocolo ONNX/FlashScan) (lazo con base receptora) | AD33: N/A | AE33: N/A | AF33: N/A | AG33: N/A | AH33: N/A | AI33: N/A | AJ33: 650 | AK33: N/A | AL33: 50 | AM33: N/A | AN33: Lineal (haz proyectado) | AO33: N/A | AP33: 6 | AQ33: 50
B34: 30 | C34: Honeywell Fire | D34: Alta | E34: EE. UU. | F34: Lineal de haz | G34: FSL-751 | H34: Alcance 70 m | I34: Haz proyectado láser con cámara refleja | J34: Compensación de deriva, anti-obstrucción | K34: Lazo Notifier | L34: Protocolo Notifier (ONNX) | M34: Lazo 24 VDC | N34: — | O34: — | P34: 0 °C a +49 °C | Q34: Transmisor 210 × 125 × 90 mm | R34: 620 g | S34: UL 864 (10.ª ed.), FM, CE | T34: Atrios, naves y grandes alturas | U34: 735 | X34: Gama de entrada | Y34: 0.054 | Z34: 0.074 | AA34: 24 | AB34: Protocolo Notifier (ONNX) | AC34: Centrales Notifier (protocolo ONNX/FlashScan) (lazo con base receptora) | AD34: N/A | AE34: N/A | AF34: N/A | AG34: N/A | AH34: N/A | AI34: N/A | AJ34: 910 | AK34: N/A | AL34: 70 | AM34: N/A | AN34: Lineal (haz proyectado) | AO34: N/A | AP34: 6 | AQ34: 70
B35: 31 | C35: Honeywell Fire | D35: Alta | E35: EE. UU. | F35: Lineal de haz | G35: FSL-756 | H35: Alcance 100 m | I35: Haz proyectado láser con cámara refleja | J35: Compensación de deriva, anti-obstrucción | K35: Lazo Notifier | L35: Protocolo Notifier (ONNX) | M35: Lazo 24 VDC | N35: — | O35: — | P35: 0 °C a +49 °C | Q35: Transmisor 210 × 125 × 90 mm | R35: 620 g | S35: UL 864 (10.ª ed.), FM, CE | T35: Atrios, naves y grandes alturas | U35: 985 | X35: Detección para techos de 8-100 m | Y35: 0.048 | Z35: 0.068 | AA35: 24 | AB35: Protocolo Notifier (ONNX) | AC35: Centrales Notifier (protocolo ONNX/FlashScan) (lazo con base receptora) | AD35: N/A | AE35: N/A | AF35: N/A | AG35: N/A | AH35: N/A | AI35: N/A | AJ35: 1200 | AK35: N/A | AL35: 100 | AM35: N/A | AN35: Lineal (haz proyectado) | AO35: N/A | AP35: 6 | AQ35: 100
B36: 32 | C36: Honeywell Fire | D36: Alta | E36: EE. UU. | F36: Lineal de haz | G36: FS-24X-BEAM | H36: 100 m auto-alineado | I36: Haz proyectado láser con cámara refleja | J36: Compensación de deriva, anti-obstrucción | K36: Lazo Notifier | L36: Protocolo Notifier (ONNX) | M36: Lazo 24 VDC | N36: — | O36: — | P36: 0 °C a +49 °C | Q36: Transmisor 210 × 125 × 90 mm | R36: 620 g | S36: UL 864 (10.ª ed.), FM, CE | T36: Atrios, naves y grandes alturas | U36: 1475 | X36: Capacidad y rendimiento mejorados | Y36: 0.04 | Z36: 0.06 | AA36: 24 | AB36: Protocolo Notifier (ONNX) | AC36: Centrales Notifier (protocolo ONNX/FlashScan) (lazo con base receptora) | AD36: N/A | AE36: N/A | AF36: N/A | AG36: N/A | AH36: N/A | AI36: N/A | AJ36: 1000 | AK36: N/A | AL36: 100 | AM36: N/A | AN36: Lineal (haz proyectado) | AO36: N/A | AP36: 6 | AQ36: 100
B37: 33 | C37: Honeywell Fire | D37: Alta | E37: EE. UU. | F37: Lineal de haz | G37: FSL-251 | H37: 150 m auto-alineado | I37: Haz proyectado láser con cámara refleja | J37: Compensación de deriva, anti-obstrucción | K37: Lazo Notifier | L37: Protocolo Notifier (ONNX) | M37: Lazo 24 VDC | N37: — | O37: — | P37: 0 °C a +49 °C | Q37: Transmisor 210 × 125 × 90 mm | R37: 620 g | S37: UL 864 (10.ª ed.), FM, CE | T37: Atrios, naves y grandes alturas | U37: 2165 | X37: Tope de gama — máxima especificación | Y37: 0.047 | Z37: 0.067 | AA37: 24 | AB37: Protocolo Notifier (ONNX) | AC37: Centrales Notifier (protocolo ONNX/FlashScan) (lazo con base receptora) | AD37: N/A | AE37: N/A | AF37: N/A | AG37: N/A | AH37: N/A | AI37: N/A | AJ37: 1650 | AK37: N/A | AL37: 150 | AM37: N/A | AN37: Lineal (haz proyectado) | AO37: N/A | AP37: 6 | AQ37: 150
B38: 34 | C38: Honeywell Fire | D38: Alta | E38: EE. UU. | F38: Estación manual | G38: NBG-12LX | H38: Simple acción | I38: Palanca doble acción con llave de rearme | J38: Cerradura knock-down reutilizable | K38: Lazo Notifier | L38: Protocolo Notifier (ONNX) | M38: Lazo 24 VDC | N38: — | O38: — | P38: 0 °C a +49 °C | Q38: 120 × 120 × 40 mm | R38: 220 g | S38: UL 864 (10.ª ed.), FM, CE | T38: Vías de evacuación (NFPA 72) | U38: 30 | X38: Variante económica de la gama | Y38: 0.00020742 | Z38: 0.003 | AA38: 24 | AB38: Protocolo Notifier (ONNX) | AC38: Centrales Notifier (protocolo ONNX/FlashScan) | AD38: N/A | AE38: N/A | AF38: N/A | AG38: N/A | AH38: N/A | AI38: N/A | AJ38: N/A | AK38: N/A | AL38: N/A | AM38: N/A | AN38: N/A | AO38: N/A | AP38: 1.05 | AQ38: 1.4
B39: 35 | C39: Honeywell Fire | D39: Alta | E39: EE. UU. | F39: Estación manual | G39: NBG-12LX-A | H39: Simple acción rearmable | I39: Palanca doble acción con llave de rearme | J39: Cerradura knock-down reutilizable | K39: Lazo Notifier | L39: Protocolo Notifier (ONNX) | M39: Lazo 24 VDC | N39: — | O39: — | P39: 0 °C a +49 °C | Q39: 120 × 120 × 40 mm | R39: 220 g | S39: UL 864 (10.ª ed.), FM, CE | T39: Vías de evacuación (NFPA 72) | U39: 50 | X39: Gama de entrada | Y39: 0.0003278 | Z39: 0.004 | AA39: 24 | AB39: Protocolo Notifier (ONNX) | AC39: Centrales Notifier (protocolo ONNX/FlashScan) | AD39: N/A | AE39: N/A | AF39: N/A | AG39: N/A | AH39: N/A | AI39: N/A | AJ39: N/A | AK39: N/A | AL39: N/A | AM39: N/A | AN39: N/A | AO39: N/A | AP39: 1.05 | AQ39: 1.4
B40: 36 | C40: Honeywell Fire | D40: Alta | E40: EE. UU. | F40: Estación manual | G40: NBG-12LO | H40: Doble acción | I40: Palanca doble acción con llave de rearme | J40: Cerradura knock-down reutilizable | K40: Lazo Notifier | L40: Protocolo Notifier (ONNX) | M40: Lazo 24 VDC | N40: — | O40: — | P40: 0 °C a +49 °C | Q40: 120 × 120 × 40 mm | R40: 220 g | S40: UL 864 (10.ª ed.), FM, CE | T40: Vías de evacuación (NFPA 72) | U40: 65 | X40: Incluye aislador opcional | Y40: 0.00034486 | Z40: 0.004 | AA40: 24 | AB40: Protocolo Notifier (ONNX) | AC40: Centrales Notifier (protocolo ONNX/FlashScan) | AD40: N/A | AE40: N/A | AF40: N/A | AG40: N/A | AH40: N/A | AI40: N/A | AJ40: N/A | AK40: N/A | AL40: N/A | AM40: N/A | AN40: N/A | AO40: N/A | AP40: 1.05 | AQ40: 1.4
B41: 37 | C41: Honeywell Fire | D41: Alta | E41: EE. UU. | F41: Estación manual | G41: NBG-12LSP | H41: Doble acción + indicador | I41: Palanca doble acción con llave de rearme | J41: Cerradura knock-down reutilizable | K41: Lazo Notifier | L41: Protocolo Notifier (ONNX) | M41: Lazo 24 VDC | N41: — | O41: — | P41: 0 °C a +49 °C | Q41: 120 × 120 × 40 mm | R41: 220 g | S41: UL 864 (10.ª ed.), FM, CE | T41: Vías de evacuación (NFPA 72) | U41: 100 | X41: Capacidad y rendimiento mejorados | Y41: 0.0003554 | Z41: 0.005 | AA41: 24 | AB41: Protocolo Notifier (ONNX) | AC41: Centrales Notifier (protocolo ONNX/FlashScan) | AD41: N/A | AE41: N/A | AF41: N/A | AG41: N/A | AH41: N/A | AI41: N/A | AJ41: N/A | AK41: N/A | AL41: N/A | AM41: N/A | AN41: N/A | AO41: N/A | AP41: 1.05 | AQ41: 1.4
B42: 38 | C42: Honeywell Fire | D42: Alta | E42: EE. UU. | F42: Estación manual | G42: M500K | H42: Direccionable con aislador | I42: Palanca doble acción con llave de rearme | J42: Cerradura knock-down reutilizable | K42: Lazo Notifier | L42: Protocolo Notifier (ONNX) | M42: Lazo 24 VDC | N42: — | O42: — | P42: 0 °C a +49 °C | Q42: 120 × 120 × 40 mm | R42: 220 g | S42: UL 864 (10.ª ed.), FM, CE | T42: Vías de evacuación (NFPA 72) | U42: 145 | X42: Tope de gama — máxima especificación | Y42: 0.00020136 | Z42: 0.003 | AA42: 24 | AB42: Protocolo Notifier (ONNX) | AC42: Centrales Notifier (protocolo ONNX/FlashScan) | AD42: N/A | AE42: N/A | AF42: N/A | AG42: N/A | AH42: N/A | AI42: N/A | AJ42: N/A | AK42: N/A | AL42: N/A | AM42: N/A | AN42: N/A | AO42: N/A | AP42: 1.05 | AQ42: 1.4
B43: 39 | C43: Honeywell Fire | D43: Alta | E43: EE. UU. | F43: Sirena con estrobo | G43: No disponible en portafolio | X43: Notificación bajo System Sensor SpectrAlert Advance | Y43: N/A | Z43: N/A | AA43: N/A | AB43: N/A | AC43: N/A | AD43: N/A | AE43: N/A | AF43: N/A | AG43: N/A | AH43: N/A | AI43: N/A | AJ43: N/A | AK43: N/A | AL43: N/A | AM43: N/A | AN43: N/A | AO43: N/A | AP43: N/A | AQ43: N/A
B44: 40 | C44: Honeywell Fire | D44: Alta | E44: EE. UU. | F44: Módulo de monitoreo | G44: FMM-1 | H44: 1 entrada | I44: Módulo direccionable FlashScan de monitoreo | J44: Monitorea zonas convencionales y contactos secos | K44: Lazo Notifier | L44: Protocolo Notifier (ONNX) | M44: Lazo 24 VDC | N44: — | O44: — | P44: 0 °C a +49 °C | Q44: 65 × 45 × 18 mm | R44: 60 g | S44: UL 864 (10.ª ed.), FM, CE | T44: Integración de equipos existentes | U44: 30 | X44: Variante económica de la gama | Y44: 0.00048252 | Z44: 0.006 | AA44: 24 | AB44: Protocolo Notifier (ONNX) | AC44: Centrales Notifier (protocolo ONNX/FlashScan) | AD44: N/A | AE44: N/A | AF44: N/A | AG44: N/A | AH44: N/A | AI44: N/A | AJ44: N/A | AK44: N/A | AL44: N/A | AM44: N/A | AN44: N/A | AO44: N/A | AP44: N/A | AQ44: N/A
B45: 41 | C45: Honeywell Fire | D45: Alta | E45: EE. UU. | F45: Módulo de monitoreo | G45: FMM-101 | H45: 1 entrada supervisada | I45: Módulo direccionable FlashScan de monitoreo | J45: Monitorea zonas convencionales y contactos secos | K45: Lazo Notifier | L45: Protocolo Notifier (ONNX) | M45: Lazo 24 VDC | N45: — | O45: — | P45: 0 °C a +49 °C | Q45: 65 × 45 × 18 mm | R45: 60 g | S45: UL 864 (10.ª ed.), FM, CE | T45: Integración de equipos existentes | U45: 45 | X45: Gama de entrada | Y45: 0.00052816 | Z45: 0.007 | AA45: 24 | AB45: Protocolo Notifier (ONNX) | AC45: Centrales Notifier (protocolo ONNX/FlashScan) | AD45: N/A | AE45: N/A | AF45: N/A | AG45: N/A | AH45: N/A | AI45: N/A | AJ45: N/A | AK45: N/A | AL45: N/A | AM45: N/A | AN45: N/A | AO45: N/A | AP45: N/A | AQ45: N/A
B46: 42 | C46: Honeywell Fire | D46: Alta | E46: EE. UU. | F46: Módulo de monitoreo | G46: FJM-5 | H46: 2 entradas | I46: Módulo direccionable FlashScan de monitoreo | J46: Monitorea zonas convencionales y contactos secos | K46: Lazo Notifier | L46: Protocolo Notifier (ONNX) | M46: Lazo 24 VDC | N46: — | O46: — | P46: 0 °C a +49 °C | Q46: 65 × 45 × 18 mm | R46: 60 g | S46: UL 864 (10.ª ed.), FM, CE | T46: Integración de equipos existentes | U46: 60 | X46: FMM-101 = versión miniatura; FZM-1 para zonas | Y46: 0.00043928 | Z46: 0.006 | AA46: 24 | AB46: Protocolo Notifier (ONNX) | AC46: Centrales Notifier (protocolo ONNX/FlashScan) | AD46: N/A | AE46: N/A | AF46: N/A | AG46: N/A | AH46: N/A | AI46: N/A | AJ46: N/A | AK46: N/A | AL46: N/A | AM46: N/A | AN46: N/A | AO46: N/A | AP46: N/A | AQ46: N/A
B47: 43 | C47: Honeywell Fire | D47: Alta | E47: EE. UU. | F47: Módulo de monitoreo | G47: FZM-1 | H47: 2 entradas + aislador | I47: Módulo direccionable FlashScan de monitoreo | J47: Monitorea zonas convencionales y contactos secos | K47: Lazo Notifier | L47: Protocolo Notifier (ONNX) | M47: Lazo 24 VDC | N47: — | O47: — | P47: 0 °C a +49 °C | Q47: 65 × 45 × 18 mm | R47: 60 g | S47: UL 864 (10.ª ed.), FM, CE | T47: Integración de equipos existentes | U47: 90 | X47: Capacidad y rendimiento mejorados | Y47: 0.00059636 | Z47: 0.008 | AA47: 24 | AB47: Protocolo Notifier (ONNX) | AC47: Centrales Notifier (protocolo ONNX/FlashScan) | AD47: N/A | AE47: N/A | AF47: N/A | AG47: N/A | AH47: N/A | AI47: N/A | AJ47: N/A | AK47: N/A | AL47: N/A | AM47: N/A | AN47: N/A | AO47: N/A | AP47: N/A | AQ47: N/A
B48: 44 | C48: Honeywell Fire | D48: Alta | E48: EE. UU. | F48: Módulo de monitoreo | G48: FMM-1 con aislador | H48: 4 entradas | I48: Módulo direccionable FlashScan de monitoreo | J48: Monitorea zonas convencionales y contactos secos | K48: Lazo Notifier | L48: Protocolo Notifier (ONNX) | M48: Lazo 24 VDC | N48: — | O48: — | P48: 0 °C a +49 °C | Q48: 65 × 45 × 18 mm | R48: 60 g | S48: UL 864 (10.ª ed.), FM, CE | T48: Integración de equipos existentes | U48: 130 | X48: Tope de gama — máxima especificación | Y48: 0.0004044 | Z48: 0.005 | AA48: 24 | AB48: Protocolo Notifier (ONNX) | AC48: Centrales Notifier (protocolo ONNX/FlashScan) | AD48: N/A | AE48: N/A | AF48: N/A | AG48: N/A | AH48: N/A | AI48: N/A | AJ48: N/A | AK48: N/A | AL48: N/A | AM48: N/A | AN48: N/A | AO48: N/A | AP48: N/A | AQ48: N/A
B49: 45 | C49: Honeywell Fire | D49: Alta | E49: EE. UU. | F49: Módulo de control/relevador | G49: FRM-1 | H49: 1 relevador | I49: Módulo direccionable de relevador FlashScan | J49: Controla equipos externos con confirmación de coils | K49: Lazo Notifier | L49: Protocolo Notifier (ONNX) | M49: Lazo 24 VDC | N49: — | O49: — | P49: 0 °C a +49 °C | Q49: 65 × 45 × 18 mm | R49: 60 g | S49: UL 864 (10.ª ed.), FM, CE | T49: Control de HVAC, ascensores y puertas | U49: 30 | X49: Variante económica de la gama | Y49: 0.00087548 | Z49: 0.058 | AA49: 24 | AB49: Protocolo Notifier (ONNX) | AC49: Centrales Notifier (protocolo ONNX/FlashScan) | AD49: N/A | AE49: N/A | AF49: N/A | AG49: N/A | AH49: N/A | AI49: N/A | AJ49: N/A | AK49: N/A | AL49: N/A | AM49: N/A | AN49: N/A | AO49: N/A | AP49: N/A | AQ49: N/A
B50: 46 | C50: Honeywell Fire | D50: Alta | E50: EE. UU. | F50: Módulo de control/relevador | G50: FCM-1 | H50: 1 relevador SPDT | I50: Módulo direccionable de relevador FlashScan | J50: Controla equipos externos con confirmación de coils | K50: Lazo Notifier | L50: Protocolo Notifier (ONNX) | M50: Lazo 24 VDC | N50: — | O50: — | P50: 0 °C a +49 °C | Q50: 65 × 45 × 18 mm | R50: 60 g | S50: UL 864 (10.ª ed.), FM, CE | T50: Control de HVAC, ascensores y puertas | U50: 50 | X50: Gama de entrada | Y50: 0.00070708 | Z50: 0.041 | AA50: 24 | AB50: Protocolo Notifier (ONNX) | AC50: Centrales Notifier (protocolo ONNX/FlashScan) | AD50: N/A | AE50: N/A | AF50: N/A | AG50: N/A | AH50: N/A | AI50: N/A | AJ50: N/A | AK50: N/A | AL50: N/A | AM50: N/A | AN50: N/A | AO50: N/A | AP50: N/A | AQ50: N/A
B51: 47 | C51: Honeywell Fire | D51: Alta | E51: EE. UU. | F51: Módulo de control/relevador | G51: FRM-1 con aislador | H51: 2 relevadores | I51: Módulo direccionable de relevador FlashScan | J51: Controla equipos externos con confirmación de coils | K51: Lazo Notifier | L51: Protocolo Notifier (ONNX) | M51: Lazo 24 VDC | N51: — | O51: — | P51: 0 °C a +49 °C | Q51: 65 × 45 × 18 mm | R51: 60 g | S51: UL 864 (10.ª ed.), FM, CE | T51: Control de HVAC, ascensores y puertas | U51: 65 | X51: FCM-1 = versión de control con alimentación supervisada | Y51: 0.0005046 | Z51: 0.02 | AA51: 24 | AB51: Protocolo Notifier (ONNX) | AC51: Centrales Notifier (protocolo ONNX/FlashScan) | AD51: N/A | AE51: N/A | AF51: N/A | AG51: N/A | AH51: N/A | AI51: N/A | AJ51: N/A | AK51: N/A | AL51: N/A | AM51: N/A | AN51: N/A | AO51: N/A | AP51: N/A | AQ51: N/A
B52: 48 | C52: Honeywell Fire | D52: Alta | E52: EE. UU. | F52: Módulo de control/relevador | G52: FCM-1 (SPDT) | H52: 2 relevadores + aislador | I52: Módulo direccionable de relevador FlashScan | J52: Controla equipos externos con confirmación de coils | K52: Lazo Notifier | L52: Protocolo Notifier (ONNX) | M52: Lazo 24 VDC | N52: — | O52: — | P52: 0 °C a +49 °C | Q52: 65 × 45 × 18 mm | R52: 60 g | S52: UL 864 (10.ª ed.), FM, CE | T52: Control de HVAC, ascensores y puertas | U52: 100 | X52: Capacidad y rendimiento mejorados | Y52: 0.00078468 | Z52: 0.048 | AA52: 24 | AB52: Protocolo Notifier (ONNX) | AC52: Centrales Notifier (protocolo ONNX/FlashScan) | AD52: N/A | AE52: N/A | AF52: N/A | AG52: N/A | AH52: N/A | AI52: N/A | AJ52: N/A | AK52: N/A | AL52: N/A | AM52: N/A | AN52: N/A | AO52: N/A | AP52: N/A | AQ52: N/A
B53: 49 | C53: Honeywell Fire | D53: Alta | E53: EE. UU. | F53: Módulo de control/relevador | G53: FRM-1 (mini) | H53: 4 relevadores | I53: Módulo direccionable de relevador FlashScan | J53: Controla equipos externos con confirmación de coils | K53: Lazo Notifier | L53: Protocolo Notifier (ONNX) | M53: Lazo 24 VDC | N53: — | O53: — | P53: 0 °C a +49 °C | Q53: 65 × 45 × 18 mm | R53: 60 g | S53: UL 864 (10.ª ed.), FM, CE | T53: Control de HVAC, ascensores y puertas | U53: 145 | X53: Tope de gama — máxima especificación | Y53: 0.0006084 | Z53: 0.031 | AA53: 24 | AB53: Protocolo Notifier (ONNX) | AC53: Centrales Notifier (protocolo ONNX/FlashScan) | AD53: N/A | AE53: N/A | AF53: N/A | AG53: N/A | AH53: N/A | AI53: N/A | AJ53: N/A | AK53: N/A | AL53: N/A | AM53: N/A | AN53: N/A | AO53: N/A | AP53: N/A | AQ53: N/A
B54: 50 | C54: Honeywell Fire | D54: Alta | E54: EE. UU. | F54: Terminal repetidora | G54: ANN-80 | H54: Anunciador LCD 80 caracteres | I54: Anunciador remoto Notifier con controles | J54: Indicación de alarma/problema y supervisión | K54: Bus EIA-485 (ACS) | L54: Protocolo Notifier (ONNX) | M54: 24 VDC desde central | N54: 85 mA | O54: — | P54: 0 °C a +49 °C | Q54: 222 × 165 × 50 mm | R54: 700 g | S54: UL 864 (10.ª ed.), FM, CE | T54: Lobbies y accesos (UL 864) | U54: 160 | X54: Variante económica de la gama | Y54: 0.085 | Z54: 0.243 | AA54: 24 | AB54: Protocolo Notifier (ONNX) | AC54: Centrales Notifier (protocolo ONNX/FlashScan) (red repetidora) | AD54: 0.085 | AE54: 0.243 | AF54: N/A | AG54: N/A | AH54: N/A | AI54: N/A | AJ54: N/A | AK54: N/A | AL54: N/A | AM54: N/A | AN54: N/A | AO54: N/A | AP54: 1.2 | AQ54: 1.7
B55: 51 | C55: Honeywell Fire | D55: Alta | E55: EE. UU. | F55: Terminal repetidora | G55: ANN-80-WH | H55: Anunciador LCD 80 caracteres | I55: Anunciador remoto Notifier con controles | J55: Indicación de alarma/problema y supervisión | K55: Bus EIA-485 (ACS) | L55: Protocolo Notifier (ONNX) | M55: 24 VDC desde central | N55: 85 mA | O55: — | P55: 0 °C a +49 °C | Q55: 222 × 165 × 50 mm | R55: 700 g | S55: UL 864 (10.ª ed.), FM, CE | T55: Lobbies y accesos (UL 864) | U55: 240 | X55: Gama de entrada | Y55: 0.085 | Z55: 0.295 | AA55: 24 | AB55: Protocolo Notifier (ONNX) | AC55: Centrales Notifier (protocolo ONNX/FlashScan) (red repetidora) | AD55: 0.085 | AE55: 0.295 | AF55: N/A | AG55: N/A | AH55: N/A | AI55: N/A | AJ55: N/A | AK55: N/A | AL55: N/A | AM55: N/A | AN55: N/A | AO55: N/A | AP55: 1.2 | AQ55: 1.7
B56: 52 | C56: Honeywell Fire | D56: Alta | E56: EE. UU. | F56: Terminal repetidora | G56: ANN-80-RLY | H56: Anunciador LCD 80 caracteres | I56: Anunciador remoto Notifier con controles | J56: Indicación de alarma/problema y supervisión | K56: Bus EIA-485 (ACS) | L56: Protocolo Notifier (ONNX) | M56: 24 VDC desde central | N56: 85 mA | O56: — | P56: 0 °C a +49 °C | Q56: 222 × 165 × 50 mm | R56: 700 g | S56: UL 864 (10.ª ed.), FM, CE | T56: Lobbies y accesos (UL 864) | U56: 320 | X56: ANN-80-WH en blanco; ANN-80-RLY con relevador | Y56: 0.085 | Z56: 0.178 | AA56: 24 | AB56: Protocolo Notifier (ONNX) | AC56: Centrales Notifier (protocolo ONNX/FlashScan) (red repetidora) | AD56: 0.085 | AE56: 0.178 | AF56: N/A | AG56: N/A | AH56: N/A | AI56: N/A | AJ56: N/A | AK56: N/A | AL56: N/A | AM56: N/A | AN56: N/A | AO56: N/A | AP56: 1.2 | AQ56: 1.7
B57: 53 | C57: Honeywell Fire | D57: Alta | E57: EE. UU. | F57: Terminal repetidora | G57: LCD-160 | H57: Anunciador LCD 80 caracteres | I57: Anunciador remoto Notifier con controles | J57: Indicación de alarma/problema y supervisión | K57: Bus EIA-485 (ACS) | L57: Protocolo Notifier (ONNX) | M57: 24 VDC desde central | N57: 85 mA | O57: — | P57: 0 °C a +49 °C | Q57: 222 × 165 × 50 mm | R57: 700 g | S57: UL 864 (10.ª ed.), FM, CE | T57: Lobbies y accesos (UL 864) | U57: 480 | X57: Capacidad y rendimiento mejorados | Y57: 0.085 | Z57: 0.298 | AA57: 24 | AB57: Protocolo Notifier (ONNX) | AC57: Centrales Notifier (protocolo ONNX/FlashScan) (red repetidora) | AD57: 0.085 | AE57: 0.298 | AF57: N/A | AG57: N/A | AH57: N/A | AI57: N/A | AJ57: N/A | AK57: N/A | AL57: N/A | AM57: N/A | AN57: N/A | AO57: N/A | AP57: 1.2 | AQ57: 1.7
B58: 54 | C58: Honeywell Fire | D58: Alta | E58: EE. UU. | F58: Terminal repetidora | G58: LCD2-160 | H58: Anunciador LCD 80 caracteres | I58: Anunciador remoto Notifier con controles | J58: Indicación de alarma/problema y supervisión | K58: Bus EIA-485 (ACS) | L58: Protocolo Notifier (ONNX) | M58: 24 VDC desde central | N58: 85 mA | O58: — | P58: 0 °C a +49 °C | Q58: 222 × 165 × 50 mm | R58: 700 g | S58: UL 864 (10.ª ed.), FM, CE | T58: Lobbies y accesos (UL 864) | U58: 700 | X58: Tope de gama — máxima especificación | Y58: 0.085 | Z58: 0.172 | AA58: 24 | AB58: Protocolo Notifier (ONNX) | AC58: Centrales Notifier (protocolo ONNX/FlashScan) (red repetidora) | AD58: 0.085 | AE58: 0.172 | AF58: N/A | AG58: N/A | AH58: N/A | AI58: N/A | AJ58: N/A | AK58: N/A | AL58: N/A | AM58: N/A | AN58: N/A | AO58: N/A | AP58: 1.2 | AQ58: 1.7
B59: 55 | C59: Honeywell Fire | D59: Alta | E59: EE. UU. | F59: Detector de ducto | G59: No disponible en portafolio | X59: Ductos bajo System Sensor InnovairFlex D4120 | Y59: N/A | Z59: N/A | AA59: N/A | AB59: N/A | AC59: N/A | AD59: N/A | AE59: N/A | AF59: N/A | AG59: N/A | AH59: N/A | AI59: N/A | AJ59: N/A | AK59: N/A | AL59: N/A | AM59: N/A | AN59: N/A | AO59: N/A | AP59: N/A | AQ59: N/A
B60: 56 | C60: Honeywell Fire | D60: Alta | E60: EE. UU. | F60: Aislador/base lazo | G60: ISO-X | H60: Básica | I60: Módulo aislador direccionable | J60: Separa cortos de lazo por sección | K60: Lazo Notifier | L60: Protocolo Notifier (ONNX) | M60: Lazo 24 VDC | N60: — | O60: — | P60: 0 °C a +49 °C | Q60: 65 × 45 × 18 mm | R60: 60 g | S60: UL 864 (10.ª ed.), FM, CE | T60: Protección del lazo (NFPA 72) | U60: 19 | X60: Variante económica de la gama | Y60: 0.00032116 | Z60: 0.002 | AA60: 24 | AB60: Protocolo Notifier (ONNX) | AC60: Centrales Centrales Notifier (protocolo ONNX/FlashScan) | AD60: N/A | AE60: N/A | AF60: N/A | AG60: N/A | AH60: N/A | AI60: N/A | AJ60: N/A | AK60: N/A | AL60: N/A | AM60: N/A | AN60: N/A | AO60: N/A | AP60: N/A | AQ60: N/A
B61: 57 | C61: Honeywell Fire | D61: Alta | E61: EE. UU. | F61: Aislador/base lazo | G61: B210LP-ISO | H61: Con aislador | I61: Módulo aislador direccionable | J61: Separa cortos de lazo por sección | K61: Lazo Notifier | L61: Protocolo Notifier (ONNX) | M61: Lazo 24 VDC | N61: — | O61: — | P61: 0 °C a +49 °C | Q61: 65 × 45 × 18 mm | R61: 60 g | S61: UL 864 (10.ª ed.), FM, CE | T61: Protección del lazo (NFPA 72) | U61: 25 | X61: Gama de entrada | Y61: 0.00035348 | Z61: 0.002 | AA61: 24 | AB61: Protocolo Notifier (ONNX) | AC61: Centrales Centrales Notifier (protocolo ONNX/FlashScan) | AD61: N/A | AE61: N/A | AF61: N/A | AG61: N/A | AH61: N/A | AI61: N/A | AJ61: N/A | AK61: N/A | AL61: N/A | AM61: N/A | AN61: N/A | AO61: N/A | AP61: N/A | AQ61: N/A
B62: 58 | C62: Honeywell Fire | D62: Alta | E62: EE. UU. | F62: Aislador/base lazo | G62: B224BI | H62: Aislador + LED | I62: Módulo aislador direccionable | J62: Separa cortos de lazo por sección | K62: Lazo Notifier | L62: Protocolo Notifier (ONNX) | M62: Lazo 24 VDC | N62: — | O62: — | P62: 0 °C a +49 °C | Q62: 65 × 45 × 18 mm | R62: 60 g | S62: UL 864 (10.ª ed.), FM, CE | T62: Protección del lazo (NFPA 72) | U62: 35 | X62: Instalar cada 25 dispositivos | Y62: 0.00039888 | Z62: 0.002 | AA62: 24 | AB62: Protocolo Notifier (ONNX) | AC62: Centrales Centrales Notifier (protocolo ONNX/FlashScan) | AD62: N/A | AE62: N/A | AF62: N/A | AG62: N/A | AH62: N/A | AI62: N/A | AJ62: N/A | AK62: N/A | AL62: N/A | AM62: N/A | AN62: N/A | AO62: N/A | AP62: N/A | AQ62: N/A
B63: 59 | C63: Honeywell Fire | D63: Alta | E63: EE. UU. | F63: Aislador/base lazo | G63: B710LP-ISO | H63: Programable | I63: Módulo aislador direccionable | J63: Separa cortos de lazo por sección | K63: Lazo Notifier | L63: Protocolo Notifier (ONNX) | M63: Lazo 24 VDC | N63: — | O63: — | P63: 0 °C a +49 °C | Q63: 65 × 45 × 18 mm | R63: 60 g | S63: UL 864 (10.ª ed.), FM, CE | T63: Protección del lazo (NFPA 72) | U63: 55 | X63: Capacidad y rendimiento mejorados | Y63: 0.00037688 | Z63: 0.002 | AA63: 24 | AB63: Protocolo Notifier (ONNX) | AC63: Centrales Centrales Notifier (protocolo ONNX/FlashScan) | AD63: N/A | AE63: N/A | AF63: N/A | AG63: N/A | AH63: N/A | AI63: N/A | AJ63: N/A | AK63: N/A | AL63: N/A | AM63: N/A | AN63: N/A | AO63: N/A | AP63: N/A | AQ63: N/A
B64: 60 | C64: Honeywell Fire | D64: Alta | E64: EE. UU. | F64: Aislador/base lazo | G64: ISO-X-Fault | H64: Programable + aislador | I64: Módulo aislador direccionable | J64: Separa cortos de lazo por sección | K64: Lazo Notifier | L64: Protocolo Notifier (ONNX) | M64: Lazo 24 VDC | N64: — | O64: — | P64: 0 °C a +49 °C | Q64: 65 × 45 × 18 mm | R64: 60 g | S64: UL 864 (10.ª ed.), FM, CE | T64: Protección del lazo (NFPA 72) | U64: 80 | X64: Tope de gama — máxima especificación | Y64: 0.00040856 | Z64: 0.002 | AA64: 24 | AB64: Protocolo Notifier (ONNX) | AC64: Centrales Centrales Notifier (protocolo ONNX/FlashScan) | AD64: N/A | AE64: N/A | AF64: N/A | AG64: N/A | AH64: N/A | AI64: N/A | AJ64: N/A | AK64: N/A | AL64: N/A | AM64: N/A | AN64: N/A | AO64: N/A | AP64: N/A | AQ64: N/A
B65: 61 | C65: Siemens | D65: Alta | E65: Alemania | F65: Panel direccionable | G65: FC721 | H65: Hasta 4 lazos · 252 direcciones | I65: Central Cerberus PRO compacta enlazable | J65: FireMIND, autodiagnóstico integral | K65: Ethernet + SNMP + FW204/Wifi | L65: Protocolo Cerberus (FDnet) | M65: 120/240 VAC · baterías 12 V | N65: 450 mA en reposo | O65: — | P65: 0 °C a +50 °C | Q65: 420 × 320 × 120 mm | R65: 11 kg | S65: EN 54-2/4, VdS, UL 864 | T65: Edificios medianos (EN 54) | U65: 725 | X65: Variante económica de la gama | Y65: 0.45 | Z65: 3.308 | AA65: 24 | AB65: Protocolo Cerberus (FDnet) | AC65: Central maestra — Cerberus PRO / Sinteso (C-NET) | AD65: 0.45 | AE65: 3.308 | AF65: 8 | AG65: N/A | AH65: 4 | AI65: 252 | AJ65: N/A | AK65: N/A | AL65: N/A | AM65: N/A | AN65: N/A | AO65: N/A | AP65: N/A | AQ65: N/A
B66: 62 | C66: Siemens | D66: Alta | E66: Alemania | F66: Panel direccionable | G66: FC722 | H66: Hasta 4 lazos · 252 direcciones | I66: Central Cerberus PRO compacta enlazable | J66: FireMIND, autodiagnóstico integral | K66: Ethernet + SNMP + FW204/Wifi | L66: Protocolo Cerberus (FDnet) | M66: 120/240 VAC · baterías 12 V | N66: 450 mA en reposo | O66: — | P66: 0 °C a +50 °C | Q66: 420 × 320 × 120 mm | R66: 11 kg | S66: EN 54-2/4, VdS, UL 864 | T66: Edificios medianos (EN 54) | U66: 1085 | X66: Gama de entrada | Y66: 0.45 | Z66: 1.298 | AA66: 24 | AB66: Protocolo Cerberus (FDnet) | AC66: Central maestra — Cerberus PRO / Sinteso (C-NET) | AD66: 0.45 | AE66: 1.298 | AF66: 5.25 | AG66: N/A | AH66: 4 | AI66: 252 | AJ66: N/A | AK66: N/A | AL66: N/A | AM66: N/A | AN66: N/A | AO66: N/A | AP66: N/A | AQ66: N/A
B67: 63 | C67: Siemens | D67: Alta | E67: Alemania | F67: Panel direccionable | G67: FC723 | H67: Hasta 4 lazos · 252 direcciones | I67: Central Cerberus PRO compacta enlazable | J67: FireMIND, autodiagnóstico integral | K67: Ethernet + SNMP + FW204/Wifi | L67: Protocolo Cerberus (FDnet) | M67: 120/240 VAC · baterías 12 V | N67: 450 mA en reposo | O67: — | P67: 0 °C a +50 °C | Q67: 420 × 320 × 120 mm | R67: 11 kg | S67: EN 54-2/4, VdS, UL 864 | T67: Edificios medianos (EN 54) | U67: 1450 | X67: Generación C-NET; FC721 compacta 1 lazo, FC726 modular hasta 28 lazos | Y67: 0.45 | Z67: 1.914 | AA67: 24 | AB67: Protocolo Cerberus (FDnet) | AC67: Central maestra — Cerberus PRO / Sinteso (C-NET) | AD67: 0.45 | AE67: 1.914 | AF67: 8 | AG67: N/A | AH67: 4 | AI67: 252 | AJ67: N/A | AK67: N/A | AL67: N/A | AM67: N/A | AN67: N/A | AO67: N/A | AP67: N/A | AQ67: N/A
B68: 64 | C68: Siemens | D68: Alta | E68: Alemania | F68: Panel direccionable | G68: FC724 | H68: Hasta 4 lazos · 252 direcciones | I68: Central Cerberus PRO compacta enlazable | J68: FireMIND, autodiagnóstico integral | K68: Ethernet + SNMP + FW204/Wifi | L68: Protocolo Cerberus (FDnet) | M68: 120/240 VAC · baterías 12 V | N68: 450 mA en reposo | O68: — | P68: 0 °C a +50 °C | Q68: 420 × 320 × 120 mm | R68: 11 kg | S68: EN 54-2/4, VdS, UL 864 | T68: Edificios medianos (EN 54) | U68: 2175 | X68: Capacidad y rendimiento mejorados | Y68: 0.45 | Z68: 1.766 | AA68: 24 | AB68: Protocolo Cerberus (FDnet) | AC68: Central maestra — Cerberus PRO / Sinteso (C-NET) | AD68: 0.45 | AE68: 1.766 | AF68: 8 | AG68: N/A | AH68: 4 | AI68: 252 | AJ68: N/A | AK68: N/A | AL68: N/A | AM68: N/A | AN68: N/A | AO68: N/A | AP68: N/A | AQ68: N/A
B69: 65 | C69: Siemens | D69: Alta | E69: Alemania | F69: Panel direccionable | G69: FC726 | H69: Hasta 4 lazos · 252 direcciones | I69: Central Cerberus PRO compacta enlazable | J69: FireMIND, autodiagnóstico integral | K69: Ethernet + SNMP + FW204/Wifi | L69: Protocolo Cerberus (FDnet) | M69: 120/240 VAC · baterías 12 V | N69: 450 mA en reposo | O69: — | P69: 0 °C a +50 °C | Q69: 420 × 320 × 120 mm | R69: 11 kg | S69: EN 54-2/4, VdS, UL 864 | T69: Edificios medianos (EN 54) | U69: 3190 | X69: Tope de gama — máxima especificación | Y69: 0.45 | Z69: 1.473 | AA69: 24 | AB69: Protocolo Cerberus (FDnet) | AC69: Central maestra — Cerberus PRO / Sinteso (C-NET) | AD69: 0.45 | AE69: 1.473 | AF69: 8 | AG69: N/A | AH69: 4 | AI69: 252 | AJ69: N/A | AK69: N/A | AL69: N/A | AM69: N/A | AN69: N/A | AO69: N/A | AP69: N/A | AQ69: N/A
B70: 66 | C70: Siemens | D70: Alta | E70: Alemania | F70: Panel convencional | G70: No disponible en portafolio | X70: Siemens se enfoca en direccionable Cerberus PRO (FC721-FC726); convencional bajo otras marcas | Y70: N/A | Z70: N/A | AA70: N/A | AB70: N/A | AC70: N/A | AD70: N/A | AE70: N/A | AF70: N/A | AG70: N/A | AH70: N/A | AI70: N/A | AJ70: N/A | AK70: N/A | AL70: N/A | AM70: N/A | AN70: N/A | AO70: N/A | AP70: N/A | AQ70: N/A
B71: 67 | C71: Siemens | D71: Alta | E71: Alemania | F71: Humo convencional | G71: DH912 | H71: Área 60 m² | I71: Óptico fotoeléctrico convencional | J71: Modo estándar/vapores, LED de alarma | K71: Zona 24 V convencional | L71: Protocolo Cerberus (FDnet) | M71: 24 VDC de central | N71: — | O71: — | P71: 0 °C a +50 °C | Q71: Ø 100 × 40 mm + base | R71: 145 g | S71: EN 54-2/4, VdS, UL 864 | T71: Interior general | U71: 25 | X71: Variante económica de la gama | Y71: 4.103e-05 | Z71: 0.041 | AA71: 24 | AB71: Protocolo Cerberus (FDnet) | AC71: Cualquier central convencional 24 V (circuito ZA) | AD71: N/A | AE71: N/A | AF71: N/A | AG71: N/A | AH71: N/A | AI71: N/A | AJ71: 60 | AK71: N/A | AL71: N/A | AM71: N/A | AN71: Volumétrica cilíndrica (montaje techo) | AO71: N/A | AP71: 2.5 | AQ71: 6
B72: 68 | C72: Siemens | D72: Alta | E72: Alemania | F72: Humo convencional | G72: DH913 | H72: Área 80 m² | I72: Óptico fotoeléctrico convencional | J72: Modo estándar/vapores, LED de alarma | K72: Zona 24 V convencional | L72: Protocolo Cerberus (FDnet) | M72: 24 VDC de central | N72: — | O72: — | P72: 0 °C a +50 °C | Q72: Ø 100 × 40 mm + base | R72: 145 g | S72: EN 54-2/4, VdS, UL 864 | T72: Interior general | U72: 40 | X72: Gama de entrada | Y72: 3.346e-05 | Z72: 0.033 | AA72: 24 | AB72: Protocolo Cerberus (FDnet) | AC72: Cualquier central convencional 24 V (circuito ZA) | AD72: N/A | AE72: N/A | AF72: N/A | AG72: N/A | AH72: N/A | AI72: N/A | AJ72: 80 | AK72: N/A | AL72: N/A | AM72: N/A | AN72: Volumétrica cilíndrica (montaje techo) | AO72: N/A | AP72: 2.5 | AQ72: 6
B73: 69 | C73: Siemens | D73: Alta | E73: Alemania | F73: Humo convencional | G73: OH921 | H73: Área 100 m² | I73: Óptico fotoeléctrico convencional | J73: Modo estándar/vapores, LED de alarma | K73: Zona 24 V convencional | L73: Protocolo Cerberus (FDnet) | M73: 24 VDC de central | N73: — | O73: — | P73: 0 °C a +50 °C | Q73: Ø 100 × 40 mm + base | R73: 145 g | S73: EN 54-2/4, VdS, UL 864 | T73: Interior general | U73: 55 | X73: Base DB-1190 incluida | Y73: 5.852e-05 | Z73: 0.059 | AA73: 24 | AB73: Protocolo Cerberus (FDnet) | AC73: Cualquier central convencional 24 V (circuito ZA) | AD73: N/A | AE73: N/A | AF73: N/A | AG73: N/A | AH73: N/A | AI73: N/A | AJ73: 100 | AK73: N/A | AL73: N/A | AM73: N/A | AN73: Volumétrica cilíndrica (montaje techo) | AO73: N/A | AP73: 2.5 | AQ73: 6
B74: 70 | C74: Siemens | D74: Alta | E74: Alemania | F74: Humo convencional | G74: DH991 | H74: Área 100 m² + modo drifter | I74: Óptico fotoeléctrico convencional | J74: Modo estándar/vapores, LED de alarma | K74: Zona 24 V convencional | L74: Protocolo Cerberus (FDnet) | M74: 24 VDC de central | N74: — | O74: — | P74: 0 °C a +50 °C | Q74: Ø 100 × 40 mm + base | R74: 145 g | S74: EN 54-2/4, VdS, UL 864 | T74: Interior general | U74: 85 | X74: Capacidad y rendimiento mejorados | Y74: 4.837e-05 | Z74: 0.048 | AA74: 24 | AB74: Protocolo Cerberus (FDnet) | AC74: Cualquier central convencional 24 V (circuito ZA) | AD74: N/A | AE74: N/A | AF74: N/A | AG74: N/A | AH74: N/A | AI74: N/A | AJ74: 100 | AK74: N/A | AL74: N/A | AM74: N/A | AN74: Volumétrica cilíndrica (montaje techo) | AO74: N/A | AP74: 2.5 | AQ74: 6
B75: 71 | C75: Siemens | D75: Alta | E75: Alemania | F75: Humo convencional | G75: ORP-73 | H75: Área 120 m² | I75: Óptico fotoeléctrico convencional | J75: Modo estándar/vapores, LED de alarma | K75: Zona 24 V convencional | L75: Protocolo Cerberus (FDnet) | M75: 24 VDC de central | N75: — | O75: — | P75: 0 °C a +50 °C | Q75: Ø 100 × 40 mm + base | R75: 145 g | S75: EN 54-2/4, VdS, UL 864 | T75: Interior general | U75: 125 | X75: Tope de gama — máxima especificación | Y75: 5.248e-05 | Z75: 0.052 | AA75: 24 | AB75: Protocolo Cerberus (FDnet) | AC75: Cualquier central convencional 24 V (circuito ZA) | AD75: N/A | AE75: N/A | AF75: N/A | AG75: N/A | AH75: N/A | AI75: N/A | AJ75: 120 | AK75: N/A | AL75: N/A | AM75: N/A | AN75: Volumétrica cilíndrica (montaje techo) | AO75: N/A | AP75: 2.5 | AQ75: 6
B76: 72 | C76: Siemens | D76: Alta | E76: Alemania | F76: Humo direccionable | G76: FDOOT241 (60 m²) | H76: Área 60 m² | I76: Óptico fotoeléctrico direccionable (FD18) | J76: Sensibilidad por software, deriva compensada | K76: Lazo C-Net / FDnet | L76: Protocolo Cerberus (FDnet) | M76: Lazo 24 VDC | N76: — | O76: — | P76: 0 °C a +50 °C | Q76: Ø 100 × 42 mm + base | R76: 150 g | S76: EN 54-2/4, VdS, UL 864 | T76: Interior general (EN 54-7) | U76: 40 | X76: Variante económica de la gama | Y76: 8.263e-05 | Z76: 0.003 | AA76: 24 | AB76: Protocolo Cerberus (FDnet) | AC76: Cerberus PRO / Sinteso (C-NET) | AD76: N/A | AE76: N/A | AF76: N/A | AG76: N/A | AH76: N/A | AI76: N/A | AJ76: 60 | AK76: N/A | AL76: N/A | AM76: N/A | AN76: Volumétrica cilíndrica (montaje techo) | AO76: N/A | AP76: 2.5 | AQ76: 6
B77: 73 | C77: Siemens | D77: Alta | E77: Alemania | F77: Humo direccionable | G77: FDOOT241 (80 m²) | H77: Área 80 m² | I77: Óptico fotoeléctrico direccionable (FD18) | J77: Sensibilidad por software, deriva compensada | K77: Lazo C-Net / FDnet | L77: Protocolo Cerberus (FDnet) | M77: Lazo 24 VDC | N77: — | O77: — | P77: 0 °C a +50 °C | Q77: Ø 100 × 42 mm + base | R77: 150 g | S77: EN 54-2/4, VdS, UL 864 | T77: Interior general (EN 54-7) | U77: 60 | X77: Gama de entrada | Y77: 0.00010283 | Z77: 0.004 | AA77: 24 | AB77: Protocolo Cerberus (FDnet) | AC77: Cerberus PRO / Sinteso (C-NET) | AD77: N/A | AE77: N/A | AF77: N/A | AG77: N/A | AH77: N/A | AI77: N/A | AJ77: 80 | AK77: N/A | AL77: N/A | AM77: N/A | AN77: Volumétrica cilíndrica (montaje techo) | AO77: N/A | AP77: 2.5 | AQ77: 6
B78: 74 | C78: Siemens | D78: Alta | E78: Alemania | F78: Humo direccionable | G78: FDOOT241 | H78: Área 100 m² | I78: Óptico fotoeléctrico direccionable (FD18) | J78: Sensibilidad por software, deriva compensada | K78: Lazo C-Net / FDnet | L78: Protocolo Cerberus (FDnet) | M78: Lazo 24 VDC | N78: — | O78: — | P78: 0 °C a +50 °C | Q78: Ø 100 × 42 mm + base | R78: 150 g | S78: EN 54-2/4, VdS, UL 864 | T78: Interior general (EN 54-7) | U78: 80 | X78: Base FDMM201-B1; familia FD18 Cerberus PRO | Y78: 8.654e-05 | Z78: 0.003 | AA78: 24 | AB78: Protocolo Cerberus (FDnet) | AC78: Cerberus PRO / Sinteso (C-NET) | AD78: N/A | AE78: N/A | AF78: N/A | AG78: N/A | AH78: N/A | AI78: N/A | AJ78: 100 | AK78: N/A | AL78: N/A | AM78: N/A | AN78: Volumétrica cilíndrica (montaje techo) | AO78: N/A | AP78: 2.5 | AQ78: 6
B79: 75 | C79: Siemens | D79: Alta | E79: Alemania | F79: Humo direccionable | G79: FDOOTC241 | H79: Área 100 m² + direccionamiento | I79: Óptico fotoeléctrico direccionable (FD18) | J79: Sensibilidad por software, deriva compensada | K79: Lazo C-Net / FDnet | L79: Protocolo Cerberus (FDnet) | M79: Lazo 24 VDC | N79: — | O79: — | P79: 0 °C a +50 °C | Q79: Ø 100 × 42 mm + base | R79: 150 g | S79: EN 54-2/4, VdS, UL 864 | T79: Interior general (EN 54-7) | U79: 120 | X79: Capacidad y rendimiento mejorados | Y79: 9.641e-05 | Z79: 0.004 | AA79: 24 | AB79: Protocolo Cerberus (FDnet) | AC79: Cerberus PRO / Sinteso (C-NET) | AD79: N/A | AE79: N/A | AF79: N/A | AG79: N/A | AH79: N/A | AI79: N/A | AJ79: 100 | AK79: N/A | AL79: N/A | AM79: N/A | AN79: Volumétrica cilíndrica (montaje techo) | AO79: N/A | AP79: 2.5 | AQ79: 6
B80: 76 | C80: Siemens | D80: Alta | E80: Alemania | F80: Humo direccionable | G80: FDOOTC241 (aislador integrado) | H80: Área 120 m² | I80: Óptico fotoeléctrico direccionable (FD18) | J80: Sensibilidad por software, deriva compensada | K80: Lazo C-Net / FDnet | L80: Protocolo Cerberus (FDnet) | M80: Lazo 24 VDC | N80: — | O80: — | P80: 0 °C a +50 °C | Q80: Ø 100 × 42 mm + base | R80: 150 g | S80: EN 54-2/4, VdS, UL 864 | T80: Interior general (EN 54-7) | U80: 180 | X80: Tope de gama — máxima especificación | Y80: 9.181e-05 | Z80: 0.004 | AA80: 24 | AB80: Protocolo Cerberus (FDnet) | AC80: Cerberus PRO / Sinteso (C-NET) | AD80: N/A | AE80: N/A | AF80: N/A | AG80: N/A | AH80: N/A | AI80: N/A | AJ80: 120 | AK80: N/A | AL80: N/A | AM80: N/A | AN80: Volumétrica cilíndrica (montaje techo) | AO80: N/A | AP80: 2.5 | AQ80: 6
